Workbook
Name Burn: [1]Projections!$E$63
Name Conversion1: [1]Projections!$D$18
Name Conversion2: [1]Projections!$D$19
Name Conversion3: [1]Projections!$D$20
Name CostPerUser: [1]Projections!$D$55
Name Price1: [1]Projections!$D$25
Name Price2: [1]Projections!$D$26
Name Price3: [1]Projections!$D$27
Name PricePSF: [1]Projections!$D$54
Name SFpp: [1]Projections!$D$53

Sheet ChargeHelp Example
A1: ChargerHelp, Inc.
A2: Profit and Loss
A3: January - June, 2023
B5: Jan 2023 | C5: Feb 2023 | D5: Mar 2023 | E5: Apr 2023 | F5: May 2023 | G5: Jun 2023 | H5: Total
A6: Income
A7: 40000 Technician Maintenance & Repairs Income | B7: =54256.58 -> 54256.58 | C7: =31504.6 -> 31504.6 | D7: =29168.4 -> 29168.4 | E7: =85981.73 -> 85981.73 | F7: =79117.05 -> 79117.05 | G7: =107813.22 -> 107813.22 | H7: =(((((B7)+(C7))+(D7))+(E7))+(F7))+(G7) -> 387841.58
A8: 40100 Campaigns | B8: =37145 -> 37145 | C8: =16910 -> 16910 | D8: =18905 -> 18905 | E8: =10355 -> 10355 | H8: =(((((B8)+(C8))+(D8))+(E8))+(F8))+(G8) -> 83315
A9: Total 40000 Technician Maintenance & Repairs Income | B9: =(B7)+(B8) -> 91401.58 | C9: =(C7)+(C8) -> 48414.6 | D9: =(D7)+(D8) -> 48073.4 | E9: =(E7)+(E8) -> 96336.73 | F9: =(F7)+(F8) -> 79117.05 | G9: =(G7)+(G8) -> 107813.22 | H9: =(((((B9)+(C9))+(D9))+(E9))+(F9))+(G9) -> 471156.58
A10: 44000 Workforce Development & Training Income | B10: =25000 -> 25000 | C10: =50000 -> 50000 | D10: =75000 -> 75000 | E10: =74000 -> 74000 | F10: =25000 -> 25000 | G10: =100000 -> 100000 | H10: =(((((B10)+(C10))+(D10))+(E10))+(F10))+(G10) -> 349000
A11: 45000 Reliability as a Service (RaaS) Income | B11: =37990 -> 37990 | C11: =39830 -> 39830 | D11: =40430 -> 40430 | E11: =40430 -> 40430 | F11: =42870 -> 42870 | G11: =42870 -> 42870 | H11: =(((((B11)+(C11))+(D11))+(E11))+(F11))+(G11) -> 244420
A12: 46000 Warranty Revenue | F12: =0 -> 0 | H12: =(((((B12)+(C12))+(D12))+(E12))+(F12))+(G12) -> 0
A13: Total Income | B13: =(((B9)+(B10))+(B11))+(B12) -> 154391.58 | C13: =(((C9)+(C10))+(C11))+(C12) -> 138244.6 | D13: =(((D9)+(D10))+(D11))+(D12) -> 163503.4 | E13: =(((E9)+(E10))+(E11))+(E12) -> 210766.73 | F13: =(((F9)+(F10))+(F11))+(F12) -> 146987.05 | G13: =(((G9)+(G10))+(G11))+(G12) -> 250683.22 | H13: =(((((B13)+(C13))+(D13))+(E13))+(F13))+(G13) -> 1064576.6
A14: Cost of Goods Sold
A15: 50000 Technician Costs | B15: =B16/B25 -> 0.66346111 | C15: =C16/C25 -> 0.67351763 | D15: =D16/D25 -> 0.67354879 | E15: =E16/E25 -> 0.59599531 | F15: =F16/F25 -> 0.61282405 | G15: =G16/G25 -> 0.6872657 | H15: =H16/H25 -> 0.65265665
A16: 50010 Technician Salaries | B16: =74743.01 -> 74743.01 | C16: =69057.57 -> 69057.57 | D16: =86660.73 -> 86660.73 | E16: =66940.2 -> 66940.2 | F16: =70956.27 -> 70956.27 | G16: =97937.34 -> 97937.34 | H16: =(((((B16)+(C16))+(D16))+(E16))+(F16))+(G16) -> 466295.12
A17: 50020 Technician Taxes | B17: =8584.26 -> 8584.26 | C17: =5466.83 -> 5466.83 | D17: =6757.23 -> 6757.23 | E17: =5796.89 -> 5796.89 | F17: =6167.03 -> 6167.03 | G17: =8370.66 -> 8370.66 | H17: =(((((B17)+(C17))+(D17))+(E17))+(F17))+(G17) -> 41142.9
A18: 50030 Technician Benefits | B18: =9749.53 -> 9749.53 | C18: =8550 -> 8550 | D18: =10607.64 -> 10607.64 | E18: =11505.71 -> 11505.71 | F18: =14358.17 -> 14358.17 | G18: =14811.2 -> 14811.2 | H18: =(((((B18)+(C18))+(D18))+(E18))+(F18))+(G18) -> 69582.25
A19: 50040 Technician Tool Costs | B19: =7189.3 -> 7189.3 | C19: =12614.87 -> 12614.87 | D19: =6631.86 -> 6631.86 | E19: =16116.88 -> 16116.88 | F19: =10941.52 -> 10941.52 | G19: =8303.1 -> 8303.1 | H19: =(((((B19)+(C19))+(D19))+(E19))+(F19))+(G19) -> 61797.53
A20: 50050 Technician Parking Charges | B20: =10 -> 10 | C20: =40.86 -> 40.86 | H20: =(((((B20)+(C20))+(D20))+(E20))+(F20))+(G20) -> 50.86
A21: 50060 Technician Toll Fees | B21: =425 -> 425 | C21: =291.57 -> 291.57 | D21: =830.15 -> 830.15 | E21: =435 -> 435 | F21: =345.53 -> 345.53 | G21: =481.2 -> 481.2 | H21: =(((((B21)+(C21))+(D21))+(E21))+(F21))+(G21) -> 2808.45
A22: 50070 Technician - Travel Expense | B22: =11754.44 -> 11754.44 | C22: =6510.31 -> 6510.31 | D22: =10156.21 -> 10156.21 | E22: =9853.05 -> 9853.05 | F22: =8831.58 -> 8831.58 | G22: =9507.07 -> 9507.07 | H22: =(((((B22)+(C22))+(D22))+(E22))+(F22))+(G22) -> 56612.66
A23: 50085 Technician EV costs | D23: =7018.39 -> 7018.39 | E23: =1668.33 -> 1668.33 | F23: =4185 -> 4185 | G23: =3091.62 -> 3091.62 | H23: =(((((B23)+(C23))+(D23))+(E23))+(F23))+(G23) -> 15963.34
A24: 50095 Technician - Per Diem | B24: =200 -> 200 | H24: =(((((B24)+(C24))+(D24))+(E24))+(F24))+(G24) -> 200
A25: Total 50000 Technician Costs | B25: =(((((((((B15)+(B16))+(B17))+(B18))+(B19))+(B20))+(B21))+(B22))+(B23))+(B24) -> 112656.2 | C25: =(((((((((C15)+(C16))+(C17))+(C18))+(C19))+(C20))+(C21))+(C22))+(C23))+(C24) -> 102532.68 | D25: =(((((((((D15)+(D16))+(D17))+(D18))+(D19))+(D20))+(D21))+(D22))+(D23))+(D24) -> 128662.88 | E25: =(((((((((E15)+(E16))+(E17))+(E18))+(E19))+(E20))+(E21))+(E22))+(E23))+(E24) -> 112316.66 | F25: =(((((((((F15)+(F16))+(F17))+(F18))+(F19))+(F20))+(F21))+(F22))+(F23))+(F24) -> 115785.71 | G25: =(((((((((G15)+(G16))+(G17))+(G18))+(G19))+(G20))+(G21))+(G22))+(G23))+(G24) -> 142502.88 | H25: =(((((B25)+(C25))+(D25))+(E25))+(F25))+(G25) -> 714457.02
A26: 53000 Contractor Costs | C26: =2278.5 -> 2278.5 | D26: =5628.58 -> 5628.58 | H26: =(((((B26)+(C26))+(D26))+(E26))+(F26))+(G26) -> 7907.08
A27: 53200 Contractor Costs | B27: =43783.5 -> 43783.5 | C27: =39756.96 -> 39756.96 | D27: =54377.18 -> 54377.18 | E27: =66233.27 -> 66233.27 | F27: =66098.32 -> 66098.32 | G27: =60538.27 -> 60538.27 | H27: =(((((B27)+(C27))+(D27))+(E27))+(F27))+(G27) -> 330787.5
A28: Total 53000 Contractor Costs | B28: =(B26)+(B27) -> 43783.5 | C28: =(C26)+(C27) -> 42035.46 | D28: =(D26)+(D27) -> 60005.76 | E28: =(E26)+(E27) -> 66233.27 | F28: =(F26)+(F27) -> 66098.32 | G28: =(G26)+(G27) -> 60538.27 | H28: =(((((B28)+(C28))+(D28))+(E28))+(F28))+(G28) -> 338694.58
A29: 55000 Workforce Development Training Costs | H29: =(((((B29)+(C29))+(D29))+(E29))+(F29))+(G29) -> 0
A30: 55100 Training Personnel | B30: =6000 -> 6000 | C30: =6000 -> 6000 | D30: =9000 -> 9000 | E30: =11100 -> 11100 | F30: =6000 -> 6000 | G30: =13724.51 -> 13724.51 | H30: =(((((B30)+(C30))+(D30))+(E30))+(F30))+(G30) -> 51824.51
A31: 55120 Training Personnel Taxes | B31: =831.31 -> 831.31 | C31: =512.99 -> 512.99 | D31: =659.8 -> 659.8 | E31: =616.01 -> 616.01 | F31: =616.03 -> 616.03 | G31: =484.04 -> 484.04 | H31: =(((((B31)+(C31))+(D31))+(E31))+(F31))+(G31) -> 3720.18
A32: 55130 Training Personnel Benefits | B32: =566.64 -> 566.64 | C32: =1067.8 -> 1067.8 | D32: =1601.7 -> 1601.7 | E32: =1536.33 -> 1536.33 | F32: =1547.67 -> 1547.67 | G32: =1216.03 -> 1216.03 | H32: =(((((B32)+(C32))+(D32))+(E32))+(F32))+(G32) -> 7536.17
A33: 55200 Other Training Costs | B33: =1500 -> 1500 | C33: =3000 -> 3000 | D33: =3000 -> 3000 | H33: =(((((B33)+(C33))+(D33))+(E33))+(F33))+(G33) -> 7500
A34: Total 55000 Workforce Development Training Costs | B34: =((((B29)+(B30))+(B31))+(B32))+(B33) -> 8897.95 | C34: =((((C29)+(C30))+(C31))+(C32))+(C33) -> 10580.79 | D34: =((((D29)+(D30))+(D31))+(D32))+(D33) -> 14261.5 | E34: =((((E29)+(E30))+(E31))+(E32))+(E33) -> 13252.34 | F34: =((((F29)+(F30))+(F31))+(F32))+(F33) -> 8163.7 | G34: =((((G29)+(G30))+(G31))+(G32))+(G33) -> 15424.58 | H34: =(((((B34)+(C34))+(D34))+(E34))+(F34))+(G34) -> 70580.86
A35: Inventory Shrinkage | G35: =0 -> 0 | H35: =(((((B35)+(C35))+(D35))+(E35))+(F35))+(G35) -> 0
A36: Total Cost of Goods Sold | B36: =(((B25)+(B28))+(B34))+(B35) -> 165337.65 | C36: =(((C25)+(C28))+(C34))+(C35) -> 155148.93 | D36: =(((D25)+(D28))+(D34))+(D35) -> 202930.14 | E36: =(((E25)+(E28))+(E34))+(E35) -> 191802.27 | F36: =(((F25)+(F28))+(F34))+(F35) -> 190047.73 | G36: =(((G25)+(G28))+(G34))+(G35) -> 218465.73 | H36: =(((((B36)+(C36))+(D36))+(E36))+(F36))+(G36) -> 1123732.5
A37: Gross Profit | B37: =(B13)-(B36) -> -10946.073 | C37: =(C13)-(C36) -> -16904.334 | D37: =(D13)-(D36) -> -39426.744 | E37: =(E13)-(E36) -> 18964.464 | F37: =(F13)-(F36) -> -43060.683 | G37: =(G13)-(G36) -> 32217.493 | H37: =(((((B37)+(C37))+(D37))+(E37))+(F37))+(G37) -> -59155.877
A38: Expenses
A39: 60100 Personnel Costs | H39: =(((((B39)+(C39))+(D39))+(E39))+(F39))+(G39) -> 0
A40: 60110 Salaries & Wages | B40: =105551.35 -> 105551.35 | C40: =95144.78 -> 95144.78 | D40: =122680.5 -> 122680.5 | E40: =123679.89 -> 123679.89 | F40: =180764.76 -> 180764.76 | G40: =252938.89 -> 252938.89 | H40: =(((((B40)+(C40))+(D40))+(E40))+(F40))+(G40) -> 880760.17
A41: 60120 Payroll Taxes | B41: =10268.21 -> 10268.21 | C41: =7172.29 -> 7172.29 | D41: =9854.82 -> 9854.82 | E41: =9706.51 -> 9706.51 | F41: =15858.82 -> 15858.82 | G41: =20704.99 -> 20704.99 | H41: =(((((B41)+(C41))+(D41))+(E41))+(F41))+(G41) -> 73565.64
A42: 60140 Employee Benefits | B42: =7833.85 -> 7833.85 | C42: =6263.99 -> 6263.99 | D42: =8189.87 -> 8189.87 | E42: =12580.9 -> 12580.9 | F42: =16005.96 -> 16005.96 | G42: =16885.21 -> 16885.21 | H42: =(((((B42)+(C42))+(D42))+(E42))+(F42))+(G42) -> 67759.78
A43: Total 60100 Personnel Costs | B43: =(((B39)+(B40))+(B41))+(B42) -> 123653.41 | C43: =(((C39)+(C40))+(C41))+(C42) -> 108581.06 | D43: =(((D39)+(D40))+(D41))+(D42) -> 140725.19 | E43: =(((E39)+(E40))+(E41))+(E42) -> 145967.3 | F43: =(((F39)+(F40))+(F41))+(F42) -> 212629.54 | G43: =(((G39)+(G40))+(G41))+(G42) -> 290529.09 | H43: =(((((B43)+(C43))+(D43))+(E43))+(F43))+(G43) -> 1022085.6
A44: 61000 Professional Fees | H44: =(((((B44)+(C44))+(D44))+(E44))+(F44))+(G44) -> 0
A45: 61010 Finance and Accounting Fees | B45: =9084.45 -> 9084.45 | C45: =13593.55 -> 13593.55 | D45: =20406.2 -> 20406.2 | E45: =19448 -> 19448 | F45: =21861.35 -> 21861.35 | G45: =23312.1 -> 23312.1 | H45: =(((((B45)+(C45))+(D45))+(E45))+(F45))+(G45) -> 107705.65
A46: 61020 Legal Fees | B46: =13873 -> 13873 | C46: =8090 -> 8090 | D46: =8858.5 -> 8858.5 | E46: =9828.5 -> 9828.5 | F46: =31606.31 -> 31606.31 | G46: =10749 -> 10749 | H46: =(((((B46)+(C46))+(D46))+(E46))+(F46))+(G46) -> 83005.31
A47: 61030 Consulting Fees - Grant Writing | B47: =3800 -> 3800 | C47: =3800 -> 3800 | D47: =3800 -> 3800 | E47: =8000 -> 8000 | F47: =8000 -> 8000 | H47: =(((((B47)+(C47))+(D47))+(E47))+(F47))+(G47) -> 27400
A48: 61050 Consulting Fees - Technology | B48: =54500 -> 54500 | C48: =54100 -> 54100 | D48: =52620 -> 52620 | E48: =45398 -> 45398 | F48: =61139.7 -> 61139.7 | G48: =90105.2 -> 90105.2 | H48: =(((((B48)+(C48))+(D48))+(E48))+(F48))+(G48) -> 357862.9
A49: 61055 Consulting Fees - Gov't Relations | B49: =9000 -> 9000 | C49: =9200 -> 9200 | D49: =9000 -> 9000 | E49: =26000 -> 26000 | F49: =23500 -> 23500 | G49: =26000 -> 26000 | H49: =(((((B49)+(C49))+(D49))+(E49))+(F49))+(G49) -> 102700
A50: 61060 Professional Fees - Recruitment | D50: =5760 -> 5760 | E50: =2288.4 -> 2288.4 | F50: =67260 -> 67260 | G50: =70500 -> 70500 | H50: =(((((B50)+(C50))+(D50))+(E50))+(F50))+(G50) -> 145808.4
A51: 61080 Other Consulting Fees | B51: =31512.46 -> 31512.46 | C51: =4755.06 -> 4755.06 | D51: =19715.28 -> 19715.28 | E51: =10523.95 -> 10523.95 | F51: =15631.23 -> 15631.23 | G51: =16948.63 -> 16948.63 | H51: =(((((B51)+(C51))+(D51))+(E51))+(F51))+(G51) -> 99086.61
A52: Total 61000 Professional Fees | B52: =(((((((B44)+(B45))+(B46))+(B47))+(B48))+(B49))+(B50))+(B51) -> 121769.91 | C52: =(((((((C44)+(C45))+(C46))+(C47))+(C48))+(C49))+(C50))+(C51) -> 93538.61 | D52: =(((((((D44)+(D45))+(D46))+(D47))+(D48))+(D49))+(D50))+(D51) -> 120159.98 | E52: =(((((((E44)+(E45))+(E46))+(E47))+(E48))+(E49))+(E50))+(E51) -> 121486.85 | F52: =(((((((F44)+(F45))+(F46))+(F47))+(F48))+(F49))+(F50))+(F51) -> 228998.59 | G52: =(((((((G44)+(G45))+(G46))+(G47))+(G48))+(G49))+(G50))+(G51) -> 237614.93 | H52: =(((((B52)+(C52))+(D52))+(E52))+(F52))+(G52) -> 923568.87
A53: 62000 Marketing & Advertising | H53: =(((((B53)+(C53))+(D53))+(E53))+(F53))+(G53) -> 0
A54: 62010 Advertising/Promotional | B54: =3502 -> 3502 | C54: =2920 -> 2920 | D54: =22468.84 -> 22468.84 | E54: =22920 -> 22920 | F54: =12480.38 -> 12480.38 | G54: =139.4 -> 139.4 | H54: =(((((B54)+(C54))+(D54))+(E54))+(F54))+(G54) -> 64430.62
A55: 62020 Events/Sponsorship | C55: =2873.9 -> 2873.9 | D55: =6871.09 -> 6871.09 | E55: =3420 -> 3420 | F55: =5834.85 -> 5834.85 | H55: =(((((B55)+(C55))+(D55))+(E55))+(F55))+(G55) -> 18999.84
A56: Total 62000 Marketing & Advertising | B56: =((B53)+(B54))+(B55) -> 3502 | C56: =((C53)+(C54))+(C55) -> 5793.9 | D56: =((D53)+(D54))+(D55) -> 29339.93 | E56: =((E53)+(E54))+(E55) -> 26340 | F56: =((F53)+(F54))+(F55) -> 18315.23 | G56: =((G53)+(G54))+(G55) -> 139.4 | H56: =(((((B56)+(C56))+(D56))+(E56))+(F56))+(G56) -> 83430.46
A57: 63000 General Office Expenses | H57: =(((((B57)+(C57))+(D57))+(E57))+(F57))+(G57) -> 0
A58: 63001 Donations | C58: =1412.5 -> 1412.5 | D58: =734.5 -> 734.5 | E58: =508.5 -> 508.5 | F58: =904 -> 904 | G58: =466.55 -> 466.55 | H58: =(((((B58)+(C58))+(D58))+(E58))+(F58))+(G58) -> 4026.05
A59: 63010 Office Supplies | B59: =21.35 -> 21.35 | C59: =352.39 -> 352.39 | D59: =6057.87 -> 6057.87 | E59: =476.34 -> 476.34 | F59: =1649.63 -> 1649.63 | G59: =1551.95 -> 1551.95 | H59: =(((((B59)+(C59))+(D59))+(E59))+(F59))+(G59) -> 10109.53
A60: 63011 Other Office Expenses | B60: =100 -> 100 | C60: =1869.15 -> 1869.15 | D60: =789.28 -> 789.28 | E60: =203.54 -> 203.54 | F60: =108 -> 108 | G60: =811.74 -> 811.74 | H60: =(((((B60)+(C60))+(D60))+(E60))+(F60))+(G60) -> 3881.71
A61: 63015 Education & Training | C61: =715 -> 715 | D61: =10363 -> 10363 | E61: =449 -> 449 | F61: =6293.94 -> 6293.94 | G61: =2822.4 -> 2822.4 | H61: =(((((B61)+(C61))+(D61))+(E61))+(F61))+(G61) -> 20643.34
A62: 63020 Bank Charges & Fees | C62: =-5.24 -> -5.24 | D62: =707.33 -> 707.33 | E62: =290.16 -> 290.16 | F62: =2470.71 -> 2470.71 | G62: =491.28 -> 491.28 | H62: =(((((B62)+(C62))+(D62))+(E62))+(F62))+(G62) -> 3954.24
A63: 63040 Other Business Expenses | B63: =5616.27 -> 5616.27 | C63: =2177.82 -> 2177.82 | D63: =9662.16 -> 9662.16 | E63: =15150.53 -> 15150.53 | F63: =16836.65 -> 16836.65 | G63: =16348.69 -> 16348.69 | H63: =(((((B63)+(C63))+(D63))+(E63))+(F63))+(G63) -> 65792.12
A64: 63050 Dues and Subscriptions | B64: =3757.59 -> 3757.59 | C64: =3559.07 -> 3559.07 | D64: =6670.7 -> 6670.7 | E64: =5923.12 -> 5923.12 | F64: =4410.41 -> 4410.41 | G64: =4498.62 -> 4498.62 | H64: =(((((B64)+(C64))+(D64))+(E64))+(F64))+(G64) -> 28819.51
A65: 63060 Freight, Postage and Delivery | B65: =4562.74 -> 4562.74 | C65: =2692.28 -> 2692.28 | D65: =3620.07 -> 3620.07 | E65: =3233.08 -> 3233.08 | F65: =4080.66 -> 4080.66 | G65: =10410.05 -> 10410.05 | H65: =(((((B65)+(C65))+(D65))+(E65))+(F65))+(G65) -> 28598.88
A66: 63065 Software License Expense | E66: =624.92 -> 624.92 | F66: =974.92 -> 974.92 | G66: =974.92 -> 974.92 | H66: =(((((B66)+(C66))+(D66))+(E66))+(F66))+(G66) -> 2574.76
A67: 63070 Processing & Service Fees | H67: =(((((B67)+(C67))+(D67))+(E67))+(F67))+(G67) -> 0
A68: 63071 Payroll Processing Cost | B68: =4569.27 -> 4569.27 | C68: =3597.73 -> 3597.73 | D68: =6229.66 -> 6229.66 | E68: =3747.01 -> 3747.01 | F68: =5637.96 -> 5637.96 | G68: =-4339.84 -> -4339.84 | H68: =(((((B68)+(C68))+(D68))+(E68))+(F68))+(G68) -> 19441.79
A69: Total 63070 Processing & Service Fees | B69: =(B67)+(B68) -> 4569.27 | C69: =(C67)+(C68) -> 3597.73 | D69: =(D67)+(D68) -> 6229.66 | E69: =(E67)+(E68) -> 3747.01 | F69: =(F67)+(F68) -> 5637.96 | G69: =(G67)+(G68) -> -4339.84 | H69: =(((((B69)+(C69))+(D69))+(E69))+(F69))+(G69) -> 19441.79
A70: 63080 Groceries | B70: =106.23 -> 106.23 | C70: =391.59 -> 391.59 | D70: =294.06 -> 294.06 | E70: =236.75 -> 236.75 | F70: =2047.57 -> 2047.57 | G70: =464.13 -> 464.13 | H70: =(((((B70)+(C70))+(D70))+(E70))+(F70))+(G70) -> 3540.33
A71: 63085 Meals | B71: =3499 -> 3499 | C71: =2520.06 -> 2520.06 | D71: =10475.04 -> 10475.04 | E71: =4611.29 -> 4611.29 | F71: =5269.87 -> 5269.87 | G71: =7279.99 -> 7279.99 | H71: =(((((B71)+(C71))+(D71))+(E71))+(F71))+(G71) -> 33655.25
A72: 63090 Software, Data & Web Hosting Services | B72: =8182.28 -> 8182.28 | C72: =5168.67 -> 5168.67 | D72: =11934.16 -> 11934.16 | E72: =6245.02 -> 6245.02 | F72: =9377.28 -> 9377.28 | G72: =9285.61 -> 9285.61 | H72: =(((((B72)+(C72))+(D72))+(E72))+(F72))+(G72) -> 50193.02
A73: Total 63000 General Office Expenses | B73: =(((((((((((((B57)+(B58))+(B59))+(B60))+(B61))+(B62))+(B63))+(B64))+(B65))+(B66))+(B69))+(B70))+(B71))+(B72) -> 30414.73 | C73: =(((((((((((((C57)+(C58))+(C59))+(C60))+(C61))+(C62))+(C63))+(C64))+(C65))+(C66))+(C69))+(C70))+(C71))+(C72) -> 24451.02 | D73: =(((((((((((((D57)+(D58))+(D59))+(D60))+(D61))+(D62))+(D63))+(D64))+(D65))+(D66))+(D69))+(D70))+(D71))+(D72) -> 67537.83 | E73: =(((((((((((((E57)+(E58))+(E59))+(E60))+(E61))+(E62))+(E63))+(E64))+(E65))+(E66))+(E69))+(E70))+(E71))+(E72) -> 41699.26 | F73: =(((((((((((((F57)+(F58))+(F59))+(F60))+(F61))+(F62))+(F63))+(F64))+(F65))+(F66))+(F69))+(F70))+(F71))+(F72) -> 60061.6 | G73: =(((((((((((((G57)+(G58))+(G59))+(G60))+(G61))+(G62))+(G63))+(G64))+(G65))+(G66))+(G69))+(G70))+(G71))+(G72) -> 51066.09 | H73: =(((((B73)+(C73))+(D73))+(E73))+(F73))+(G73) -> 275230.53
A74: 65000 Travel & Transportation | H74: =(((((B74)+(C74))+(D74))+(E74))+(F74))+(G74) -> 0
A75: 65001 Travel Expense | B75: =21654.81 -> 21654.81 | C75: =30026.3 -> 30026.3 | D75: =52112.66 -> 52112.66 | E75: =33016.07 -> 33016.07 | F75: =63704.7 -> 63704.7 | G75: =70845.42 -> 70845.42 | H75: =(((((B75)+(C75))+(D75))+(E75))+(F75))+(G75) -> 271359.96
A76: 65002 Airfare | B76: =6736.49 -> 6736.49 | C76: =16124.78 -> 16124.78 | D76: =39716.75 -> 39716.75 | E76: =20272.09 -> 20272.09 | F76: =21812.43 -> 21812.43 | G76: =27464.58 -> 27464.58 | H76: =(((((B76)+(C76))+(D76))+(E76))+(F76))+(G76) -> 132127.12
A77: 65010 Gas/Fuel | B77: =1137.75 -> 1137.75 | C77: =812.83 -> 812.83 | D77: =975.85 -> 975.85 | E77: =1442.74 -> 1442.74 | F77: =4747.02 -> 4747.02 | G77: =3391.61 -> 3391.61 | H77: =(((((B77)+(C77))+(D77))+(E77))+(F77))+(G77) -> 12507.8
A78: 65020 Accommodation | B78: =12687.58 -> 12687.58 | C78: =23795.92 -> 23795.92 | D78: =45568.08 -> 45568.08 | E78: =21791.02 -> 21791.02 | F78: =16469.83 -> 16469.83 | G78: =13848.73 -> 13848.73 | H78: =(((((B78)+(C78))+(D78))+(E78))+(F78))+(G78) -> 134161.16
A79: 65050 Parking | B79: =294.12 -> 294.12 | C79: =270.17 -> 270.17 | D79: =375.75 -> 375.75 | E79: =545.84 -> 545.84 | F79: =871.13 -> 871.13 | G79: =585.07 -> 585.07 | H79: =(((((B79)+(C79))+(D79))+(E79))+(F79))+(G79) -> 2942.08
A80: Total 65000 Travel & Transportation | B80: =(((((B74)+(B75))+(B76))+(B77))+(B78))+(B79) -> 42510.75 | C80: =(((((C74)+(C75))+(C76))+(C77))+(C78))+(C79) -> 71030 | D80: =(((((D74)+(D75))+(D76))+(D77))+(D78))+(D79) -> 138749.09 | E80: =(((((E74)+(E75))+(E76))+(E77))+(E78))+(E79) -> 77067.76 | F80: =(((((F74)+(F75))+(F76))+(F77))+(F78))+(F79) -> 107605.11 | G80: =(((((G74)+(G75))+(G76))+(G77))+(G78))+(G79) -> 116135.41 | H80: =(((((B80)+(C80))+(D80))+(E80))+(F80))+(G80) -> 553098.12
A81: 66000 Facilities | B81: =1700.78 -> 1700.78 | C81: =1367.63 -> 1367.63 | D81: =1211 -> 1211 | E81: =1612.5 -> 1612.5 | F81: =2820.25 -> 2820.25 | G81: =2145.17 -> 2145.17 | H81: =(((((B81)+(C81))+(D81))+(E81))+(F81))+(G81) -> 10857.33
A82: 66001 Rent Expense | B82: =1299 -> 1299 | C82: =2421.5 -> 2421.5 | D82: =1835.52 -> 1835.52 | E82: =1054.16 -> 1054.16 | F82: =529.63 -> 529.63 | G82: =1129 -> 1129 | H82: =(((((B82)+(C82))+(D82))+(E82))+(F82))+(G82) -> 8268.81
A83: 66030 Telephone Expense | B83: =3870.58 -> 3870.58 | C83: =3820.05 -> 3820.05 | D83: =3348.85 -> 3348.85 | E83: =4281.86 -> 4281.86 | F83: =4672.02 -> 4672.02 | G83: =4274.46 -> 4274.46 | H83: =(((((B83)+(C83))+(D83))+(E83))+(F83))+(G83) -> 24267.82
A84: 66060 Expensed Equipment | B84: =247.89 -> 247.89 | H84: =(((((B84)+(C84))+(D84))+(E84))+(F84))+(G84) -> 247.89
A85: 66070 Cable & Radio Expenses | B85: =119.98 -> 119.98 | H85: =(((((B85)+(C85))+(D85))+(E85))+(F85))+(G85) -> 119.98
A86: Total 66000 Facilities | B86: =((((B81)+(B82))+(B83))+(B84))+(B85) -> 7238.23 | C86: =((((C81)+(C82))+(C83))+(C84))+(C85) -> 7609.18 | D86: =((((D81)+(D82))+(D83))+(D84))+(D85) -> 6395.37 | E86: =((((E81)+(E82))+(E83))+(E84))+(E85) -> 6948.52 | F86: =((((F81)+(F82))+(F83))+(F84))+(F85) -> 8021.9 | G86: =((((G81)+(G82))+(G83))+(G84))+(G85) -> 7548.63 | H86: =(((((B86)+(C86))+(D86))+(E86))+(F86))+(G86) -> 43761.83
A87: 69000 Insurance Expense | B87: =9037.93 -> 9037.93 | C87: =8986.4 -> 8986.4 | D87: =9016.72 -> 9016.72 | E87: =10453.6 -> 10453.6 | F87: =10403.48 -> 10403.48 | G87: =11331.83 -> 11331.83 | H87: =(((((B87)+(C87))+(D87))+(E87))+(F87))+(G87) -> 59229.96
A88: 90000 Taxes & Licenses | B88: =131.81 -> 131.81 | C88: =200 -> 200 | D88: =25.5 -> 25.5 | F88: =5 -> 5 | G88: =122.1 -> 122.1 | H88: =(((((B88)+(C88))+(D88))+(E88))+(F88))+(G88) -> 484.41
A89: 90010 State & Local Taxes | B89: =320.25 -> 320.25 | D89: =86.03 -> 86.03 | E89: =800 -> 800 | G89: =151.7 -> 151.7 | H89: =(((((B89)+(C89))+(D89))+(E89))+(F89))+(G89) -> 1357.98
A90: Total 90000 Taxes & Licenses | B90: =(B88)+(B89) -> 452.06 | C90: =(C88)+(C89) -> 200 | D90: =(D88)+(D89) -> 111.53 | E90: =(E88)+(E89) -> 800 | F90: =(F88)+(F89) -> 5 | G90: =(G88)+(G89) -> 273.8 | H90: =(((((B90)+(C90))+(D90))+(E90))+(F90))+(G90) -> 1842.39
A91: 90020 Local Taxes | D91: =950 -> 950 | H91: =(((((B91)+(C91))+(D91))+(E91))+(F91))+(G91) -> 950
A92: QuickBooks Payments Fees | D92: =4.52 -> 4.52 | G92: =2.21 -> 2.21 | H92: =(((((B92)+(C92))+(D92))+(E92))+(F92))+(G92) -> 6.73
A93: Total Expenses | B93: =(((((((((B43)+(B52))+(B56))+(B73))+(B80))+(B86))+(B87))+(B90))+(B91))+(B92) -> 338579.02 | C93: =(((((((((C43)+(C52))+(C56))+(C73))+(C80))+(C86))+(C87))+(C90))+(C91))+(C92) -> 320190.17 | D93: =(((((((((D43)+(D52))+(D56))+(D73))+(D80))+(D86))+(D87))+(D90))+(D91))+(D92) -> 512990.16 | E93: =(((((((((E43)+(E52))+(E56))+(E73))+(E80))+(E86))+(E87))+(E90))+(E91))+(E92) -> 430763.29 | F93: =(((((((((F43)+(F52))+(F56))+(F73))+(F80))+(F86))+(F87))+(F90))+(F91))+(F92) -> 646040.45 | G93: =(((((((((G43)+(G52))+(G56))+(G73))+(G80))+(G86))+(G87))+(G90))+(G91))+(G92) -> 714641.39 | H93: =(((((B93)+(C93))+(D93))+(E93))+(F93))+(G93) -> 2963204.5
A94: Net Operating Income | B94: =(B37)-(B93) -> -349525.09 | C94: =(C37)-(C93) -> -337094.5 | D94: =(D37)-(D93) -> -552416.9 | E94: =(E37)-(E93) -> -411798.83 | F94: =(F37)-(F93) -> -689101.13 | G94: =(G37)-(G93) -> -682423.9 | H94: =(((((B94)+(C94))+(D94))+(E94))+(F94))+(G94) -> -3022360.4
A95: Other Income
A96: 70000 Other Income | B96: =0 -> 0 | C96: =0 -> 0 | D96: =1000 -> 1000 | E96: =0.84 -> 0.84 | F96: =0 -> 0 | G96: =0 -> 0 | H96: =(((((B96)+(C96))+(D96))+(E96))+(F96))+(G96) -> 1000.84
A97: 70020 Interest Income | D97: =404.2 -> 404.2 | E97: =2197.94 -> 2197.94 | F97: =9953.16 -> 9953.16 | G97: =17434.03 -> 17434.03 | H97: =(((((B97)+(C97))+(D97))+(E97))+(F97))+(G97) -> 29989.33
A98: Total Other Income | B98: =(B96)+(B97) -> 0 | C98: =(C96)+(C97) -> 0 | D98: =(D96)+(D97) -> 1404.2 | E98: =(E96)+(E97) -> 2198.78 | F98: =(F96)+(F97) -> 9953.16 | G98: =(G96)+(G97) -> 17434.03 | H98: =(((((B98)+(C98))+(D98))+(E98))+(F98))+(G98) -> 30990.17
A99: Net Other Income | B99: =(B98)-(0) -> 0 | C99: =(C98)-(0) -> 0 | D99: =(D98)-(0) -> 1404.2 | E99: =(E98)-(0) -> 2198.78 | F99: =(F98)-(0) -> 9953.16 | G99: =(G98)-(0) -> 17434.03 | H99: =(((((B99)+(C99))+(D99))+(E99))+(F99))+(G99) -> 30990.17
A100: Net Income | B100: =(B94)+(B99) -> -349525.09 | C100: =(C94)+(C99) -> -337094.5 | D100: =(D94)+(D99) -> -551012.7 | E100: =(E94)+(E99) -> -409600.05 | F100: =(F94)+(F99) -> -679147.97 | G100: =(G94)+(G99) -> -664989.87 | H100: =(((((B100)+(C100))+(D100))+(E100))+(F100))+(G100) -> -2991370.2
A104: Tuesday, Jul 18, 2023 08:52:15 AM GMT-7 - Accrual Basis

Sheet Price
B2: Rev | C2: Single Product
D3: Requires Tech Team
D4: Subscription Service
D5: Churn
B8: Cost
C9: Salaries | D9: VC
C10: Battery Degredation | D10: VC | E10: Batteries degarde 1.8% per yer
C12: Production | D12: VC
C13: Logistics
C14: Recycling the battery

Sheet Aid
B3: Users | C3: 1000000 | D3: people
G4: Sunrun Inc.
B5: Activation | C5: 0.85 | D5: Using | G5: Tesla, Inc.
G6: Samsara Inc.
B7: Total Activated | C7: =C3*C5 -> 850000 | G7: ChargePoint Holdings, Inc.
G8: ServiceTitan, Inc.
B9: Subscription Conversion | C9: 0.02 | G9: Nextracker Inc.
G10: Karooooo Ltd.
B11: Number of Free Users | C11: =(1-C9)*C7 -> 833000 | G11: Siemens Aktiengesellschaft
B12: Number of Subscribers | C12: =C9*C7 -> 17000
B14: Subscription Fee | C14: 19
B16: Total | C16: =C14*C12 -> 323000
B19: -You offer a subscription service that includes upgrades or replacements | C19: COST item

Sheet RevnueDrivers>>

Sheet Head Count
F1: Yr | H1: 1 | I1: =H1+1 -> 2 | J1: =I1+1 -> 3 | K1: =J1+1 -> 4 | L1: =K1+1 -> 5 | M1: =L1+1 -> 6 | N1: =M1+1 -> 7 | O1: =N1+1 -> 8 | P1: =O1+1 -> 9 | ... V1: =U1+1 -> 15
A3: Head Count | B3: Starting Value | C3: Starting Year | D3: Increment Value | E3: Every X Years | F3: Max Value
A4: Technicians | B4: 1 | C4: 1 | D4: 1 | E4: 3 | F4: 6 | H4: =MIN($F$4,IF(H$1<$C$4,0,IF(H$1=$C4,$B4,IF(IF($D4>0,MOD(H$1-$C$4,$E4)=0,0),G4+$D4,G4)))) -> 1 | I4: =MIN($F$4,IF(I$1<$C$4,0,IF(I$1=$C4,$B4,IF(IF($D4>0,MOD(I$1-$C$4,$E4)=0,0),H4+$D4,H4)))) -> 1 | J4: =MIN($F$4,IF(J$1<$C$4,0,IF(J$1=$C4,$B4,IF(IF($D4>0,MOD(J$1-$C$4,$E4)=0,0),I4+$D4,I4)))) -> 1 | K4: =MIN($F$4,IF(K$1<$C$4,0,IF(K$1=$C4,$B4,IF(IF($D4>0,MOD(K$1-$C$4,$E4)=0,0),J4+$D4,J4)))) -> 2 | L4: =MIN($F$4,IF(L$1<$C$4,0,IF(L$1=$C4,$B4,IF(IF($D4>0,MOD(L$1-$C$4,$E4)=0,0),K4+$D4,K4)))) -> 2 | M4: =MIN($F$4,IF(M$1<$C$4,0,IF(M$1=$C4,$B4,IF(IF($D4>0,MOD(M$1-$C$4,$E4)=0,0),L4+$D4,L4)))) -> 2 | N4: =MIN($F$4,IF(N$1<$C$4,0,IF(N$1=$C4,$B4,IF(IF($D4>0,MOD(N$1-$C$4,$E4)=0,0),M4+$D4,M4)))) -> 3 | O4: =MIN($F$4,IF(O$1<$C$4,0,IF(O$1=$C4,$B4,IF(IF($D4>0,MOD(O$1-$C$4,$E4)=0,0),N4+$D4,N4)))) -> 3 | ... V4: =MIN($F$4,IF(V$1<$C$4,0,IF(V$1=$C4,$B4,IF(IF($D4>0,MOD(V$1-$C$4,$E4)=0,0),U4+$D4,U4)))) -> 5
A7: Avg All in Compensation | B7: Starting Value | C7: Starting Year | D7: Increment Value | E7: Every X Years | F7: Max Per Year/Head Count
A8: Technicians | B8: 60000 | C8: =C4 -> 1 | D8: 10000 | E8: 2 | F8: 92000 | H8: =IF(H$1=$C8,$B8,IF(IF($D8>0,MOD(H$1,$E8)=0,0),MIN($F8,G8+$D8),G8)) -> 60000 | I8: =IF(I$1=$C8,$B8,IF(IF($D8>0,MOD(I$1,$E8)=0,0),MIN($F8,H8+$D8),H8)) -> 70000 | J8: =IF(J$1=$C8,$B8,IF(IF($D8>0,MOD(J$1,$E8)=0,0),MIN($F8,I8+$D8),I8)) -> 70000 | K8: =IF(K$1=$C8,$B8,IF(IF($D8>0,MOD(K$1,$E8)=0,0),MIN($F8,J8+$D8),J8)) -> 80000 | L8: =IF(L$1=$C8,$B8,IF(IF($D8>0,MOD(L$1,$E8)=0,0),MIN($F8,K8+$D8),K8)) -> 80000 | M8: =IF(M$1=$C8,$B8,IF(IF($D8>0,MOD(M$1,$E8)=0,0),MIN($F8,L8+$D8),L8)) -> 90000 | N8: =IF(N$1=$C8,$B8,IF(IF($D8>0,MOD(N$1,$E8)=0,0),MIN($F8,M8+$D8),M8)) -> 90000 | O8: =IF(O$1=$C8,$B8,IF(IF($D8>0,MOD(O$1,$E8)=0,0),MIN($F8,N8+$D8),N8)) -> 92000 | ... V8: =IF(V$1=$C8,$B8,IF(IF($D8>0,MOD(V$1,$E8)=0,0),MIN($F8,U8+$D8),U8)) -> 92000
F11: Total Compensation
F12: Technicians | H12: =H4*H8 -> 60000 | I12: =I4*I8 -> 70000 | J12: =J4*J8 -> 70000 | K12: =K4*K8 -> 160000 | L12: =L4*L8 -> 160000 | M12: =M4*M8 -> 180000 | N12: =N4*N8 -> 270000 | O12: =O4*O8 -> 276000 | ... V12: =V4*V8 -> 460000

Sheet GrowthForecast
Q27: How can we model growth?
Q37: This should cover intrest in new tech

Sheet ChurnMatrix
D4: Month | E4: ='P&Lv2'!D5 -> 1 | F4: =E4+1 -> 2 | G4: =F4+1 -> 3 | H4: =G4+1 -> 4 | I4: =H4+1 -> 5 | J4: =I4+1 -> 6
D5: User Retention | E5: 0.56 | F5: 0.25 | G5: 0.25 | H5: 0.23 | I5: 0.11 | J5: 0.11
C9: Yr | D9: 1 | E9: =D9+1 -> 2 | F9: =E9+1 -> 3 | G9: =F9+1 -> 4 | H9: =G9+1 -> 5 | I9: =H9+1 -> 6 | J9: =I9+1 -> 7 | K9: =J9+1 -> 8 | L9: =K9+1 -> 9 | M9: =L9+1 -> 10
B11: Inputs Rev | C11: New customers | D11: ='P&Lv2'!D15 -> 1300 | E11: ='P&Lv2'!E15 -> 2000 | F11: ='P&Lv2'!F15 -> 3300 | G11: ='P&Lv2'!G15 -> 3465 | H11: ='P&Lv2'!H15 -> 3638.25 | I11: ='P&Lv2'!I15 -> 3820.1625 | J11: ='P&Lv2'!J15 -> 4011.1706 | K11: ='P&Lv2'!K15 -> 4211.7292 | ... M11: ='P&Lv2'!M15 -> 4643.4314
C13: Total Customers | D13: =D11 -> 1300 | E13: =(E11+D13) +E98 -> 2897 | F13: =(F11+E13) +F98 -> 5577 | G13: =(G11+F13) +G98 -> 7993 | H13: =(H11+G13) +H98 -> 10361.1 | I13: =(I11+H13) +I98 -> 12747.405 | J13: =(J11+I13) +J98 -> 15109.025 | K13: =(K11+J13) +K98 -> 17588.727 | L13: =(L11+K13) +L98 -> 20192.413 | M13: =(M11+L13) +M98 -> 22926.283
C15: Cohort Retention
C16: 1 | D16: =ChurnMatrix!E$5 -> 0.56 | E16: =ChurnMatrix!F$5 -> 0.25 | F16: =ChurnMatrix!G$5 -> 0.25 | G16: =ChurnMatrix!H$5 -> 0.23 | H16: =ChurnMatrix!I$5 -> 0.11 | I16: =ChurnMatrix!J$5 -> 0.11
C17: =C16+1 -> 2 | D17: =IF(OR(D$9>($C17+5),(D$9-$C17)<0),"",_xlfn.XLOOKUP(D$9-$C16,ChurnMatrix!$E$4:$J$4,ChurnMatrix!$E$5:$J$5)) | E17: =IF(OR(E$9>($C17+5),(E$9-$C17)<0),"",_xlfn.XLOOKUP(E$9-$C16,ChurnMatrix!$E$4:$J$4,ChurnMatrix!$E$5:$J$5)) -> 0.56 | F17: =IF(OR(F$9>($C17+5),(F$9-$C17)<0),"",_xlfn.XLOOKUP(F$9-$C16,ChurnMatrix!$E$4:$J$4,ChurnMatrix!$E$5:$J$5)) -> 0.25 | G17: =IF(OR(G$9>($C17+5),(G$9-$C17)<0),"",_xlfn.XLOOKUP(G$9-$C16,ChurnMatrix!$E$4:$J$4,ChurnMatrix!$E$5:$J$5)) -> 0.25 | H17: =IF(OR(H$9>($C17+5),(H$9-$C17)<0),"",_xlfn.XLOOKUP(H$9-$C16,ChurnMatrix!$E$4:$J$4,ChurnMatrix!$E$5:$J$5)) -> 0.23 | I17: =IF(OR(I$9>($C17+5),(I$9-$C17)<0),"",_xlfn.XLOOKUP(I$9-$C16,ChurnMatrix!$E$4:$J$4,ChurnMatrix!$E$5:$J$5)) -> 0.11 | J17: =IF(OR(J$9>($C17+5),(J$9-$C17)<0),"",_xlfn.XLOOKUP(J$9-$C16,ChurnMatrix!$E$4:$J$4,ChurnMatrix!$E$5:$J$5)) -> 0.11 | K17: =IF(OR(K$9>($C17+5),(K$9-$C17)<0),"",_xlfn.XLOOKUP(K$9-$C16,ChurnMatrix!$E$4:$J$4,ChurnMatrix!$E$5:$J$5)) | ... M17: =IF(OR(M$9>($C17+5),(M$9-$C17)<0),"",_xlfn.XLOOKUP(M$9-$C16,ChurnMatrix!$E$4:$J$4,ChurnMatrix!$E$5:$J$5))
C18: =C17+1 -> 3 | D18: =IF(OR(D$9>($C18+5),(D$9-$C18)<0),"",_xlfn.XLOOKUP(D$9-$C17,ChurnMatrix!$E$4:$J$4,ChurnMatrix!$E$5:$J$5)) | E18: =IF(OR(E$9>($C18+5),(E$9-$C18)<0),"",_xlfn.XLOOKUP(E$9-$C17,ChurnMatrix!$E$4:$J$4,ChurnMatrix!$E$5:$J$5)) | F18: =IF(OR(F$9>($C18+5),(F$9-$C18)<0),"",_xlfn.XLOOKUP(F$9-$C17,ChurnMatrix!$E$4:$J$4,ChurnMatrix!$E$5:$J$5)) -> 0.56 | G18: =IF(OR(G$9>($C18+5),(G$9-$C18)<0),"",_xlfn.XLOOKUP(G$9-$C17,ChurnMatrix!$E$4:$J$4,ChurnMatrix!$E$5:$J$5)) -> 0.25 | H18: =IF(OR(H$9>($C18+5),(H$9-$C18)<0),"",_xlfn.XLOOKUP(H$9-$C17,ChurnMatrix!$E$4:$J$4,ChurnMatrix!$E$5:$J$5)) -> 0.25 | I18: =IF(OR(I$9>($C18+5),(I$9-$C18)<0),"",_xlfn.XLOOKUP(I$9-$C17,ChurnMatrix!$E$4:$J$4,ChurnMatrix!$E$5:$J$5)) -> 0.23 | J18: =IF(OR(J$9>($C18+5),(J$9-$C18)<0),"",_xlfn.XLOOKUP(J$9-$C17,ChurnMatrix!$E$4:$J$4,ChurnMatrix!$E$5:$J$5)) -> 0.11 | K18: =IF(OR(K$9>($C18+5),(K$9-$C18)<0),"",_xlfn.XLOOKUP(K$9-$C17,ChurnMatrix!$E$4:$J$4,ChurnMatrix!$E$5:$J$5)) -> 0.11 | ... M18: =IF(OR(M$9>($C18+5),(M$9-$C18)<0),"",_xlfn.XLOOKUP(M$9-$C17,ChurnMatrix!$E$4:$J$4,ChurnMatrix!$E$5:$J$5))
C19: =C18+1 -> 4 | D19: =IF(OR(D$9>($C19+5),(D$9-$C19)<0),"",_xlfn.XLOOKUP(D$9-$C18,ChurnMatrix!$E$4:$J$4,ChurnMatrix!$E$5:$J$5)) | E19: =IF(OR(E$9>($C19+5),(E$9-$C19)<0),"",_xlfn.XLOOKUP(E$9-$C18,ChurnMatrix!$E$4:$J$4,ChurnMatrix!$E$5:$J$5)) | F19: =IF(OR(F$9>($C19+5),(F$9-$C19)<0),"",_xlfn.XLOOKUP(F$9-$C18,ChurnMatrix!$E$4:$J$4,ChurnMatrix!$E$5:$J$5)) | G19: =IF(OR(G$9>($C19+5),(G$9-$C19)<0),"",_xlfn.XLOOKUP(G$9-$C18,ChurnMatrix!$E$4:$J$4,ChurnMatrix!$E$5:$J$5)) -> 0.56 | H19: =IF(OR(H$9>($C19+5),(H$9-$C19)<0),"",_xlfn.XLOOKUP(H$9-$C18,ChurnMatrix!$E$4:$J$4,ChurnMatrix!$E$5:$J$5)) -> 0.25 | I19: =IF(OR(I$9>($C19+5),(I$9-$C19)<0),"",_xlfn.XLOOKUP(I$9-$C18,ChurnMatrix!$E$4:$J$4,ChurnMatrix!$E$5:$J$5)) -> 0.25 | J19: =IF(OR(J$9>($C19+5),(J$9-$C19)<0),"",_xlfn.XLOOKUP(J$9-$C18,ChurnMatrix!$E$4:$J$4,ChurnMatrix!$E$5:$J$5)) -> 0.23 | K19: =IF(OR(K$9>($C19+5),(K$9-$C19)<0),"",_xlfn.XLOOKUP(K$9-$C18,ChurnMatrix!$E$4:$J$4,ChurnMatrix!$E$5:$J$5)) -> 0.11 | ... M19: =IF(OR(M$9>($C19+5),(M$9-$C19)<0),"",_xlfn.XLOOKUP(M$9-$C18,ChurnMatrix!$E$4:$J$4,ChurnMatrix!$E$5:$J$5))
C20: =C19+1 -> 5 | D20: =IF(OR(D$9>($C20+5),(D$9-$C20)<0),"",_xlfn.XLOOKUP(D$9-$C19,ChurnMatrix!$E$4:$J$4,ChurnMatrix!$E$5:$J$5)) | E20: =IF(OR(E$9>($C20+5),(E$9-$C20)<0),"",_xlfn.XLOOKUP(E$9-$C19,ChurnMatrix!$E$4:$J$4,ChurnMatrix!$E$5:$J$5)) | F20: =IF(OR(F$9>($C20+5),(F$9-$C20)<0),"",_xlfn.XLOOKUP(F$9-$C19,ChurnMatrix!$E$4:$J$4,ChurnMatrix!$E$5:$J$5)) | G20: =IF(OR(G$9>($C20+5),(G$9-$C20)<0),"",_xlfn.XLOOKUP(G$9-$C19,ChurnMatrix!$E$4:$J$4,ChurnMatrix!$E$5:$J$5)) | H20: =IF(OR(H$9>($C20+5),(H$9-$C20)<0),"",_xlfn.XLOOKUP(H$9-$C19,ChurnMatrix!$E$4:$J$4,ChurnMatrix!$E$5:$J$5)) -> 0.56 | I20: =IF(OR(I$9>($C20+5),(I$9-$C20)<0),"",_xlfn.XLOOKUP(I$9-$C19,ChurnMatrix!$E$4:$J$4,ChurnMatrix!$E$5:$J$5)) -> 0.25 | J20: =IF(OR(J$9>($C20+5),(J$9-$C20)<0),"",_xlfn.XLOOKUP(J$9-$C19,ChurnMatrix!$E$4:$J$4,ChurnMatrix!$E$5:$J$5)) -> 0.25 | K20: =IF(OR(K$9>($C20+5),(K$9-$C20)<0),"",_xlfn.XLOOKUP(K$9-$C19,ChurnMatrix!$E$4:$J$4,ChurnMatrix!$E$5:$J$5)) -> 0.23 | ... M20: =IF(OR(M$9>($C20+5),(M$9-$C20)<0),"",_xlfn.XLOOKUP(M$9-$C19,ChurnMatrix!$E$4:$J$4,ChurnMatrix!$E$5:$J$5)) -> 0.11
C21: =C20+1 -> 6 | D21: =IF(OR(D$9>($C21+5),(D$9-$C21)<0),"",_xlfn.XLOOKUP(D$9-$C20,ChurnMatrix!$E$4:$J$4,ChurnMatrix!$E$5:$J$5)) | E21: =IF(OR(E$9>($C21+5),(E$9-$C21)<0),"",_xlfn.XLOOKUP(E$9-$C20,ChurnMatrix!$E$4:$J$4,ChurnMatrix!$E$5:$J$5)) | F21: =IF(OR(F$9>($C21+5),(F$9-$C21)<0),"",_xlfn.XLOOKUP(F$9-$C20,ChurnMatrix!$E$4:$J$4,ChurnMatrix!$E$5:$J$5)) | G21: =IF(OR(G$9>($C21+5),(G$9-$C21)<0),"",_xlfn.XLOOKUP(G$9-$C20,ChurnMatrix!$E$4:$J$4,ChurnMatrix!$E$5:$J$5)) | H21: =IF(OR(H$9>($C21+5),(H$9-$C21)<0),"",_xlfn.XLOOKUP(H$9-$C20,ChurnMatrix!$E$4:$J$4,ChurnMatrix!$E$5:$J$5)) | I21: =IF(OR(I$9>($C21+5),(I$9-$C21)<0),"",_xlfn.XLOOKUP(I$9-$C20,ChurnMatrix!$E$4:$J$4,ChurnMatrix!$E$5:$J$5)) -> 0.56 | J21: =IF(OR(J$9>($C21+5),(J$9-$C21)<0),"",_xlfn.XLOOKUP(J$9-$C20,ChurnMatrix!$E$4:$J$4,ChurnMatrix!$E$5:$J$5)) -> 0.25 | K21: =IF(OR(K$9>($C21+5),(K$9-$C21)<0),"",_xlfn.XLOOKUP(K$9-$C20,ChurnMatrix!$E$4:$J$4,ChurnMatrix!$E$5:$J$5)) -> 0.25 | ... M21: =IF(OR(M$9>($C21+5),(M$9-$C21)<0),"",_xlfn.XLOOKUP(M$9-$C20,ChurnMatrix!$E$4:$J$4,ChurnMatrix!$E$5:$J$5)) -> 0.11
C22: =C21+1 -> 7 | D22: =IF(OR(D$9>($C22+5),(D$9-$C22)<0),"",_xlfn.XLOOKUP(D$9-$C21,ChurnMatrix!$E$4:$J$4,ChurnMatrix!$E$5:$J$5)) | E22: =IF(OR(E$9>($C22+5),(E$9-$C22)<0),"",_xlfn.XLOOKUP(E$9-$C21,ChurnMatrix!$E$4:$J$4,ChurnMatrix!$E$5:$J$5)) | F22: =IF(OR(F$9>($C22+5),(F$9-$C22)<0),"",_xlfn.XLOOKUP(F$9-$C21,ChurnMatrix!$E$4:$J$4,ChurnMatrix!$E$5:$J$5)) | G22: =IF(OR(G$9>($C22+5),(G$9-$C22)<0),"",_xlfn.XLOOKUP(G$9-$C21,ChurnMatrix!$E$4:$J$4,ChurnMatrix!$E$5:$J$5)) | H22: =IF(OR(H$9>($C22+5),(H$9-$C22)<0),"",_xlfn.XLOOKUP(H$9-$C21,ChurnMatrix!$E$4:$J$4,ChurnMatrix!$E$5:$J$5)) | I22: =IF(OR(I$9>($C22+5),(I$9-$C22)<0),"",_xlfn.XLOOKUP(I$9-$C21,ChurnMatrix!$E$4:$J$4,ChurnMatrix!$E$5:$J$5)) | J22: =IF(OR(J$9>($C22+5),(J$9-$C22)<0),"",_xlfn.XLOOKUP(J$9-$C21,ChurnMatrix!$E$4:$J$4,ChurnMatrix!$E$5:$J$5)) -> 0.56 | K22: =IF(OR(K$9>($C22+5),(K$9-$C22)<0),"",_xlfn.XLOOKUP(K$9-$C21,ChurnMatrix!$E$4:$J$4,ChurnMatrix!$E$5:$J$5)) -> 0.25 | ... M22: =IF(OR(M$9>($C22+5),(M$9-$C22)<0),"",_xlfn.XLOOKUP(M$9-$C21,ChurnMatrix!$E$4:$J$4,ChurnMatrix!$E$5:$J$5)) -> 0.23
C23: =C22+1 -> 8 | D23: =IF(OR(D$9>($C23+5),(D$9-$C23)<0),"",_xlfn.XLOOKUP(D$9-$C22,ChurnMatrix!$E$4:$J$4,ChurnMatrix!$E$5:$J$5)) | E23: =IF(OR(E$9>($C23+5),(E$9-$C23)<0),"",_xlfn.XLOOKUP(E$9-$C22,ChurnMatrix!$E$4:$J$4,ChurnMatrix!$E$5:$J$5)) | F23: =IF(OR(F$9>($C23+5),(F$9-$C23)<0),"",_xlfn.XLOOKUP(F$9-$C22,ChurnMatrix!$E$4:$J$4,ChurnMatrix!$E$5:$J$5)) | G23: =IF(OR(G$9>($C23+5),(G$9-$C23)<0),"",_xlfn.XLOOKUP(G$9-$C22,ChurnMatrix!$E$4:$J$4,ChurnMatrix!$E$5:$J$5)) | H23: =IF(OR(H$9>($C23+5),(H$9-$C23)<0),"",_xlfn.XLOOKUP(H$9-$C22,ChurnMatrix!$E$4:$J$4,ChurnMatrix!$E$5:$J$5)) | I23: =IF(OR(I$9>($C23+5),(I$9-$C23)<0),"",_xlfn.XLOOKUP(I$9-$C22,ChurnMatrix!$E$4:$J$4,ChurnMatrix!$E$5:$J$5)) | J23: =IF(OR(J$9>($C23+5),(J$9-$C23)<0),"",_xlfn.XLOOKUP(J$9-$C22,ChurnMatrix!$E$4:$J$4,ChurnMatrix!$E$5:$J$5)) | K23: =IF(OR(K$9>($C23+5),(K$9-$C23)<0),"",_xlfn.XLOOKUP(K$9-$C22,ChurnMatrix!$E$4:$J$4,ChurnMatrix!$E$5:$J$5)) -> 0.56 | ... M23: =IF(OR(M$9>($C23+5),(M$9-$C23)<0),"",_xlfn.XLOOKUP(M$9-$C22,ChurnMatrix!$E$4:$J$4,ChurnMatrix!$E$5:$J$5)) -> 0.25
C24: =C23+1 -> 9 | D24: =IF(OR(D$9>($C24+5),(D$9-$C24)<0),"",_xlfn.XLOOKUP(D$9-$C23,ChurnMatrix!$E$4:$J$4,ChurnMatrix!$E$5:$J$5)) | E24: =IF(OR(E$9>($C24+5),(E$9-$C24)<0),"",_xlfn.XLOOKUP(E$9-$C23,ChurnMatrix!$E$4:$J$4,ChurnMatrix!$E$5:$J$5)) | F24: =IF(OR(F$9>($C24+5),(F$9-$C24)<0),"",_xlfn.XLOOKUP(F$9-$C23,ChurnMatrix!$E$4:$J$4,ChurnMatrix!$E$5:$J$5)) | G24: =IF(OR(G$9>($C24+5),(G$9-$C24)<0),"",_xlfn.XLOOKUP(G$9-$C23,ChurnMatrix!$E$4:$J$4,ChurnMatrix!$E$5:$J$5)) | H24: =IF(OR(H$9>($C24+5),(H$9-$C24)<0),"",_xlfn.XLOOKUP(H$9-$C23,ChurnMatrix!$E$4:$J$4,ChurnMatrix!$E$5:$J$5)) | I24: =IF(OR(I$9>($C24+5),(I$9-$C24)<0),"",_xlfn.XLOOKUP(I$9-$C23,ChurnMatrix!$E$4:$J$4,ChurnMatrix!$E$5:$J$5)) | J24: =IF(OR(J$9>($C24+5),(J$9-$C24)<0),"",_xlfn.XLOOKUP(J$9-$C23,ChurnMatrix!$E$4:$J$4,ChurnMatrix!$E$5:$J$5)) | K24: =IF(OR(K$9>($C24+5),(K$9-$C24)<0),"",_xlfn.XLOOKUP(K$9-$C23,ChurnMatrix!$E$4:$J$4,ChurnMatrix!$E$5:$J$5)) | ... M24: =IF(OR(M$9>($C24+5),(M$9-$C24)<0),"",_xlfn.XLOOKUP(M$9-$C23,ChurnMatrix!$E$4:$J$4,ChurnMatrix!$E$5:$J$5)) -> 0.25
C25: =C24+1 -> 10 | D25: =IF(OR(D$9>($C25+5),(D$9-$C25)<0),"",_xlfn.XLOOKUP(D$9-$C24,ChurnMatrix!$E$4:$J$4,ChurnMatrix!$E$5:$J$5)) | E25: =IF(OR(E$9>($C25+5),(E$9-$C25)<0),"",_xlfn.XLOOKUP(E$9-$C24,ChurnMatrix!$E$4:$J$4,ChurnMatrix!$E$5:$J$5)) | F25: =IF(OR(F$9>($C25+5),(F$9-$C25)<0),"",_xlfn.XLOOKUP(F$9-$C24,ChurnMatrix!$E$4:$J$4,ChurnMatrix!$E$5:$J$5)) | G25: =IF(OR(G$9>($C25+5),(G$9-$C25)<0),"",_xlfn.XLOOKUP(G$9-$C24,ChurnMatrix!$E$4:$J$4,ChurnMatrix!$E$5:$J$5)) | H25: =IF(OR(H$9>($C25+5),(H$9-$C25)<0),"",_xlfn.XLOOKUP(H$9-$C24,ChurnMatrix!$E$4:$J$4,ChurnMatrix!$E$5:$J$5)) | I25: =IF(OR(I$9>($C25+5),(I$9-$C25)<0),"",_xlfn.XLOOKUP(I$9-$C24,ChurnMatrix!$E$4:$J$4,ChurnMatrix!$E$5:$J$5)) | J25: =IF(OR(J$9>($C25+5),(J$9-$C25)<0),"",_xlfn.XLOOKUP(J$9-$C24,ChurnMatrix!$E$4:$J$4,ChurnMatrix!$E$5:$J$5)) | K25: =IF(OR(K$9>($C25+5),(K$9-$C25)<0),"",_xlfn.XLOOKUP(K$9-$C24,ChurnMatrix!$E$4:$J$4,ChurnMatrix!$E$5:$J$5)) | ... M25: =IF(OR(M$9>($C25+5),(M$9-$C25)<0),"",_xlfn.XLOOKUP(M$9-$C24,ChurnMatrix!$E$4:$J$4,ChurnMatrix!$E$5:$J$5)) -> 0.56
C26: =C25+1 -> 11 | D26: =IF(OR(D$9>($C26+5),(D$9-$C26)<0),"",_xlfn.XLOOKUP(D$9-$C25,ChurnMatrix!$E$4:$J$4,ChurnMatrix!$E$5:$J$5)) | E26: =IF(OR(E$9>($C26+5),(E$9-$C26)<0),"",_xlfn.XLOOKUP(E$9-$C25,ChurnMatrix!$E$4:$J$4,ChurnMatrix!$E$5:$J$5)) | F26: =IF(OR(F$9>($C26+5),(F$9-$C26)<0),"",_xlfn.XLOOKUP(F$9-$C25,ChurnMatrix!$E$4:$J$4,ChurnMatrix!$E$5:$J$5)) | G26: =IF(OR(G$9>($C26+5),(G$9-$C26)<0),"",_xlfn.XLOOKUP(G$9-$C25,ChurnMatrix!$E$4:$J$4,ChurnMatrix!$E$5:$J$5)) | H26: =IF(OR(H$9>($C26+5),(H$9-$C26)<0),"",_xlfn.XLOOKUP(H$9-$C25,ChurnMatrix!$E$4:$J$4,ChurnMatrix!$E$5:$J$5)) | I26: =IF(OR(I$9>($C26+5),(I$9-$C26)<0),"",_xlfn.XLOOKUP(I$9-$C25,ChurnMatrix!$E$4:$J$4,ChurnMatrix!$E$5:$J$5)) | J26: =IF(OR(J$9>($C26+5),(J$9-$C26)<0),"",_xlfn.XLOOKUP(J$9-$C25,ChurnMatrix!$E$4:$J$4,ChurnMatrix!$E$5:$J$5)) | K26: =IF(OR(K$9>($C26+5),(K$9-$C26)<0),"",_xlfn.XLOOKUP(K$9-$C25,ChurnMatrix!$E$4:$J$4,ChurnMatrix!$E$5:$J$5)) | ... M26: =IF(OR(M$9>($C26+5),(M$9-$C26)<0),"",_xlfn.XLOOKUP(M$9-$C25,ChurnMatrix!$E$4:$J$4,ChurnMatrix!$E$5:$J$5))
C27: =C26+1 -> 12 | D27: =IF(OR(D$9>($C27+5),(D$9-$C27)<0),"",_xlfn.XLOOKUP(D$9-$C26,ChurnMatrix!$E$4:$J$4,ChurnMatrix!$E$5:$J$5)) | E27: =IF(OR(E$9>($C27+5),(E$9-$C27)<0),"",_xlfn.XLOOKUP(E$9-$C26,ChurnMatrix!$E$4:$J$4,ChurnMatrix!$E$5:$J$5)) | F27: =IF(OR(F$9>($C27+5),(F$9-$C27)<0),"",_xlfn.XLOOKUP(F$9-$C26,ChurnMatrix!$E$4:$J$4,ChurnMatrix!$E$5:$J$5)) | G27: =IF(OR(G$9>($C27+5),(G$9-$C27)<0),"",_xlfn.XLOOKUP(G$9-$C26,ChurnMatrix!$E$4:$J$4,ChurnMatrix!$E$5:$J$5)) | H27: =IF(OR(H$9>($C27+5),(H$9-$C27)<0),"",_xlfn.XLOOKUP(H$9-$C26,ChurnMatrix!$E$4:$J$4,ChurnMatrix!$E$5:$J$5)) | I27: =IF(OR(I$9>($C27+5),(I$9-$C27)<0),"",_xlfn.XLOOKUP(I$9-$C26,ChurnMatrix!$E$4:$J$4,ChurnMatrix!$E$5:$J$5)) | J27: =IF(OR(J$9>($C27+5),(J$9-$C27)<0),"",_xlfn.XLOOKUP(J$9-$C26,ChurnMatrix!$E$4:$J$4,ChurnMatrix!$E$5:$J$5)) | K27: =IF(OR(K$9>($C27+5),(K$9-$C27)<0),"",_xlfn.XLOOKUP(K$9-$C26,ChurnMatrix!$E$4:$J$4,ChurnMatrix!$E$5:$J$5)) | ... M27: =IF(OR(M$9>($C27+5),(M$9-$C27)<0),"",_xlfn.XLOOKUP(M$9-$C26,ChurnMatrix!$E$4:$J$4,ChurnMatrix!$E$5:$J$5))
C28: =C27+1 -> 13 | D28: =IF(OR(D$9>($C28+5),(D$9-$C28)<0),"",_xlfn.XLOOKUP(D$9-$C27,ChurnMatrix!$E$4:$J$4,ChurnMatrix!$E$5:$J$5)) | E28: =IF(OR(E$9>($C28+5),(E$9-$C28)<0),"",_xlfn.XLOOKUP(E$9-$C27,ChurnMatrix!$E$4:$J$4,ChurnMatrix!$E$5:$J$5)) | F28: =IF(OR(F$9>($C28+5),(F$9-$C28)<0),"",_xlfn.XLOOKUP(F$9-$C27,ChurnMatrix!$E$4:$J$4,ChurnMatrix!$E$5:$J$5)) | G28: =IF(OR(G$9>($C28+5),(G$9-$C28)<0),"",_xlfn.XLOOKUP(G$9-$C27,ChurnMatrix!$E$4:$J$4,ChurnMatrix!$E$5:$J$5)) | H28: =IF(OR(H$9>($C28+5),(H$9-$C28)<0),"",_xlfn.XLOOKUP(H$9-$C27,ChurnMatrix!$E$4:$J$4,ChurnMatrix!$E$5:$J$5)) | I28: =IF(OR(I$9>($C28+5),(I$9-$C28)<0),"",_xlfn.XLOOKUP(I$9-$C27,ChurnMatrix!$E$4:$J$4,ChurnMatrix!$E$5:$J$5)) | J28: =IF(OR(J$9>($C28+5),(J$9-$C28)<0),"",_xlfn.XLOOKUP(J$9-$C27,ChurnMatrix!$E$4:$J$4,ChurnMatrix!$E$5:$J$5)) | K28: =IF(OR(K$9>($C28+5),(K$9-$C28)<0),"",_xlfn.XLOOKUP(K$9-$C27,ChurnMatrix!$E$4:$J$4,ChurnMatrix!$E$5:$J$5)) | ... M28: =IF(OR(M$9>($C28+5),(M$9-$C28)<0),"",_xlfn.XLOOKUP(M$9-$C27,ChurnMatrix!$E$4:$J$4,ChurnMatrix!$E$5:$J$5))
... C39: =C38+1 -> 24 | D39: =IF(OR(D$9>($C39+5),(D$9-$C39)<0),"",_xlfn.XLOOKUP(D$9-$C38,ChurnMatrix!$E$4:$J$4,ChurnMatrix!$E$5:$J$5)) | E39: =IF(OR(E$9>($C39+5),(E$9-$C39)<0),"",_xlfn.XLOOKUP(E$9-$C38,ChurnMatrix!$E$4:$J$4,ChurnMatrix!$E$5:$J$5)) | F39: =IF(OR(F$9>($C39+5),(F$9-$C39)<0),"",_xlfn.XLOOKUP(F$9-$C38,ChurnMatrix!$E$4:$J$4,ChurnMatrix!$E$5:$J$5)) | G39: =IF(OR(G$9>($C39+5),(G$9-$C39)<0),"",_xlfn.XLOOKUP(G$9-$C38,ChurnMatrix!$E$4:$J$4,ChurnMatrix!$E$5:$J$5)) | H39: =IF(OR(H$9>($C39+5),(H$9-$C39)<0),"",_xlfn.XLOOKUP(H$9-$C38,ChurnMatrix!$E$4:$J$4,ChurnMatrix!$E$5:$J$5)) | I39: =IF(OR(I$9>($C39+5),(I$9-$C39)<0),"",_xlfn.XLOOKUP(I$9-$C38,ChurnMatrix!$E$4:$J$4,ChurnMatrix!$E$5:$J$5)) | J39: =IF(OR(J$9>($C39+5),(J$9-$C39)<0),"",_xlfn.XLOOKUP(J$9-$C38,ChurnMatrix!$E$4:$J$4,ChurnMatrix!$E$5:$J$5)) | K39: =IF(OR(K$9>($C39+5),(K$9-$C39)<0),"",_xlfn.XLOOKUP(K$9-$C38,ChurnMatrix!$E$4:$J$4,ChurnMatrix!$E$5:$J$5)) | ... M39: =IF(OR(M$9>($C39+5),(M$9-$C39)<0),"",_xlfn.XLOOKUP(M$9-$C38,ChurnMatrix!$E$4:$J$4,ChurnMatrix!$E$5:$J$5))
C44: Cohort Count
C45: 1 | D45: =IFERROR(IF(D$9<($C45+6),HLOOKUP($C45,$D$9:$AA$11,3,FALSE)*D16,C45),"") -> 728 | E45: =IFERROR(IF(E$9<($C45+6),HLOOKUP($C45,$D$9:$AA$11,3,FALSE)*E16,D45),"") -> 325 | F45: =IFERROR(IF(F$9<($C45+6),HLOOKUP($C45,$D$9:$AA$11,3,FALSE)*F16,E45),"") -> 325 | G45: =IFERROR(IF(G$9<($C45+6),HLOOKUP($C45,$D$9:$AA$11,3,FALSE)*G16,F45),"") -> 299 | H45: =IFERROR(IF(H$9<($C45+6),HLOOKUP($C45,$D$9:$AA$11,3,FALSE)*H16,G45),"") -> 143 | I45: =IFERROR(IF(I$9<($C45+6),HLOOKUP($C45,$D$9:$AA$11,3,FALSE)*I16,H45),"") -> 143 | J45: =IFERROR(IF(J$9<($C45+6),HLOOKUP($C45,$D$9:$AA$11,3,FALSE)*J16,I45),"") -> 143 | K45: =IFERROR(IF(K$9<($C45+6),HLOOKUP($C45,$D$9:$AA$11,3,FALSE)*K16,J45),"") -> 143 | ... M45: =IFERROR(IF(M$9<($C45+6),HLOOKUP($C45,$D$9:$AA$11,3,FALSE)*M16,L45),"") -> 143
C46: =C45+1 -> 2 | D46: =IFERROR(IF(D$9<($C46+6),HLOOKUP($C46,$D$9:$AA$11,3,FALSE)*D17,C46),"") | E46: =IFERROR(IF(E$9<($C46+6),HLOOKUP($C46,$D$9:$AA$11,3,FALSE)*E17,D46),"") -> 1120 | F46: =IFERROR(IF(F$9<($C46+6),HLOOKUP($C46,$D$9:$AA$11,3,FALSE)*F17,E46),"") -> 500 | G46: =IFERROR(IF(G$9<($C46+6),HLOOKUP($C46,$D$9:$AA$11,3,FALSE)*G17,F46),"") -> 500 | H46: =IFERROR(IF(H$9<($C46+6),HLOOKUP($C46,$D$9:$AA$11,3,FALSE)*H17,G46),"") -> 460 | I46: =IFERROR(IF(I$9<($C46+6),HLOOKUP($C46,$D$9:$AA$11,3,FALSE)*I17,H46),"") -> 220 | J46: =IFERROR(IF(J$9<($C46+6),HLOOKUP($C46,$D$9:$AA$11,3,FALSE)*J17,I46),"") -> 220 | K46: =IFERROR(IF(K$9<($C46+6),HLOOKUP($C46,$D$9:$AA$11,3,FALSE)*K17,J46),"") -> 220 | ... M46: =IFERROR(IF(M$9<($C46+6),HLOOKUP($C46,$D$9:$AA$11,3,FALSE)*M17,L46),"") -> 220
C47: =C46+1 -> 3 | D47: =IFERROR(IF(D$9<($C47+6),HLOOKUP($C47,$D$9:$AA$11,3,FALSE)*D18,C47),"") | E47: =IFERROR(IF(E$9<($C47+6),HLOOKUP($C47,$D$9:$AA$11,3,FALSE)*E18,D47),"") | F47: =IFERROR(IF(F$9<($C47+6),HLOOKUP($C47,$D$9:$AA$11,3,FALSE)*F18,E47),"") -> 1848 | G47: =IFERROR(IF(G$9<($C47+6),HLOOKUP($C47,$D$9:$AA$11,3,FALSE)*G18,F47),"") -> 825 | H47: =IFERROR(IF(H$9<($C47+6),HLOOKUP($C47,$D$9:$AA$11,3,FALSE)*H18,G47),"") -> 825 | I47: =IFERROR(IF(I$9<($C47+6),HLOOKUP($C47,$D$9:$AA$11,3,FALSE)*I18,H47),"") -> 759 | J47: =IFERROR(IF(J$9<($C47+6),HLOOKUP($C47,$D$9:$AA$11,3,FALSE)*J18,I47),"") -> 363 | K47: =IFERROR(IF(K$9<($C47+6),HLOOKUP($C47,$D$9:$AA$11,3,FALSE)*K18,J47),"") -> 363 | ... M47: =IFERROR(IF(M$9<($C47+6),HLOOKUP($C47,$D$9:$AA$11,3,FALSE)*M18,L47),"") -> 363
C48: =C47+1 -> 4 | D48: =IFERROR(IF(D$9<($C48+6),HLOOKUP($C48,$D$9:$AA$11,3,FALSE)*D19,C48),"") | E48: =IFERROR(IF(E$9<($C48+6),HLOOKUP($C48,$D$9:$AA$11,3,FALSE)*E19,D48),"") | F48: =IFERROR(IF(F$9<($C48+6),HLOOKUP($C48,$D$9:$AA$11,3,FALSE)*F19,E48),"") | G48: =IFERROR(IF(G$9<($C48+6),HLOOKUP($C48,$D$9:$AA$11,3,FALSE)*G19,F48),"") -> 1940.4 | H48: =IFERROR(IF(H$9<($C48+6),HLOOKUP($C48,$D$9:$AA$11,3,FALSE)*H19,G48),"") -> 866.25 | I48: =IFERROR(IF(I$9<($C48+6),HLOOKUP($C48,$D$9:$AA$11,3,FALSE)*I19,H48),"") -> 866.25 | J48: =IFERROR(IF(J$9<($C48+6),HLOOKUP($C48,$D$9:$AA$11,3,FALSE)*J19,I48),"") -> 796.95 | K48: =IFERROR(IF(K$9<($C48+6),HLOOKUP($C48,$D$9:$AA$11,3,FALSE)*K19,J48),"") -> 381.15 | ... M48: =IFERROR(IF(M$9<($C48+6),HLOOKUP($C48,$D$9:$AA$11,3,FALSE)*M19,L48),"") -> 381.15
C49: =C48+1 -> 5 | D49: =IFERROR(IF(D$9<($C49+6),HLOOKUP($C49,$D$9:$AA$11,3,FALSE)*D20,C49),"") | E49: =IFERROR(IF(E$9<($C49+6),HLOOKUP($C49,$D$9:$AA$11,3,FALSE)*E20,D49),"") | F49: =IFERROR(IF(F$9<($C49+6),HLOOKUP($C49,$D$9:$AA$11,3,FALSE)*F20,E49),"") | G49: =IFERROR(IF(G$9<($C49+6),HLOOKUP($C49,$D$9:$AA$11,3,FALSE)*G20,F49),"") | H49: =IFERROR(IF(H$9<($C49+6),HLOOKUP($C49,$D$9:$AA$11,3,FALSE)*H20,G49),"") -> 2037.42 | I49: =IFERROR(IF(I$9<($C49+6),HLOOKUP($C49,$D$9:$AA$11,3,FALSE)*I20,H49),"") -> 909.5625 | J49: =IFERROR(IF(J$9<($C49+6),HLOOKUP($C49,$D$9:$AA$11,3,FALSE)*J20,I49),"") -> 909.5625 | K49: =IFERROR(IF(K$9<($C49+6),HLOOKUP($C49,$D$9:$AA$11,3,FALSE)*K20,J49),"") -> 836.7975 | ... M49: =IFERROR(IF(M$9<($C49+6),HLOOKUP($C49,$D$9:$AA$11,3,FALSE)*M20,L49),"") -> 400.2075
C50: =C49+1 -> 6 | D50: =IFERROR(IF(D$9<($C50+6),HLOOKUP($C50,$D$9:$AA$11,3,FALSE)*D21,C50),"") | E50: =IFERROR(IF(E$9<($C50+6),HLOOKUP($C50,$D$9:$AA$11,3,FALSE)*E21,D50),"") | F50: =IFERROR(IF(F$9<($C50+6),HLOOKUP($C50,$D$9:$AA$11,3,FALSE)*F21,E50),"") | G50: =IFERROR(IF(G$9<($C50+6),HLOOKUP($C50,$D$9:$AA$11,3,FALSE)*G21,F50),"") | H50: =IFERROR(IF(H$9<($C50+6),HLOOKUP($C50,$D$9:$AA$11,3,FALSE)*H21,G50),"") | I50: =IFERROR(IF(I$9<($C50+6),HLOOKUP($C50,$D$9:$AA$11,3,FALSE)*I21,H50),"") -> 2139.291 | J50: =IFERROR(IF(J$9<($C50+6),HLOOKUP($C50,$D$9:$AA$11,3,FALSE)*J21,I50),"") -> 955.04062 | K50: =IFERROR(IF(K$9<($C50+6),HLOOKUP($C50,$D$9:$AA$11,3,FALSE)*K21,J50),"") -> 955.04062 | ... M50: =IFERROR(IF(M$9<($C50+6),HLOOKUP($C50,$D$9:$AA$11,3,FALSE)*M21,L50),"") -> 420.21787
C51: =C50+1 -> 7 | D51: =IFERROR(IF(D$9<($C51+6),HLOOKUP($C51,$D$9:$AA$11,3,FALSE)*D22,C51),"") | E51: =IFERROR(IF(E$9<($C51+6),HLOOKUP($C51,$D$9:$AA$11,3,FALSE)*E22,D51),"") | F51: =IFERROR(IF(F$9<($C51+6),HLOOKUP($C51,$D$9:$AA$11,3,FALSE)*F22,E51),"") | G51: =IFERROR(IF(G$9<($C51+6),HLOOKUP($C51,$D$9:$AA$11,3,FALSE)*G22,F51),"") | H51: =IFERROR(IF(H$9<($C51+6),HLOOKUP($C51,$D$9:$AA$11,3,FALSE)*H22,G51),"") | I51: =IFERROR(IF(I$9<($C51+6),HLOOKUP($C51,$D$9:$AA$11,3,FALSE)*I22,H51),"") | J51: =IFERROR(IF(J$9<($C51+6),HLOOKUP($C51,$D$9:$AA$11,3,FALSE)*J22,I51),"") -> 2246.2556 | K51: =IFERROR(IF(K$9<($C51+6),HLOOKUP($C51,$D$9:$AA$11,3,FALSE)*K22,J51),"") -> 1002.7927 | ... M51: =IFERROR(IF(M$9<($C51+6),HLOOKUP($C51,$D$9:$AA$11,3,FALSE)*M22,L51),"") -> 922.56924
C52: =C51+1 -> 8 | D52: =IFERROR(IF(D$9<($C52+6),HLOOKUP($C52,$D$9:$AA$11,3,FALSE)*D23,C52),"") | E52: =IFERROR(IF(E$9<($C52+6),HLOOKUP($C52,$D$9:$AA$11,3,FALSE)*E23,D52),"") | F52: =IFERROR(IF(F$9<($C52+6),HLOOKUP($C52,$D$9:$AA$11,3,FALSE)*F23,E52),"") | G52: =IFERROR(IF(G$9<($C52+6),HLOOKUP($C52,$D$9:$AA$11,3,FALSE)*G23,F52),"") | H52: =IFERROR(IF(H$9<($C52+6),HLOOKUP($C52,$D$9:$AA$11,3,FALSE)*H23,G52),"") | I52: =IFERROR(IF(I$9<($C52+6),HLOOKUP($C52,$D$9:$AA$11,3,FALSE)*I23,H52),"") | J52: =IFERROR(IF(J$9<($C52+6),HLOOKUP($C52,$D$9:$AA$11,3,FALSE)*J23,I52),"") | K52: =IFERROR(IF(K$9<($C52+6),HLOOKUP($C52,$D$9:$AA$11,3,FALSE)*K23,J52),"") -> 2358.5683 | ... M52: =IFERROR(IF(M$9<($C52+6),HLOOKUP($C52,$D$9:$AA$11,3,FALSE)*M23,L52),"") -> 1052.9323
C53: =C52+1 -> 9 | D53: =IFERROR(IF(D$9<($C53+6),HLOOKUP($C53,$D$9:$AA$11,3,FALSE)*D24,C53),"") | E53: =IFERROR(IF(E$9<($C53+6),HLOOKUP($C53,$D$9:$AA$11,3,FALSE)*E24,D53),"") | F53: =IFERROR(IF(F$9<($C53+6),HLOOKUP($C53,$D$9:$AA$11,3,FALSE)*F24,E53),"") | G53: =IFERROR(IF(G$9<($C53+6),HLOOKUP($C53,$D$9:$AA$11,3,FALSE)*G24,F53),"") | H53: =IFERROR(IF(H$9<($C53+6),HLOOKUP($C53,$D$9:$AA$11,3,FALSE)*H24,G53),"") | I53: =IFERROR(IF(I$9<($C53+6),HLOOKUP($C53,$D$9:$AA$11,3,FALSE)*I24,H53),"") | J53: =IFERROR(IF(J$9<($C53+6),HLOOKUP($C53,$D$9:$AA$11,3,FALSE)*J24,I53),"") | K53: =IFERROR(IF(K$9<($C53+6),HLOOKUP($C53,$D$9:$AA$11,3,FALSE)*K24,J53),"") | ... M53: =IFERROR(IF(M$9<($C53+6),HLOOKUP($C53,$D$9:$AA$11,3,FALSE)*M24,L53),"") -> 1105.5789
C54: =C53+1 -> 10 | D54: =IFERROR(IF(D$9<($C54+6),HLOOKUP($C54,$D$9:$AA$11,3,FALSE)*D25,C54),"") | E54: =IFERROR(IF(E$9<($C54+6),HLOOKUP($C54,$D$9:$AA$11,3,FALSE)*E25,D54),"") | F54: =IFERROR(IF(F$9<($C54+6),HLOOKUP($C54,$D$9:$AA$11,3,FALSE)*F25,E54),"") | G54: =IFERROR(IF(G$9<($C54+6),HLOOKUP($C54,$D$9:$AA$11,3,FALSE)*G25,F54),"") | H54: =IFERROR(IF(H$9<($C54+6),HLOOKUP($C54,$D$9:$AA$11,3,FALSE)*H25,G54),"") | I54: =IFERROR(IF(I$9<($C54+6),HLOOKUP($C54,$D$9:$AA$11,3,FALSE)*I25,H54),"") | J54: =IFERROR(IF(J$9<($C54+6),HLOOKUP($C54,$D$9:$AA$11,3,FALSE)*J25,I54),"") | K54: =IFERROR(IF(K$9<($C54+6),HLOOKUP($C54,$D$9:$AA$11,3,FALSE)*K25,J54),"") | ... M54: =IFERROR(IF(M$9<($C54+6),HLOOKUP($C54,$D$9:$AA$11,3,FALSE)*M25,L54),"") -> 2600.3216
C55: =C54+1 -> 11 | D55: =IFERROR(IF(D$9<($C55+6),HLOOKUP($C55,$D$9:$AA$11,3,FALSE)*D26,C55),"") | E55: =IFERROR(IF(E$9<($C55+6),HLOOKUP($C55,$D$9:$AA$11,3,FALSE)*E26,D55),"") | F55: =IFERROR(IF(F$9<($C55+6),HLOOKUP($C55,$D$9:$AA$11,3,FALSE)*F26,E55),"") | G55: =IFERROR(IF(G$9<($C55+6),HLOOKUP($C55,$D$9:$AA$11,3,FALSE)*G26,F55),"") | H55: =IFERROR(IF(H$9<($C55+6),HLOOKUP($C55,$D$9:$AA$11,3,FALSE)*H26,G55),"") | I55: =IFERROR(IF(I$9<($C55+6),HLOOKUP($C55,$D$9:$AA$11,3,FALSE)*I26,H55),"") | J55: =IFERROR(IF(J$9<($C55+6),HLOOKUP($C55,$D$9:$AA$11,3,FALSE)*J26,I55),"") | K55: =IFERROR(IF(K$9<($C55+6),HLOOKUP($C55,$D$9:$AA$11,3,FALSE)*K26,J55),"") | ... M55: =IFERROR(IF(M$9<($C55+6),HLOOKUP($C55,$D$9:$AA$11,3,FALSE)*M26,L55),"")
C56: =C55+1 -> 12 | D56: =IFERROR(IF(D$9<($C56+6),HLOOKUP($C56,$D$9:$AA$11,3,FALSE)*D27,C56),"") | E56: =IFERROR(IF(E$9<($C56+6),HLOOKUP($C56,$D$9:$AA$11,3,FALSE)*E27,D56),"") | F56: =IFERROR(IF(F$9<($C56+6),HLOOKUP($C56,$D$9:$AA$11,3,FALSE)*F27,E56),"") | G56: =IFERROR(IF(G$9<($C56+6),HLOOKUP($C56,$D$9:$AA$11,3,FALSE)*G27,F56),"") | H56: =IFERROR(IF(H$9<($C56+6),HLOOKUP($C56,$D$9:$AA$11,3,FALSE)*H27,G56),"") | I56: =IFERROR(IF(I$9<($C56+6),HLOOKUP($C56,$D$9:$AA$11,3,FALSE)*I27,H56),"") | J56: =IFERROR(IF(J$9<($C56+6),HLOOKUP($C56,$D$9:$AA$11,3,FALSE)*J27,I56),"") | K56: =IFERROR(IF(K$9<($C56+6),HLOOKUP($C56,$D$9:$AA$11,3,FALSE)*K27,J56),"") | ... M56: =IFERROR(IF(M$9<($C56+6),HLOOKUP($C56,$D$9:$AA$11,3,FALSE)*M27,L56),"")
C57: =C56+1 -> 13 | D57: =IFERROR(IF(D$9<($C57+6),HLOOKUP($C57,$D$9:$AA$11,3,FALSE)*D28,C57),"") | E57: =IFERROR(IF(E$9<($C57+6),HLOOKUP($C57,$D$9:$AA$11,3,FALSE)*E28,D57),"") | F57: =IFERROR(IF(F$9<($C57+6),HLOOKUP($C57,$D$9:$AA$11,3,FALSE)*F28,E57),"") | G57: =IFERROR(IF(G$9<($C57+6),HLOOKUP($C57,$D$9:$AA$11,3,FALSE)*G28,F57),"") | H57: =IFERROR(IF(H$9<($C57+6),HLOOKUP($C57,$D$9:$AA$11,3,FALSE)*H28,G57),"") | I57: =IFERROR(IF(I$9<($C57+6),HLOOKUP($C57,$D$9:$AA$11,3,FALSE)*I28,H57),"") | J57: =IFERROR(IF(J$9<($C57+6),HLOOKUP($C57,$D$9:$AA$11,3,FALSE)*J28,I57),"") | K57: =IFERROR(IF(K$9<($C57+6),HLOOKUP($C57,$D$9:$AA$11,3,FALSE)*K28,J57),"") | ... M57: =IFERROR(IF(M$9<($C57+6),HLOOKUP($C57,$D$9:$AA$11,3,FALSE)*M28,L57),"")
... C68: =C67+1 -> 24 | D68: =IFERROR(IF(D$9<($C68+6),HLOOKUP($C68,$D$9:$AA$11,3,FALSE)*D39,C68),"") | E68: =IFERROR(IF(E$9<($C68+6),HLOOKUP($C68,$D$9:$AA$11,3,FALSE)*E39,D68),"") | F68: =IFERROR(IF(F$9<($C68+6),HLOOKUP($C68,$D$9:$AA$11,3,FALSE)*F39,E68),"") | G68: =IFERROR(IF(G$9<($C68+6),HLOOKUP($C68,$D$9:$AA$11,3,FALSE)*G39,F68),"") | H68: =IFERROR(IF(H$9<($C68+6),HLOOKUP($C68,$D$9:$AA$11,3,FALSE)*H39,G68),"") | I68: =IFERROR(IF(I$9<($C68+6),HLOOKUP($C68,$D$9:$AA$11,3,FALSE)*I39,H68),"") | J68: =IFERROR(IF(J$9<($C68+6),HLOOKUP($C68,$D$9:$AA$11,3,FALSE)*J39,I68),"") | K68: =IFERROR(IF(K$9<($C68+6),HLOOKUP($C68,$D$9:$AA$11,3,FALSE)*K39,J68),"") | ... M68: =IFERROR(IF(M$9<($C68+6),HLOOKUP($C68,$D$9:$AA$11,3,FALSE)*M39,L68),"")
C72: Cohort Attrition
C73: 1 | D73: =IF(AND(D$9>($C73),D$9<($C73+6)), D45-C45,"") | E73: =IF(AND(E$9>($C73),E$9<($C73+6)), E45-D45,"") -> -403 | F73: =IF(AND(F$9>($C73),F$9<($C73+6)), F45-E45,"") -> 0 | G73: =IF(AND(G$9>($C73),G$9<($C73+6)), G45-F45,"") -> -26 | H73: =IF(AND(H$9>($C73),H$9<($C73+6)), H45-G45,"") -> -156 | I73: =IF(AND(I$9>($C73),I$9<($C73+6)), I45-H45,"") -> 0 | J73: =IF(AND(J$9>($C73),J$9<($C73+6)), J45-I45,"") | K73: =IF(AND(K$9>($C73),K$9<($C73+6)), K45-J45,"") | ... M73: =IF(AND(M$9>($C73),M$9<($C73+6)), M45-L45,"")
C74: =C73+1 -> 2 | D74: =IF(AND(D$9>($C74),D$9<($C74+6)), D46-C46,"") | E74: =IF(AND(E$9>($C74),E$9<($C74+6)), E46-D46,"") | F74: =IF(AND(F$9>($C74),F$9<($C74+6)), F46-E46,"") -> -620 | G74: =IF(AND(G$9>($C74),G$9<($C74+6)), G46-F46,"") -> 0 | H74: =IF(AND(H$9>($C74),H$9<($C74+6)), H46-G46,"") -> -40 | I74: =IF(AND(I$9>($C74),I$9<($C74+6)), I46-H46,"") -> -240 | J74: =IF(AND(J$9>($C74),J$9<($C74+6)), J46-I46,"") -> 0 | K74: =IF(AND(K$9>($C74),K$9<($C74+6)), K46-J46,"") | ... M74: =IF(AND(M$9>($C74),M$9<($C74+6)), M46-L46,"")
C75: =C74+1 -> 3 | D75: =IF(AND(D$9>($C75),D$9<($C75+6)), D47-C47,"") | E75: =IF(AND(E$9>($C75),E$9<($C75+6)), E47-D47,"") | F75: =IF(AND(F$9>($C75),F$9<($C75+6)), F47-E47,"") | G75: =IF(AND(G$9>($C75),G$9<($C75+6)), G47-F47,"") -> -1023 | H75: =IF(AND(H$9>($C75),H$9<($C75+6)), H47-G47,"") -> 0 | I75: =IF(AND(I$9>($C75),I$9<($C75+6)), I47-H47,"") -> -66 | J75: =IF(AND(J$9>($C75),J$9<($C75+6)), J47-I47,"") -> -396 | K75: =IF(AND(K$9>($C75),K$9<($C75+6)), K47-J47,"") -> 0 | ... M75: =IF(AND(M$9>($C75),M$9<($C75+6)), M47-L47,"")
C76: =C75+1 -> 4 | D76: =IF(AND(D$9>($C76),D$9<($C76+6)), D48-C48,"") | E76: =IF(AND(E$9>($C76),E$9<($C76+6)), E48-D48,"") | F76: =IF(AND(F$9>($C76),F$9<($C76+6)), F48-E48,"") | G76: =IF(AND(G$9>($C76),G$9<($C76+6)), G48-F48,"") | H76: =IF(AND(H$9>($C76),H$9<($C76+6)), H48-G48,"") -> -1074.15 | I76: =IF(AND(I$9>($C76),I$9<($C76+6)), I48-H48,"") -> 0 | J76: =IF(AND(J$9>($C76),J$9<($C76+6)), J48-I48,"") -> -69.3 | K76: =IF(AND(K$9>($C76),K$9<($C76+6)), K48-J48,"") -> -415.8 | ... M76: =IF(AND(M$9>($C76),M$9<($C76+6)), M48-L48,"")
C77: =C76+1 -> 5 | D77: =IF(AND(D$9>($C77),D$9<($C77+6)), D49-C49,"") | E77: =IF(AND(E$9>($C77),E$9<($C77+6)), E49-D49,"") | F77: =IF(AND(F$9>($C77),F$9<($C77+6)), F49-E49,"") | G77: =IF(AND(G$9>($C77),G$9<($C77+6)), G49-F49,"") | H77: =IF(AND(H$9>($C77),H$9<($C77+6)), H49-G49,"") | I77: =IF(AND(I$9>($C77),I$9<($C77+6)), I49-H49,"") -> -1127.8575 | J77: =IF(AND(J$9>($C77),J$9<($C77+6)), J49-I49,"") -> 0 | K77: =IF(AND(K$9>($C77),K$9<($C77+6)), K49-J49,"") -> -72.765 | ... M77: =IF(AND(M$9>($C77),M$9<($C77+6)), M49-L49,"") -> 0
C78: =C77+1 -> 6 | D78: =IF(AND(D$9>($C78),D$9<($C78+6)), D50-C50,"") | E78: =IF(AND(E$9>($C78),E$9<($C78+6)), E50-D50,"") | F78: =IF(AND(F$9>($C78),F$9<($C78+6)), F50-E50,"") | G78: =IF(AND(G$9>($C78),G$9<($C78+6)), G50-F50,"") | H78: =IF(AND(H$9>($C78),H$9<($C78+6)), H50-G50,"") | I78: =IF(AND(I$9>($C78),I$9<($C78+6)), I50-H50,"") | J78: =IF(AND(J$9>($C78),J$9<($C78+6)), J50-I50,"") -> -1184.2504 | K78: =IF(AND(K$9>($C78),K$9<($C78+6)), K50-J50,"") -> 0 | ... M78: =IF(AND(M$9>($C78),M$9<($C78+6)), M50-L50,"") -> -458.4195
C79: =C78+1 -> 7 | D79: =IF(AND(D$9>($C79),D$9<($C79+6)), D51-C51,"") | E79: =IF(AND(E$9>($C79),E$9<($C79+6)), E51-D51,"") | F79: =IF(AND(F$9>($C79),F$9<($C79+6)), F51-E51,"") | G79: =IF(AND(G$9>($C79),G$9<($C79+6)), G51-F51,"") | H79: =IF(AND(H$9>($C79),H$9<($C79+6)), H51-G51,"") | I79: =IF(AND(I$9>($C79),I$9<($C79+6)), I51-H51,"") | J79: =IF(AND(J$9>($C79),J$9<($C79+6)), J51-I51,"") | K79: =IF(AND(K$9>($C79),K$9<($C79+6)), K51-J51,"") -> -1243.4629 | ... M79: =IF(AND(M$9>($C79),M$9<($C79+6)), M51-L51,"") -> -80.223412
C80: =C79+1 -> 8 | D80: =IF(AND(D$9>($C80),D$9<($C80+6)), D52-C52,"") | E80: =IF(AND(E$9>($C80),E$9<($C80+6)), E52-D52,"") | F80: =IF(AND(F$9>($C80),F$9<($C80+6)), F52-E52,"") | G80: =IF(AND(G$9>($C80),G$9<($C80+6)), G52-F52,"") | H80: =IF(AND(H$9>($C80),H$9<($C80+6)), H52-G52,"") | I80: =IF(AND(I$9>($C80),I$9<($C80+6)), I52-H52,"") | J80: =IF(AND(J$9>($C80),J$9<($C80+6)), J52-I52,"") | K80: =IF(AND(K$9>($C80),K$9<($C80+6)), K52-J52,"") | ... M80: =IF(AND(M$9>($C80),M$9<($C80+6)), M52-L52,"") -> 0
C81: =C80+1 -> 9 | D81: =IF(AND(D$9>($C81),D$9<($C81+6)), D53-C53,"") | E81: =IF(AND(E$9>($C81),E$9<($C81+6)), E53-D53,"") | F81: =IF(AND(F$9>($C81),F$9<($C81+6)), F53-E53,"") | G81: =IF(AND(G$9>($C81),G$9<($C81+6)), G53-F53,"") | H81: =IF(AND(H$9>($C81),H$9<($C81+6)), H53-G53,"") | I81: =IF(AND(I$9>($C81),I$9<($C81+6)), I53-H53,"") | J81: =IF(AND(J$9>($C81),J$9<($C81+6)), J53-I53,"") | K81: =IF(AND(K$9>($C81),K$9<($C81+6)), K53-J53,"") | ... M81: =IF(AND(M$9>($C81),M$9<($C81+6)), M53-L53,"") -> -1370.9178
C82: =C81+1 -> 10 | D82: =IF(AND(D$9>($C82),D$9<($C82+6)), D54-C54,"") | E82: =IF(AND(E$9>($C82),E$9<($C82+6)), E54-D54,"") | F82: =IF(AND(F$9>($C82),F$9<($C82+6)), F54-E54,"") | G82: =IF(AND(G$9>($C82),G$9<($C82+6)), G54-F54,"") | H82: =IF(AND(H$9>($C82),H$9<($C82+6)), H54-G54,"") | I82: =IF(AND(I$9>($C82),I$9<($C82+6)), I54-H54,"") | J82: =IF(AND(J$9>($C82),J$9<($C82+6)), J54-I54,"") | K82: =IF(AND(K$9>($C82),K$9<($C82+6)), K54-J54,"") | ... M82: =IF(AND(M$9>($C82),M$9<($C82+6)), M54-L54,"")
C83: =C82+1 -> 11 | D83: =IF(AND(D$9>($C83),D$9<($C83+6)), D55-C55,"") | E83: =IF(AND(E$9>($C83),E$9<($C83+6)), E55-D55,"") | F83: =IF(AND(F$9>($C83),F$9<($C83+6)), F55-E55,"") | G83: =IF(AND(G$9>($C83),G$9<($C83+6)), G55-F55,"") | H83: =IF(AND(H$9>($C83),H$9<($C83+6)), H55-G55,"") | I83: =IF(AND(I$9>($C83),I$9<($C83+6)), I55-H55,"") | J83: =IF(AND(J$9>($C83),J$9<($C83+6)), J55-I55,"") | K83: =IF(AND(K$9>($C83),K$9<($C83+6)), K55-J55,"") | ... M83: =IF(AND(M$9>($C83),M$9<($C83+6)), M55-L55,"")
C84: =C83+1 -> 12 | D84: =IF(AND(D$9>($C84),D$9<($C84+6)), D56-C56,"") | E84: =IF(AND(E$9>($C84),E$9<($C84+6)), E56-D56,"") | F84: =IF(AND(F$9>($C84),F$9<($C84+6)), F56-E56,"") | G84: =IF(AND(G$9>($C84),G$9<($C84+6)), G56-F56,"") | H84: =IF(AND(H$9>($C84),H$9<($C84+6)), H56-G56,"") | I84: =IF(AND(I$9>($C84),I$9<($C84+6)), I56-H56,"") | J84: =IF(AND(J$9>($C84),J$9<($C84+6)), J56-I56,"") | K84: =IF(AND(K$9>($C84),K$9<($C84+6)), K56-J56,"") | ... M84: =IF(AND(M$9>($C84),M$9<($C84+6)), M56-L56,"")
C85: =C84+1 -> 13 | D85: =IF(AND(D$9>($C85),D$9<($C85+6)), D57-C57,"") | E85: =IF(AND(E$9>($C85),E$9<($C85+6)), E57-D57,"") | F85: =IF(AND(F$9>($C85),F$9<($C85+6)), F57-E57,"") | G85: =IF(AND(G$9>($C85),G$9<($C85+6)), G57-F57,"") | H85: =IF(AND(H$9>($C85),H$9<($C85+6)), H57-G57,"") | I85: =IF(AND(I$9>($C85),I$9<($C85+6)), I57-H57,"") | J85: =IF(AND(J$9>($C85),J$9<($C85+6)), J57-I57,"") | K85: =IF(AND(K$9>($C85),K$9<($C85+6)), K57-J57,"") | ... M85: =IF(AND(M$9>($C85),M$9<($C85+6)), M57-L57,"")
... C96: =C95+1 -> 24 | D96: =IF(AND(D$9>($C96),D$9<($C96+6)), D68-C68,"") | E96: =IF(AND(E$9>($C96),E$9<($C96+6)), E68-D68,"") | F96: =IF(AND(F$9>($C96),F$9<($C96+6)), F68-E68,"") | G96: =IF(AND(G$9>($C96),G$9<($C96+6)), G68-F68,"") | H96: =IF(AND(H$9>($C96),H$9<($C96+6)), H68-G68,"") | I96: =IF(AND(I$9>($C96),I$9<($C96+6)), I68-H68,"") | J96: =IF(AND(J$9>($C96),J$9<($C96+6)), J68-I68,"") | K96: =IF(AND(K$9>($C96),K$9<($C96+6)), K68-J68,"") | ... M96: =IF(AND(M$9>($C96),M$9<($C96+6)), M68-L68,"")
C98: Total Attrition | D98: =SUM(D73:D96) -> 0 | E98: =SUM(E73:E96) -> -403 | F98: =SUM(F73:F96) -> -620 | G98: =SUM(G73:G96) -> -1049 | H98: =SUM(H73:H96) -> -1270.15 | I98: =SUM(I73:I96) -> -1433.8575 | J98: =SUM(J73:J96) -> -1649.5504 | K98: =SUM(K73:K96) -> -1732.0279 | ... M98: =SUM(M73:M96) -> -1909.5608
C100: Attrition % | D100: =D98/D13 -> 0 | E100: =E98/E13 -> -0.13910942 | F100: =F98/F13 -> -0.11117088 | G100: =G98/G13 -> -0.13123983 | H100: =H98/H13 -> -0.12258834 | I100: =I98/I13 -> -0.11248231 | J100: =J98/J13 -> -0.10917649 | K100: =K98/K13 -> -0.098473752 | ... M100: =M98/M13 -> -0.083291335
C101: Adoption Rate % | D101: =D11/D13 -> 1 | E101: =E11/E13 -> 0.69036935 | F101: =F11/F13 -> 0.59171598 | G101: =G11/G13 -> 0.43350432 | H101: =H11/H13 -> 0.35114515 | I101: =I11/I13 -> 0.29968158 | J101: =J11/J13 -> 0.26548176 | K101: =K11/K13 -> 0.23945617 | ... M101: =M11/M13 -> 0.20253747

Sheet ModelDrivers
C3: EV Market growth | E3: 0.05 | G3: Month | H3: User Retention
B4: Assume % of customers we could get from our potetnial pool | C4: Activation % | E4: 0.05 | G4: 1 | H4: 0.56
C5: Subscription Conversion % | E5: 0.02 | G5: =G4+1 -> 2 | H5: 0.25
G6: =G5+1 -> 3 | H6: 0.25
G7: =G6+1 -> 4 | H7: 0.23
D8: Assume Price / customer | E8: Assume % Subs in Plan | G8: =G7+1 -> 5 | H8: 0.11
C9: Plan A | D9: 100 | E9: 0.6 | G9: =G8+1 -> 6 | H9: 0.11
C10: Plan B | D10: 120 | E10: 0.3
C11: Plan C | D11: 140 | E11: =1- SUM(E9:E10) -> 0.1
C21: Fixed Monthly Information | G21: Daily Labor Costs
C22: Rent | D22: 2000 | G22: Items | H22: Rate | I22: Qty | J22: Total Pay
C23: Electric | D23: 150 | G23: Taxes | H23: 40 | I23: 8 | J23: =H23*I23 -> 320
C24: Phone | D24: 100 | G24: Tool Cost | H24: 50 | I24: 4 | J24: =H24*I24 -> 200
C25: Internet | D25: 150 | G25: Battery Replacement | H25: 89.99 | I25: 4 | J25: =H25*I25 -> 359.96
C26: Water | D26: 50 | G26: Parking Charges | H26: 25 | I26: 1 | J26: =H26*I26 -> 25
C27: Insurance | D27: 150 | G27: Recycling | H27: 89.99 | I27: 4 | J27: =H27*I27 -> 359.96
C28: Accounting/Legal | D28: 100 | G28: Meals | H28: 200 | I28: 1 | J28: =H28*I28 -> 200
C29: Advertising | D29: 250 | G29: Toll fees | H29: 8 | I29: 23 | J29: =H29*I29 -> 184
C30: Other | D30: 300 | G30: Travel Expenses | H30: 50 | I30: 11 | J30: =H30*I30 -> 550
C31: Total | D31: =SUM(D22:D30) -> 3250 | G31: Total | H31: =SUM(H23:H30) -> 552.98 | I31: 1000 | J31: =SUM(J23:J30) -> 2198.92

Sheet PB_CACHE
A1: H4sIAAAAAAAEAO2YC3RT9R3Hc+kzoeALkW1qr2KBag1N0gftivSRtNSW9JG2gF3XJumFht4m9SZhbTluqMA2cThQ5mBwcMoUJlNU5HGkOHFjOhRxPjZ22EDEeTjOzfmAHTjW/f6X/P73l5jk3KP1nB0POafJ/58mn9/r+/v9741BMBgMn8GDvbJH1hh4amr0hbw9lYFAr9gy2C8FxXqfR3Erg3lim6QEfQH/TGu+tdBsM+eb8/PEqrAcCivSTL8UDiluOU9sDHtkn7dOGmwJ9Er+mf6wLKcxvotjO1VsZwRrdkmKzy37htweWapye3ukz79zQ0ugv15aLMnqzu7zhsAN+G4qcDMiXmVWBfr63YqkZM52B3tcviFpHDjR5pbDUqPbpwQNKYaUzDWCazAYkvrMVQFZllRM0Fwj+cGgF18dt4bBeGgQeV2W9vbIt1whxedfmCf2Bb0BRfZ5tJQUsGzoyYenuNhd6C0sspTYCqT8GSUdHZm/HpPEKRpDl/Ur9SSv/cuUKKY0YG60ZdTR0d7BBMrUZEyBJ/ZnZBpIZav/x9qypspgHqpOs7+ULReqrbPaqedgNF1Il950sdZI6ZUG0xazlAipdaPoMGOnp7MnV48khSzGDFinsafRtPL1GOcPf30U2w3nrs/7FY7yMhzl89nCyOpvxGnJ/pey+UIy9UzK0zApL6Tqi0zJmlFyVp2QY+FJdFa4SsWqZkebUwqJdskTqm7KL55uKZrOnG112bPGwafmOga8kmz3u821/pC0UHGzcmlxWcwWfUEtsFoLpZKiwpIZhcVSt0fKGg/wiuqA0ucOBb/EFfvHIKjRSg3r74llqvxu6u3srHR7e0F01T5J7r6yzC4FvYqvn4Uf+88rys7HEfv+GCH1skiEZpV6fsMiZ1UwXgRPprQPIIJ4H2OjJUMtfmenIXN85DJS+Dd8nHVR+qWwm+qa7SgV8yFpJQUtgZBbFpvh7sMPiOhSCu/DN1iqMtMtO+e9tO/Q5ZUm4Z+wZ8bTGPY9xE5k0misdc4rFZ119RVNjsraFntFLO9UhGecxGIQ3o2gVA//gahvMRTxMD7qJHcte+nCg+PPvllhEt6mrp1AXjbsLI6W5lKxrWGuDc7JvoBfdPXAYRkUG8KhYMjt72a5jzFwnBuA72+a9tYwGDhGDfwdDUyG3dW8LeK7exQjz1Ej/yuN/AiCpjFPKxvmlIqFNqutwMY6rNbvDfRJ4jQnqy5IUOrOjWX/mXv6t+vSM852rgFP36SevoEG8rQGdjidCRpYeI1G3rXzIx/w/kR5ryIvH3bZKq+mpjkR7hWK6xHffRJwhyjuZcQVwC4/IqJmu0Nn+Acp32D4qOg5k/BHyn8R+TNgNz0qfB34P3B838Ci3JflVsAfoPjfI56d6Dkqfk5rvTNpYz0f5XP2iWbIyX4KfQ6h5dxnBtXp87Mc/5179uceWXkn+LyP4ocRb+c+V93saEnq8zMo4WpVwnuohHcjrxZ216EikuJ20hSUl7WtghQ8TX3cgcw5bGSR2ZIU+yR62aB6uZ16+TgSm2F3TbTQ4in3N1FV2jE8BGncRl18FIFtsLsKw44/AbZGwdaH5kO8WyjsEYTdwtoAYbrn1a8of/Xe9U8AfzPlP4T878LORsaMbhO/pCY+fKduL5h4gJrYhCY8bNDwmZsovxs5b0btofktj82C42UD5f0CeQtgZ6aDRkcTrItK+P2vdkP1fk7p9yN9EZu75MTRaWAtN/DgnnG71+w9DOm4jxq4Fw34mQF+QujO92rUcr+q5XuollchOwi7ydrxJgeCktgI18Sf64y7ubuH903M3VDTXm4SVlJ370Lk91gTa+2RhPkjzrSpjzOzTMIPKXMFMpfA7tqYHMfTxDJO3HisY9d9L2btNwl3UuIdSPwBSyoZCzqrthSTerua1O/TpN6G7GXaQQljMZGvSxC1QkUNUtQAon7MBnhUK+hwcjHPwo5nL37B1/o2SCtMsxBC/E/4xQc7H+KPHoV2QteSw+w4uJXS+pG2mh0HpEpJSu/n0J5VN25f/9NqkFMfhcoIXcugpFBJoIs49NjxsfduveMJ0JOPQnsQuo5B6RBLDF3AoT8Tt+dIR8rBU4lCuxG6kU1G6qneTvWgEjapSuiiSuhE+oPa5UdEVDqU0IHkzSq5nZJvQfIjsJuiNWzSA3Je1Fg0qNS5NBttSH2UZYOKQW82WoiJD6ZmD3wM6nVRE81o4nGmXt4c8dXbyGn2laa1r0xOg1OigdKcSHuKj1nWC7rdrY/KyNJ/PQ/6qKMGbkYDu9gQ4ydzYsXN5sRPT4ePb7jkDZBxDSVWI/EZTRORW2odmrCjJobV6lVSTVQg+bfsqok0SFJRzOIOV+e0TgrPew0qdhN1eCZif8eOGy3HiXPwbY6cMOvA0aeX7YUclFJkCSJf0E5HuCzXXbbiqKl2MHAb+FxEDRSigZdgZyXnmV4LtihhLH/KDxas1IIFLRzWbgEhhPg6nk5pSx/6sAmmsJnSbkTa6zzHakIS5/gGjhw8NcWSue0k5Ph6isxF5F80JLsCSYycypG7r17+XtPuy6AZplBkDiKParcO4GVSeU2OSuTW+eWQyGsp9BqEHmcdFnOoxzt6s7EFTqgtcBVtgSsR9g6DxdxPx4N9k7v3+sCeNcs7ToJ736DuTULiKXZdQIjxKz2R8w7U7fpk3ZYtwLuc8iYg731296cpMz7u0qjsDQxZQTiXUNzFiPsPKwkfp0lLMp5DpXMPB64YscJUHUehWQj9RKszSCcp1IRVOaNWJZNWJQN5Z/m1Fd7RxqtJGg36gZXbFkMOU6l/Kcgb0aQNx2oSaQscOfutoQmP1aSDtA0U+dlIBDlG4BOJIfXOi09HIuGnCiz8cyMk/LPIzhD4qAB2/Ir/F0FGFXSagNLYz3/Z8X5eNatvOhQloET9CJjBfpC9HkQMLxedX+Zoy2pt2aAt+7Xl7dpyhbbcpC03a8thbXlCW57RliwxkaWRL8f+D6dCpn6pIQAA

Sheet P&Lv2
B3: x
D4: A | E4: A | F4: A | G4: P | H4: P | I4: P | J4: P | K4: P | L4: P | M4: P | N4: P | O4: P
C5: Yr | D5: 1 | E5: 2 | F5: 3 | G5: 4 | H5: 5 | I5: 6 | J5: 7 | K5: 8 | L5: 9 | M5: 10 | N5: 11 | O5: 12
B6: x | C6: Growth Forecast
C7: Total People who own an EV | D7: =(1.3*10^6) -> 1300000 | E7: =(2*10^6) -> 2000000 | F7: =3.3*10 ^6 -> 3300000 | G7: =F7*(1+ModelDrivers!$E$3) -> 3465000 | H7: =G7*(1+ModelDrivers!$E$3) -> 3638250 | I7: =H7*(1+ModelDrivers!$E$3) -> 3820162.5 | J7: =I7*(1+ModelDrivers!$E$3) -> 4011170.6 | K7: =J7*(1+ModelDrivers!$E$3) -> 4211729.2 | L7: =K7*(1+ModelDrivers!$E$3) -> 4422315.6 | M7: =L7*(1+ModelDrivers!$E$3) -> 4643431.4 | N7: =M7*(1+ModelDrivers!$E$3) -> 4875603 | O7: =N7*(1+ModelDrivers!$E$3) -> 5119383.1
C8: EV Market growth | E8: =(E7/D7)-1 -> 0.53846154 | F8: =(F7/E7)-1 -> 0.65 | G8: =(G7/F7)-1 -> 0.05 | H8: =(H7/G7)-1 -> 0.05 | I8: =(I7/H7)-1 -> 0.05 | J8: =(J7/I7)-1 -> 0.05 | K8: =(K7/J7)-1 -> 0.05 | L8: =(L7/K7)-1 -> 0.05 | ... O8: =(O7/N7)-1 -> 0.05 | Q8: Ref Growth Forecast
C9: Penetration % | D9: =ModelDrivers!E4 -> 0.05 | E9: =D9 -> 0.05 | F9: =E9 -> 0.05 | G9: =F9 -> 0.05 | H9: =G9 -> 0.05 | I9: =H9 -> 0.05 | J9: =I9 -> 0.05 | K9: =J9 -> 0.05 | L9: =K9 -> 0.05 | ... O9: =N9 -> 0.05
C11: Potential Customers thru Ads | D11: =D7*D$9 -> 65000 | E11: =E7*E$9 -> 100000 | F11: =F7*F$9 -> 165000 | G11: =G7*G$9 -> 173250 | H11: =H7*H$9 -> 181912.5 | I11: =I7*I$9 -> 191008.12 | J11: =J7*J$9 -> 200558.53 | K11: =K7*K$9 -> 210586.46 | ... O11: =O7*O$9 -> 255969.16
C13: Subscription Conversion % | D13: =ModelDrivers!E5 -> 0.02 | E13: =D13 -> 0.02 | F13: =E13 -> 0.02 | G13: =F13 -> 0.02 | H13: =G13 -> 0.02 | I13: =H13 -> 0.02 | J13: =I13 -> 0.02 | K13: =J13 -> 0.02 | L13: =K13 -> 0.02 | ... O13: =N13 -> 0.02 | Q13: Ref Headcount Forecast
C15: NEW Yearly Number of Subscribers | D15: =(D13)*D11 -> 1300 | E15: =(E13)*E11 -> 2000 | F15: =(F13)*F11 -> 3300 | G15: =(G13)*G11 -> 3465 | H15: =(H13)*H11 -> 3638.25 | I15: =(I13)*I11 -> 3820.1625 | J15: =(J13)*J11 -> 4011.1706 | K15: =(K13)*K11 -> 4211.7292 | ... O15: =(O13)*O11 -> 5119.3831
C17: Total Customers | D17: =D15 -> 1300 | E17: =(E15+D17) +E107 -> 2897 | F17: =(F15+E17) +F107 -> 5577 | G17: =(G15+F17) +G107 -> 7993 | H17: =(H15+G17) +H107 -> 10361.1 | I17: =(I15+H17) +I107 -> 12747.405 | J17: =(J15+I17) +J107 -> 15109.025 | K17: =(K15+J17) +K107 -> 17588.727 | L17: =(L15+K17) +L107 -> 20192.413 | ... O17: =(O15+N17) +O107 -> 28810.94
B21: x | C21: Cohort Retention
C22: 1 | D22: =ChurnMatrix!E5 -> 0.56 | E22: =ChurnMatrix!F5 -> 0.25 | F22: =ChurnMatrix!G5 -> 0.25 | G22: =ChurnMatrix!H5 -> 0.23 | H22: =ChurnMatrix!I5 -> 0.11 | I22: =ChurnMatrix!J5 -> 0.11
C23: =C22+1 -> 2 | D23: =IF(OR(D$5>($C23+5),(D$5-$C23)<0),"",_xlfn.XLOOKUP(D$5-$C22,ModelDrivers!$G$4:$G$9,ModelDrivers!$H$4:$H$9)) | E23: =IF(OR(E$5>($C23+5),(E$5-$C23)<0),"",_xlfn.XLOOKUP(E$5-$C22,ModelDrivers!$G$4:$G$9,ModelDrivers!$H$4:$H$9)) -> 0.56 | F23: =IF(OR(F$5>($C23+5),(F$5-$C23)<0),"",_xlfn.XLOOKUP(F$5-$C22,ModelDrivers!$G$4:$G$9,ModelDrivers!$H$4:$H$9)) -> 0.25 | G23: =IF(OR(G$5>($C23+5),(G$5-$C23)<0),"",_xlfn.XLOOKUP(G$5-$C22,ModelDrivers!$G$4:$G$9,ModelDrivers!$H$4:$H$9)) -> 0.25 | H23: =IF(OR(H$5>($C23+5),(H$5-$C23)<0),"",_xlfn.XLOOKUP(H$5-$C22,ModelDrivers!$G$4:$G$9,ModelDrivers!$H$4:$H$9)) -> 0.23 | I23: =IF(OR(I$5>($C23+5),(I$5-$C23)<0),"",_xlfn.XLOOKUP(I$5-$C22,ModelDrivers!$G$4:$G$9,ModelDrivers!$H$4:$H$9)) -> 0.11 | J23: =IF(OR(J$5>($C23+5),(J$5-$C23)<0),"",_xlfn.XLOOKUP(J$5-$C22,ModelDrivers!$G$4:$G$9,ModelDrivers!$H$4:$H$9)) -> 0.11 | K23: =IF(OR(K$5>($C23+5),(K$5-$C23)<0),"",_xlfn.XLOOKUP(K$5-$C22,ModelDrivers!$G$4:$G$9,ModelDrivers!$H$4:$H$9)) | ... O23: =IF(OR(O$5>($C23+5),(O$5-$C23)<0),"",_xlfn.XLOOKUP(O$5-$C22,ModelDrivers!$G$4:$G$9,ModelDrivers!$H$4:$H$9))
C24: =C23+1 -> 3 | D24: =IF(OR(D$5>($C24+5),(D$5-$C24)<0),"",_xlfn.XLOOKUP(D$5-$C23,ModelDrivers!$G$4:$G$9,ModelDrivers!$H$4:$H$9)) | E24: =IF(OR(E$5>($C24+5),(E$5-$C24)<0),"",_xlfn.XLOOKUP(E$5-$C23,ModelDrivers!$G$4:$G$9,ModelDrivers!$H$4:$H$9)) | F24: =IF(OR(F$5>($C24+5),(F$5-$C24)<0),"",_xlfn.XLOOKUP(F$5-$C23,ModelDrivers!$G$4:$G$9,ModelDrivers!$H$4:$H$9)) -> 0.56 | G24: =IF(OR(G$5>($C24+5),(G$5-$C24)<0),"",_xlfn.XLOOKUP(G$5-$C23,ModelDrivers!$G$4:$G$9,ModelDrivers!$H$4:$H$9)) -> 0.25 | H24: =IF(OR(H$5>($C24+5),(H$5-$C24)<0),"",_xlfn.XLOOKUP(H$5-$C23,ModelDrivers!$G$4:$G$9,ModelDrivers!$H$4:$H$9)) -> 0.25 | I24: =IF(OR(I$5>($C24+5),(I$5-$C24)<0),"",_xlfn.XLOOKUP(I$5-$C23,ModelDrivers!$G$4:$G$9,ModelDrivers!$H$4:$H$9)) -> 0.23 | J24: =IF(OR(J$5>($C24+5),(J$5-$C24)<0),"",_xlfn.XLOOKUP(J$5-$C23,ModelDrivers!$G$4:$G$9,ModelDrivers!$H$4:$H$9)) -> 0.11 | K24: =IF(OR(K$5>($C24+5),(K$5-$C24)<0),"",_xlfn.XLOOKUP(K$5-$C23,ModelDrivers!$G$4:$G$9,ModelDrivers!$H$4:$H$9)) -> 0.11 | ... O24: =IF(OR(O$5>($C24+5),(O$5-$C24)<0),"",_xlfn.XLOOKUP(O$5-$C23,ModelDrivers!$G$4:$G$9,ModelDrivers!$H$4:$H$9))
C25: =C24+1 -> 4 | D25: =IF(OR(D$5>($C25+5),(D$5-$C25)<0),"",_xlfn.XLOOKUP(D$5-$C24,ModelDrivers!$G$4:$G$9,ModelDrivers!$H$4:$H$9)) | E25: =IF(OR(E$5>($C25+5),(E$5-$C25)<0),"",_xlfn.XLOOKUP(E$5-$C24,ModelDrivers!$G$4:$G$9,ModelDrivers!$H$4:$H$9)) | F25: =IF(OR(F$5>($C25+5),(F$5-$C25)<0),"",_xlfn.XLOOKUP(F$5-$C24,ModelDrivers!$G$4:$G$9,ModelDrivers!$H$4:$H$9)) | G25: =IF(OR(G$5>($C25+5),(G$5-$C25)<0),"",_xlfn.XLOOKUP(G$5-$C24,ModelDrivers!$G$4:$G$9,ModelDrivers!$H$4:$H$9)) -> 0.56 | H25: =IF(OR(H$5>($C25+5),(H$5-$C25)<0),"",_xlfn.XLOOKUP(H$5-$C24,ModelDrivers!$G$4:$G$9,ModelDrivers!$H$4:$H$9)) -> 0.25 | I25: =IF(OR(I$5>($C25+5),(I$5-$C25)<0),"",_xlfn.XLOOKUP(I$5-$C24,ModelDrivers!$G$4:$G$9,ModelDrivers!$H$4:$H$9)) -> 0.25 | J25: =IF(OR(J$5>($C25+5),(J$5-$C25)<0),"",_xlfn.XLOOKUP(J$5-$C24,ModelDrivers!$G$4:$G$9,ModelDrivers!$H$4:$H$9)) -> 0.23 | K25: =IF(OR(K$5>($C25+5),(K$5-$C25)<0),"",_xlfn.XLOOKUP(K$5-$C24,ModelDrivers!$G$4:$G$9,ModelDrivers!$H$4:$H$9)) -> 0.11 | ... O25: =IF(OR(O$5>($C25+5),(O$5-$C25)<0),"",_xlfn.XLOOKUP(O$5-$C24,ModelDrivers!$G$4:$G$9,ModelDrivers!$H$4:$H$9))
C26: =C25+1 -> 5 | D26: =IF(OR(D$5>($C26+5),(D$5-$C26)<0),"",_xlfn.XLOOKUP(D$5-$C25,ModelDrivers!$G$4:$G$9,ModelDrivers!$H$4:$H$9)) | E26: =IF(OR(E$5>($C26+5),(E$5-$C26)<0),"",_xlfn.XLOOKUP(E$5-$C25,ModelDrivers!$G$4:$G$9,ModelDrivers!$H$4:$H$9)) | F26: =IF(OR(F$5>($C26+5),(F$5-$C26)<0),"",_xlfn.XLOOKUP(F$5-$C25,ModelDrivers!$G$4:$G$9,ModelDrivers!$H$4:$H$9)) | G26: =IF(OR(G$5>($C26+5),(G$5-$C26)<0),"",_xlfn.XLOOKUP(G$5-$C25,ModelDrivers!$G$4:$G$9,ModelDrivers!$H$4:$H$9)) | H26: =IF(OR(H$5>($C26+5),(H$5-$C26)<0),"",_xlfn.XLOOKUP(H$5-$C25,ModelDrivers!$G$4:$G$9,ModelDrivers!$H$4:$H$9)) -> 0.56 | I26: =IF(OR(I$5>($C26+5),(I$5-$C26)<0),"",_xlfn.XLOOKUP(I$5-$C25,ModelDrivers!$G$4:$G$9,ModelDrivers!$H$4:$H$9)) -> 0.25 | J26: =IF(OR(J$5>($C26+5),(J$5-$C26)<0),"",_xlfn.XLOOKUP(J$5-$C25,ModelDrivers!$G$4:$G$9,ModelDrivers!$H$4:$H$9)) -> 0.25 | K26: =IF(OR(K$5>($C26+5),(K$5-$C26)<0),"",_xlfn.XLOOKUP(K$5-$C25,ModelDrivers!$G$4:$G$9,ModelDrivers!$H$4:$H$9)) -> 0.23 | ... O26: =IF(OR(O$5>($C26+5),(O$5-$C26)<0),"",_xlfn.XLOOKUP(O$5-$C25,ModelDrivers!$G$4:$G$9,ModelDrivers!$H$4:$H$9))
C27: =C26+1 -> 6 | D27: =IF(OR(D$5>($C27+5),(D$5-$C27)<0),"",_xlfn.XLOOKUP(D$5-$C26,ModelDrivers!$G$4:$G$9,ModelDrivers!$H$4:$H$9)) | E27: =IF(OR(E$5>($C27+5),(E$5-$C27)<0),"",_xlfn.XLOOKUP(E$5-$C26,ModelDrivers!$G$4:$G$9,ModelDrivers!$H$4:$H$9)) | F27: =IF(OR(F$5>($C27+5),(F$5-$C27)<0),"",_xlfn.XLOOKUP(F$5-$C26,ModelDrivers!$G$4:$G$9,ModelDrivers!$H$4:$H$9)) | G27: =IF(OR(G$5>($C27+5),(G$5-$C27)<0),"",_xlfn.XLOOKUP(G$5-$C26,ModelDrivers!$G$4:$G$9,ModelDrivers!$H$4:$H$9)) | H27: =IF(OR(H$5>($C27+5),(H$5-$C27)<0),"",_xlfn.XLOOKUP(H$5-$C26,ModelDrivers!$G$4:$G$9,ModelDrivers!$H$4:$H$9)) | I27: =IF(OR(I$5>($C27+5),(I$5-$C27)<0),"",_xlfn.XLOOKUP(I$5-$C26,ModelDrivers!$G$4:$G$9,ModelDrivers!$H$4:$H$9)) -> 0.56 | J27: =IF(OR(J$5>($C27+5),(J$5-$C27)<0),"",_xlfn.XLOOKUP(J$5-$C26,ModelDrivers!$G$4:$G$9,ModelDrivers!$H$4:$H$9)) -> 0.25 | K27: =IF(OR(K$5>($C27+5),(K$5-$C27)<0),"",_xlfn.XLOOKUP(K$5-$C26,ModelDrivers!$G$4:$G$9,ModelDrivers!$H$4:$H$9)) -> 0.25 | ... O27: =IF(OR(O$5>($C27+5),(O$5-$C27)<0),"",_xlfn.XLOOKUP(O$5-$C26,ModelDrivers!$G$4:$G$9,ModelDrivers!$H$4:$H$9))
C28: =C27+1 -> 7 | D28: =IF(OR(D$5>($C28+5),(D$5-$C28)<0),"",_xlfn.XLOOKUP(D$5-$C27,ModelDrivers!$G$4:$G$9,ModelDrivers!$H$4:$H$9)) | E28: =IF(OR(E$5>($C28+5),(E$5-$C28)<0),"",_xlfn.XLOOKUP(E$5-$C27,ModelDrivers!$G$4:$G$9,ModelDrivers!$H$4:$H$9)) | F28: =IF(OR(F$5>($C28+5),(F$5-$C28)<0),"",_xlfn.XLOOKUP(F$5-$C27,ModelDrivers!$G$4:$G$9,ModelDrivers!$H$4:$H$9)) | G28: =IF(OR(G$5>($C28+5),(G$5-$C28)<0),"",_xlfn.XLOOKUP(G$5-$C27,ModelDrivers!$G$4:$G$9,ModelDrivers!$H$4:$H$9)) | H28: =IF(OR(H$5>($C28+5),(H$5-$C28)<0),"",_xlfn.XLOOKUP(H$5-$C27,ModelDrivers!$G$4:$G$9,ModelDrivers!$H$4:$H$9)) | I28: =IF(OR(I$5>($C28+5),(I$5-$C28)<0),"",_xlfn.XLOOKUP(I$5-$C27,ModelDrivers!$G$4:$G$9,ModelDrivers!$H$4:$H$9)) | J28: =IF(OR(J$5>($C28+5),(J$5-$C28)<0),"",_xlfn.XLOOKUP(J$5-$C27,ModelDrivers!$G$4:$G$9,ModelDrivers!$H$4:$H$9)) -> 0.56 | K28: =IF(OR(K$5>($C28+5),(K$5-$C28)<0),"",_xlfn.XLOOKUP(K$5-$C27,ModelDrivers!$G$4:$G$9,ModelDrivers!$H$4:$H$9)) -> 0.25 | ... O28: =IF(OR(O$5>($C28+5),(O$5-$C28)<0),"",_xlfn.XLOOKUP(O$5-$C27,ModelDrivers!$G$4:$G$9,ModelDrivers!$H$4:$H$9)) -> 0.11
C29: =C28+1 -> 8 | D29: =IF(OR(D$5>($C29+5),(D$5-$C29)<0),"",_xlfn.XLOOKUP(D$5-$C28,ModelDrivers!$G$4:$G$9,ModelDrivers!$H$4:$H$9)) | E29: =IF(OR(E$5>($C29+5),(E$5-$C29)<0),"",_xlfn.XLOOKUP(E$5-$C28,ModelDrivers!$G$4:$G$9,ModelDrivers!$H$4:$H$9)) | F29: =IF(OR(F$5>($C29+5),(F$5-$C29)<0),"",_xlfn.XLOOKUP(F$5-$C28,ModelDrivers!$G$4:$G$9,ModelDrivers!$H$4:$H$9)) | G29: =IF(OR(G$5>($C29+5),(G$5-$C29)<0),"",_xlfn.XLOOKUP(G$5-$C28,ModelDrivers!$G$4:$G$9,ModelDrivers!$H$4:$H$9)) | H29: =IF(OR(H$5>($C29+5),(H$5-$C29)<0),"",_xlfn.XLOOKUP(H$5-$C28,ModelDrivers!$G$4:$G$9,ModelDrivers!$H$4:$H$9)) | I29: =IF(OR(I$5>($C29+5),(I$5-$C29)<0),"",_xlfn.XLOOKUP(I$5-$C28,ModelDrivers!$G$4:$G$9,ModelDrivers!$H$4:$H$9)) | J29: =IF(OR(J$5>($C29+5),(J$5-$C29)<0),"",_xlfn.XLOOKUP(J$5-$C28,ModelDrivers!$G$4:$G$9,ModelDrivers!$H$4:$H$9)) | K29: =IF(OR(K$5>($C29+5),(K$5-$C29)<0),"",_xlfn.XLOOKUP(K$5-$C28,ModelDrivers!$G$4:$G$9,ModelDrivers!$H$4:$H$9)) -> 0.56 | ... O29: =IF(OR(O$5>($C29+5),(O$5-$C29)<0),"",_xlfn.XLOOKUP(O$5-$C28,ModelDrivers!$G$4:$G$9,ModelDrivers!$H$4:$H$9)) -> 0.11
C30: =C29+1 -> 9 | D30: =IF(OR(D$5>($C30+5),(D$5-$C30)<0),"",_xlfn.XLOOKUP(D$5-$C29,ModelDrivers!$G$4:$G$9,ModelDrivers!$H$4:$H$9)) | E30: =IF(OR(E$5>($C30+5),(E$5-$C30)<0),"",_xlfn.XLOOKUP(E$5-$C29,ModelDrivers!$G$4:$G$9,ModelDrivers!$H$4:$H$9)) | F30: =IF(OR(F$5>($C30+5),(F$5-$C30)<0),"",_xlfn.XLOOKUP(F$5-$C29,ModelDrivers!$G$4:$G$9,ModelDrivers!$H$4:$H$9)) | G30: =IF(OR(G$5>($C30+5),(G$5-$C30)<0),"",_xlfn.XLOOKUP(G$5-$C29,ModelDrivers!$G$4:$G$9,ModelDrivers!$H$4:$H$9)) | H30: =IF(OR(H$5>($C30+5),(H$5-$C30)<0),"",_xlfn.XLOOKUP(H$5-$C29,ModelDrivers!$G$4:$G$9,ModelDrivers!$H$4:$H$9)) | I30: =IF(OR(I$5>($C30+5),(I$5-$C30)<0),"",_xlfn.XLOOKUP(I$5-$C29,ModelDrivers!$G$4:$G$9,ModelDrivers!$H$4:$H$9)) | J30: =IF(OR(J$5>($C30+5),(J$5-$C30)<0),"",_xlfn.XLOOKUP(J$5-$C29,ModelDrivers!$G$4:$G$9,ModelDrivers!$H$4:$H$9)) | K30: =IF(OR(K$5>($C30+5),(K$5-$C30)<0),"",_xlfn.XLOOKUP(K$5-$C29,ModelDrivers!$G$4:$G$9,ModelDrivers!$H$4:$H$9)) | ... O30: =IF(OR(O$5>($C30+5),(O$5-$C30)<0),"",_xlfn.XLOOKUP(O$5-$C29,ModelDrivers!$G$4:$G$9,ModelDrivers!$H$4:$H$9)) -> 0.23
C31: =C30+1 -> 10 | D31: =IF(OR(D$5>($C31+5),(D$5-$C31)<0),"",_xlfn.XLOOKUP(D$5-$C30,ModelDrivers!$G$4:$G$9,ModelDrivers!$H$4:$H$9)) | E31: =IF(OR(E$5>($C31+5),(E$5-$C31)<0),"",_xlfn.XLOOKUP(E$5-$C30,ModelDrivers!$G$4:$G$9,ModelDrivers!$H$4:$H$9)) | F31: =IF(OR(F$5>($C31+5),(F$5-$C31)<0),"",_xlfn.XLOOKUP(F$5-$C30,ModelDrivers!$G$4:$G$9,ModelDrivers!$H$4:$H$9)) | G31: =IF(OR(G$5>($C31+5),(G$5-$C31)<0),"",_xlfn.XLOOKUP(G$5-$C30,ModelDrivers!$G$4:$G$9,ModelDrivers!$H$4:$H$9)) | H31: =IF(OR(H$5>($C31+5),(H$5-$C31)<0),"",_xlfn.XLOOKUP(H$5-$C30,ModelDrivers!$G$4:$G$9,ModelDrivers!$H$4:$H$9)) | I31: =IF(OR(I$5>($C31+5),(I$5-$C31)<0),"",_xlfn.XLOOKUP(I$5-$C30,ModelDrivers!$G$4:$G$9,ModelDrivers!$H$4:$H$9)) | J31: =IF(OR(J$5>($C31+5),(J$5-$C31)<0),"",_xlfn.XLOOKUP(J$5-$C30,ModelDrivers!$G$4:$G$9,ModelDrivers!$H$4:$H$9)) | K31: =IF(OR(K$5>($C31+5),(K$5-$C31)<0),"",_xlfn.XLOOKUP(K$5-$C30,ModelDrivers!$G$4:$G$9,ModelDrivers!$H$4:$H$9)) | ... O31: =IF(OR(O$5>($C31+5),(O$5-$C31)<0),"",_xlfn.XLOOKUP(O$5-$C30,ModelDrivers!$G$4:$G$9,ModelDrivers!$H$4:$H$9)) -> 0.25
C32: =C31+1 -> 11 | D32: =IF(OR(D$5>($C32+5),(D$5-$C32)<0),"",_xlfn.XLOOKUP(D$5-$C31,ModelDrivers!$G$4:$G$9,ModelDrivers!$H$4:$H$9)) | E32: =IF(OR(E$5>($C32+5),(E$5-$C32)<0),"",_xlfn.XLOOKUP(E$5-$C31,ModelDrivers!$G$4:$G$9,ModelDrivers!$H$4:$H$9)) | F32: =IF(OR(F$5>($C32+5),(F$5-$C32)<0),"",_xlfn.XLOOKUP(F$5-$C31,ModelDrivers!$G$4:$G$9,ModelDrivers!$H$4:$H$9)) | G32: =IF(OR(G$5>($C32+5),(G$5-$C32)<0),"",_xlfn.XLOOKUP(G$5-$C31,ModelDrivers!$G$4:$G$9,ModelDrivers!$H$4:$H$9)) | H32: =IF(OR(H$5>($C32+5),(H$5-$C32)<0),"",_xlfn.XLOOKUP(H$5-$C31,ModelDrivers!$G$4:$G$9,ModelDrivers!$H$4:$H$9)) | I32: =IF(OR(I$5>($C32+5),(I$5-$C32)<0),"",_xlfn.XLOOKUP(I$5-$C31,ModelDrivers!$G$4:$G$9,ModelDrivers!$H$4:$H$9)) | J32: =IF(OR(J$5>($C32+5),(J$5-$C32)<0),"",_xlfn.XLOOKUP(J$5-$C31,ModelDrivers!$G$4:$G$9,ModelDrivers!$H$4:$H$9)) | K32: =IF(OR(K$5>($C32+5),(K$5-$C32)<0),"",_xlfn.XLOOKUP(K$5-$C31,ModelDrivers!$G$4:$G$9,ModelDrivers!$H$4:$H$9)) | ... O32: =IF(OR(O$5>($C32+5),(O$5-$C32)<0),"",_xlfn.XLOOKUP(O$5-$C31,ModelDrivers!$G$4:$G$9,ModelDrivers!$H$4:$H$9)) -> 0.25
C33: =C32+1 -> 12 | D33: =IF(OR(D$5>($C33+5),(D$5-$C33)<0),"",_xlfn.XLOOKUP(D$5-$C32,ModelDrivers!$G$4:$G$9,ModelDrivers!$H$4:$H$9)) | E33: =IF(OR(E$5>($C33+5),(E$5-$C33)<0),"",_xlfn.XLOOKUP(E$5-$C32,ModelDrivers!$G$4:$G$9,ModelDrivers!$H$4:$H$9)) | F33: =IF(OR(F$5>($C33+5),(F$5-$C33)<0),"",_xlfn.XLOOKUP(F$5-$C32,ModelDrivers!$G$4:$G$9,ModelDrivers!$H$4:$H$9)) | G33: =IF(OR(G$5>($C33+5),(G$5-$C33)<0),"",_xlfn.XLOOKUP(G$5-$C32,ModelDrivers!$G$4:$G$9,ModelDrivers!$H$4:$H$9)) | H33: =IF(OR(H$5>($C33+5),(H$5-$C33)<0),"",_xlfn.XLOOKUP(H$5-$C32,ModelDrivers!$G$4:$G$9,ModelDrivers!$H$4:$H$9)) | I33: =IF(OR(I$5>($C33+5),(I$5-$C33)<0),"",_xlfn.XLOOKUP(I$5-$C32,ModelDrivers!$G$4:$G$9,ModelDrivers!$H$4:$H$9)) | J33: =IF(OR(J$5>($C33+5),(J$5-$C33)<0),"",_xlfn.XLOOKUP(J$5-$C32,ModelDrivers!$G$4:$G$9,ModelDrivers!$H$4:$H$9)) | K33: =IF(OR(K$5>($C33+5),(K$5-$C33)<0),"",_xlfn.XLOOKUP(K$5-$C32,ModelDrivers!$G$4:$G$9,ModelDrivers!$H$4:$H$9)) | ... O33: =IF(OR(O$5>($C33+5),(O$5-$C33)<0),"",_xlfn.XLOOKUP(O$5-$C32,ModelDrivers!$G$4:$G$9,ModelDrivers!$H$4:$H$9)) -> 0.56
C34: =C33+1 -> 13 | D34: =IF(OR(D$5>($C34+5),(D$5-$C34)<0),"",_xlfn.XLOOKUP(D$5-$C33,ModelDrivers!$G$4:$G$9,ModelDrivers!$H$4:$H$9)) | E34: =IF(OR(E$5>($C34+5),(E$5-$C34)<0),"",_xlfn.XLOOKUP(E$5-$C33,ModelDrivers!$G$4:$G$9,ModelDrivers!$H$4:$H$9)) | F34: =IF(OR(F$5>($C34+5),(F$5-$C34)<0),"",_xlfn.XLOOKUP(F$5-$C33,ModelDrivers!$G$4:$G$9,ModelDrivers!$H$4:$H$9)) | G34: =IF(OR(G$5>($C34+5),(G$5-$C34)<0),"",_xlfn.XLOOKUP(G$5-$C33,ModelDrivers!$G$4:$G$9,ModelDrivers!$H$4:$H$9)) | H34: =IF(OR(H$5>($C34+5),(H$5-$C34)<0),"",_xlfn.XLOOKUP(H$5-$C33,ModelDrivers!$G$4:$G$9,ModelDrivers!$H$4:$H$9)) | I34: =IF(OR(I$5>($C34+5),(I$5-$C34)<0),"",_xlfn.XLOOKUP(I$5-$C33,ModelDrivers!$G$4:$G$9,ModelDrivers!$H$4:$H$9)) | J34: =IF(OR(J$5>($C34+5),(J$5-$C34)<0),"",_xlfn.XLOOKUP(J$5-$C33,ModelDrivers!$G$4:$G$9,ModelDrivers!$H$4:$H$9)) | K34: =IF(OR(K$5>($C34+5),(K$5-$C34)<0),"",_xlfn.XLOOKUP(K$5-$C33,ModelDrivers!$G$4:$G$9,ModelDrivers!$H$4:$H$9)) | ... O34: =IF(OR(O$5>($C34+5),(O$5-$C34)<0),"",_xlfn.XLOOKUP(O$5-$C33,ModelDrivers!$G$4:$G$9,ModelDrivers!$H$4:$H$9))
... C45: =C44+1 -> 24 | D45: =IF(OR(D$5>($C45+5),(D$5-$C45)<0),"",_xlfn.XLOOKUP(D$5-$C44,ModelDrivers!$G$4:$G$9,ModelDrivers!$H$4:$H$9)) | E45: =IF(OR(E$5>($C45+5),(E$5-$C45)<0),"",_xlfn.XLOOKUP(E$5-$C44,ModelDrivers!$G$4:$G$9,ModelDrivers!$H$4:$H$9)) | F45: =IF(OR(F$5>($C45+5),(F$5-$C45)<0),"",_xlfn.XLOOKUP(F$5-$C44,ModelDrivers!$G$4:$G$9,ModelDrivers!$H$4:$H$9)) | G45: =IF(OR(G$5>($C45+5),(G$5-$C45)<0),"",_xlfn.XLOOKUP(G$5-$C44,ModelDrivers!$G$4:$G$9,ModelDrivers!$H$4:$H$9)) | H45: =IF(OR(H$5>($C45+5),(H$5-$C45)<0),"",_xlfn.XLOOKUP(H$5-$C44,ModelDrivers!$G$4:$G$9,ModelDrivers!$H$4:$H$9)) | I45: =IF(OR(I$5>($C45+5),(I$5-$C45)<0),"",_xlfn.XLOOKUP(I$5-$C44,ModelDrivers!$G$4:$G$9,ModelDrivers!$H$4:$H$9)) | J45: =IF(OR(J$5>($C45+5),(J$5-$C45)<0),"",_xlfn.XLOOKUP(J$5-$C44,ModelDrivers!$G$4:$G$9,ModelDrivers!$H$4:$H$9)) | K45: =IF(OR(K$5>($C45+5),(K$5-$C45)<0),"",_xlfn.XLOOKUP(K$5-$C44,ModelDrivers!$G$4:$G$9,ModelDrivers!$H$4:$H$9)) | ... O45: =IF(OR(O$5>($C45+5),(O$5-$C45)<0),"",_xlfn.XLOOKUP(O$5-$C44,ModelDrivers!$G$4:$G$9,ModelDrivers!$H$4:$H$9))
H49: =IFERROR(IF(H$8<($C51+6),HLOOKUP($C51,$D$8:$AA$10,3,FALSE)*H20,G51),"") | I49: =IFERROR(IF(I$8<($C51+6),HLOOKUP($C51,$D$8:$AA$10,3,FALSE)*I20,H49),"") | J49: =IFERROR(IF(J$8<($C51+6),HLOOKUP($C51,$D$8:$AA$10,3,FALSE)*J20,I49),"") | K49: =IFERROR(IF(K$8<($C51+6),HLOOKUP($C51,$D$8:$AA$10,3,FALSE)*K20,J49),"") | L49: =IFERROR(IF(L$8<($C51+6),HLOOKUP($C51,$D$8:$AA$10,3,FALSE)*L20,K49),"") | M49: =IFERROR(IF(M$8<($C51+6),HLOOKUP($C51,$D$8:$AA$10,3,FALSE)*M20,L49),"")
C50: Cohort Count | H50: =IFERROR(IF(H$8<($C52+6),HLOOKUP($C52,$D$8:$AA$10,3,FALSE)*H21,G52),"") | I50: =IFERROR(IF(I$8<($C52+6),HLOOKUP($C52,$D$8:$AA$10,3,FALSE)*I21,H50),"") | J50: =IFERROR(IF(J$8<($C52+6),HLOOKUP($C52,$D$8:$AA$10,3,FALSE)*J21,I50),"") | K50: =IFERROR(IF(K$8<($C52+6),HLOOKUP($C52,$D$8:$AA$10,3,FALSE)*K21,J50),"") | L50: =IFERROR(IF(L$8<($C52+6),HLOOKUP($C52,$D$8:$AA$10,3,FALSE)*L21,K50),"") | M50: =IFERROR(IF(M$8<($C52+6),HLOOKUP($C52,$D$8:$AA$10,3,FALSE)*M21,L50),"")
C51: 1 | D51: =IFERROR(IF(D$8<($C51+6),_xlfn.XLOOKUP($C51,$5:$5,$15:$15)*D22,C51),"") -> 728 | E51: =IFERROR(IF(E$8<($C51+6),_xlfn.XLOOKUP($C51,$5:$5,$15:$15)*E22,D51),"") -> 325 | F51: =IFERROR(IF(F$8<($C51+6),_xlfn.XLOOKUP($C51,$5:$5,$15:$15)*F22,E51),"") -> 325 | G51: =IFERROR(IF(G$8<($C51+6),_xlfn.XLOOKUP($C51,$5:$5,$15:$15)*G22,F51),"") -> 299 | H51: =IFERROR(IF(H$8<($C51+6),_xlfn.XLOOKUP($C51,$5:$5,$15:$15)*H22,G51),"") -> 143 | I51: =IFERROR(IF(I$8<($C51+6),_xlfn.XLOOKUP($C51,$5:$5,$15:$15)*I22,H51),"") -> 143 | J51: =IFERROR(IF(J$8<($C51+6),_xlfn.XLOOKUP($C51,$5:$5,$15:$15)*J22,I51),"") -> 0 | K51: =IFERROR(IF(K$8<($C51+6),_xlfn.XLOOKUP($C51,$5:$5,$15:$15)*K22,J51),"") -> 0 | ... P51: =IFERROR(IF(P$8<($C51+6),_xlfn.XLOOKUP($C51,$5:$5,$15:$15)*P22,O51),"") -> 0
C52: =C51+1 -> 2 | D52: =IFERROR(IF(D$8<($C52+6),_xlfn.XLOOKUP($C52,$5:$5,$15:$15)*D23,C52),"") | E52: =IFERROR(IF(E$8<($C52+6),_xlfn.XLOOKUP($C52,$5:$5,$15:$15)*E23,D52),"") -> 1120 | F52: =IFERROR(IF(F$8<($C52+6),_xlfn.XLOOKUP($C52,$5:$5,$15:$15)*F23,E52),"") -> 500 | G52: =IFERROR(IF(G$8<($C52+6),_xlfn.XLOOKUP($C52,$5:$5,$15:$15)*G23,F52),"") -> 500 | H52: =IFERROR(IF(H$8<($C52+6),_xlfn.XLOOKUP($C52,$5:$5,$15:$15)*H23,G52),"") -> 460 | I52: =IFERROR(IF(I$8<($C52+6),_xlfn.XLOOKUP($C52,$5:$5,$15:$15)*I23,H52),"") -> 220 | J52: =IFERROR(IF(J$8<($C52+6),_xlfn.XLOOKUP($C52,$5:$5,$15:$15)*J23,I52),"") -> 220 | K52: =IFERROR(IF(K$8<($C52+6),_xlfn.XLOOKUP($C52,$5:$5,$15:$15)*K23,J52),"") | ... P52: =IFERROR(IF(P$8<($C52+6),_xlfn.XLOOKUP($C52,$5:$5,$15:$15)*P23,O52),"") -> 0
C53: =C52+1 -> 3 | D53: =IFERROR(IF(D$8<($C53+6),_xlfn.XLOOKUP($C53,$5:$5,$15:$15)*D24,C53),"") | E53: =IFERROR(IF(E$8<($C53+6),_xlfn.XLOOKUP($C53,$5:$5,$15:$15)*E24,D53),"") | F53: =IFERROR(IF(F$8<($C53+6),_xlfn.XLOOKUP($C53,$5:$5,$15:$15)*F24,E53),"") -> 1848 | G53: =IFERROR(IF(G$8<($C53+6),_xlfn.XLOOKUP($C53,$5:$5,$15:$15)*G24,F53),"") -> 825 | H53: =IFERROR(IF(H$8<($C53+6),_xlfn.XLOOKUP($C53,$5:$5,$15:$15)*H24,G53),"") -> 825 | I53: =IFERROR(IF(I$8<($C53+6),_xlfn.XLOOKUP($C53,$5:$5,$15:$15)*I24,H53),"") -> 759 | J53: =IFERROR(IF(J$8<($C53+6),_xlfn.XLOOKUP($C53,$5:$5,$15:$15)*J24,I53),"") -> 363 | K53: =IFERROR(IF(K$8<($C53+6),_xlfn.XLOOKUP($C53,$5:$5,$15:$15)*K24,J53),"") -> 363 | ... P53: =IFERROR(IF(P$8<($C53+6),_xlfn.XLOOKUP($C53,$5:$5,$15:$15)*P24,O53),"") -> 0
C54: =C53+1 -> 4 | D54: =IFERROR(IF(D$8<($C54+6),_xlfn.XLOOKUP($C54,$5:$5,$15:$15)*D25,C54),"") | E54: =IFERROR(IF(E$8<($C54+6),_xlfn.XLOOKUP($C54,$5:$5,$15:$15)*E25,D54),"") | F54: =IFERROR(IF(F$8<($C54+6),_xlfn.XLOOKUP($C54,$5:$5,$15:$15)*F25,E54),"") | G54: =IFERROR(IF(G$8<($C54+6),_xlfn.XLOOKUP($C54,$5:$5,$15:$15)*G25,F54),"") -> 1940.4 | H54: =IFERROR(IF(H$8<($C54+6),_xlfn.XLOOKUP($C54,$5:$5,$15:$15)*H25,G54),"") -> 866.25 | I54: =IFERROR(IF(I$8<($C54+6),_xlfn.XLOOKUP($C54,$5:$5,$15:$15)*I25,H54),"") -> 866.25 | J54: =IFERROR(IF(J$8<($C54+6),_xlfn.XLOOKUP($C54,$5:$5,$15:$15)*J25,I54),"") -> 796.95 | K54: =IFERROR(IF(K$8<($C54+6),_xlfn.XLOOKUP($C54,$5:$5,$15:$15)*K25,J54),"") -> 381.15 | ... P54: =IFERROR(IF(P$8<($C54+6),_xlfn.XLOOKUP($C54,$5:$5,$15:$15)*P25,O54),"") -> 0
C55: =C54+1 -> 5 | D55: =IFERROR(IF(D$8<($C55+6),_xlfn.XLOOKUP($C55,$5:$5,$15:$15)*D26,C55),"") | E55: =IFERROR(IF(E$8<($C55+6),_xlfn.XLOOKUP($C55,$5:$5,$15:$15)*E26,D55),"") | F55: =IFERROR(IF(F$8<($C55+6),_xlfn.XLOOKUP($C55,$5:$5,$15:$15)*F26,E55),"") | G55: =IFERROR(IF(G$8<($C55+6),_xlfn.XLOOKUP($C55,$5:$5,$15:$15)*G26,F55),"") | H55: =IFERROR(IF(H$8<($C55+6),_xlfn.XLOOKUP($C55,$5:$5,$15:$15)*H26,G55),"") -> 2037.42 | I55: =IFERROR(IF(I$8<($C55+6),_xlfn.XLOOKUP($C55,$5:$5,$15:$15)*I26,H55),"") -> 909.5625 | J55: =IFERROR(IF(J$8<($C55+6),_xlfn.XLOOKUP($C55,$5:$5,$15:$15)*J26,I55),"") -> 909.5625 | K55: =IFERROR(IF(K$8<($C55+6),_xlfn.XLOOKUP($C55,$5:$5,$15:$15)*K26,J55),"") -> 836.7975 | ... P55: =IFERROR(IF(P$8<($C55+6),_xlfn.XLOOKUP($C55,$5:$5,$15:$15)*P26,O55),"") -> 0
C56: =C55+1 -> 6 | D56: =IFERROR(IF(D$8<($C56+6),_xlfn.XLOOKUP($C56,$5:$5,$15:$15)*D27,C56),"") | E56: =IFERROR(IF(E$8<($C56+6),_xlfn.XLOOKUP($C56,$5:$5,$15:$15)*E27,D56),"") | F56: =IFERROR(IF(F$8<($C56+6),_xlfn.XLOOKUP($C56,$5:$5,$15:$15)*F27,E56),"") | G56: =IFERROR(IF(G$8<($C56+6),_xlfn.XLOOKUP($C56,$5:$5,$15:$15)*G27,F56),"") | H56: =IFERROR(IF(H$8<($C56+6),_xlfn.XLOOKUP($C56,$5:$5,$15:$15)*H27,G56),"") | I56: =IFERROR(IF(I$8<($C56+6),_xlfn.XLOOKUP($C56,$5:$5,$15:$15)*I27,H56),"") -> 2139.291 | J56: =IFERROR(IF(J$8<($C56+6),_xlfn.XLOOKUP($C56,$5:$5,$15:$15)*J27,I56),"") -> 955.04062 | K56: =IFERROR(IF(K$8<($C56+6),_xlfn.XLOOKUP($C56,$5:$5,$15:$15)*K27,J56),"") -> 955.04062 | ... P56: =IFERROR(IF(P$8<($C56+6),_xlfn.XLOOKUP($C56,$5:$5,$15:$15)*P27,O56),"") -> 0
C57: =C56+1 -> 7 | D57: =IFERROR(IF(D$8<($C57+6),_xlfn.XLOOKUP($C57,$5:$5,$15:$15)*D28,C57),"") | E57: =IFERROR(IF(E$8<($C57+6),_xlfn.XLOOKUP($C57,$5:$5,$15:$15)*E28,D57),"") | F57: =IFERROR(IF(F$8<($C57+6),_xlfn.XLOOKUP($C57,$5:$5,$15:$15)*F28,E57),"") | G57: =IFERROR(IF(G$8<($C57+6),_xlfn.XLOOKUP($C57,$5:$5,$15:$15)*G28,F57),"") | H57: =IFERROR(IF(H$8<($C57+6),_xlfn.XLOOKUP($C57,$5:$5,$15:$15)*H28,G57),"") | I57: =IFERROR(IF(I$8<($C57+6),_xlfn.XLOOKUP($C57,$5:$5,$15:$15)*I28,H57),"") | J57: =IFERROR(IF(J$8<($C57+6),_xlfn.XLOOKUP($C57,$5:$5,$15:$15)*J28,I57),"") -> 2246.2556 | K57: =IFERROR(IF(K$8<($C57+6),_xlfn.XLOOKUP($C57,$5:$5,$15:$15)*K28,J57),"") -> 1002.7927 | ... P57: =IFERROR(IF(P$8<($C57+6),_xlfn.XLOOKUP($C57,$5:$5,$15:$15)*P28,O57),"") -> 0
C58: =C57+1 -> 8 | D58: =IFERROR(IF(D$8<($C58+6),_xlfn.XLOOKUP($C58,$5:$5,$15:$15)*D29,C58),"") | E58: =IFERROR(IF(E$8<($C58+6),_xlfn.XLOOKUP($C58,$5:$5,$15:$15)*E29,D58),"") | F58: =IFERROR(IF(F$8<($C58+6),_xlfn.XLOOKUP($C58,$5:$5,$15:$15)*F29,E58),"") | G58: =IFERROR(IF(G$8<($C58+6),_xlfn.XLOOKUP($C58,$5:$5,$15:$15)*G29,F58),"") | H58: =IFERROR(IF(H$8<($C58+6),_xlfn.XLOOKUP($C58,$5:$5,$15:$15)*H29,G58),"") | I58: =IFERROR(IF(I$8<($C58+6),_xlfn.XLOOKUP($C58,$5:$5,$15:$15)*I29,H58),"") | J58: =IFERROR(IF(J$8<($C58+6),_xlfn.XLOOKUP($C58,$5:$5,$15:$15)*J29,I58),"") | K58: =IFERROR(IF(K$8<($C58+6),_xlfn.XLOOKUP($C58,$5:$5,$15:$15)*K29,J58),"") -> 2358.5683 | ... P58: =IFERROR(IF(P$8<($C58+6),_xlfn.XLOOKUP($C58,$5:$5,$15:$15)*P29,O58),"") -> 0
C59: =C58+1 -> 9 | D59: =IFERROR(IF(D$8<($C59+6),_xlfn.XLOOKUP($C59,$5:$5,$15:$15)*D30,C59),"") | E59: =IFERROR(IF(E$8<($C59+6),_xlfn.XLOOKUP($C59,$5:$5,$15:$15)*E30,D59),"") | F59: =IFERROR(IF(F$8<($C59+6),_xlfn.XLOOKUP($C59,$5:$5,$15:$15)*F30,E59),"") | G59: =IFERROR(IF(G$8<($C59+6),_xlfn.XLOOKUP($C59,$5:$5,$15:$15)*G30,F59),"") | H59: =IFERROR(IF(H$8<($C59+6),_xlfn.XLOOKUP($C59,$5:$5,$15:$15)*H30,G59),"") | I59: =IFERROR(IF(I$8<($C59+6),_xlfn.XLOOKUP($C59,$5:$5,$15:$15)*I30,H59),"") | J59: =IFERROR(IF(J$8<($C59+6),_xlfn.XLOOKUP($C59,$5:$5,$15:$15)*J30,I59),"") | K59: =IFERROR(IF(K$8<($C59+6),_xlfn.XLOOKUP($C59,$5:$5,$15:$15)*K30,J59),"") | ... P59: =IFERROR(IF(P$8<($C59+6),_xlfn.XLOOKUP($C59,$5:$5,$15:$15)*P30,O59),"") -> 0
C60: =C59+1 -> 10 | D60: =IFERROR(IF(D$8<($C60+6),_xlfn.XLOOKUP($C60,$5:$5,$15:$15)*D31,C60),"") | E60: =IFERROR(IF(E$8<($C60+6),_xlfn.XLOOKUP($C60,$5:$5,$15:$15)*E31,D60),"") | F60: =IFERROR(IF(F$8<($C60+6),_xlfn.XLOOKUP($C60,$5:$5,$15:$15)*F31,E60),"") | G60: =IFERROR(IF(G$8<($C60+6),_xlfn.XLOOKUP($C60,$5:$5,$15:$15)*G31,F60),"") | H60: =IFERROR(IF(H$8<($C60+6),_xlfn.XLOOKUP($C60,$5:$5,$15:$15)*H31,G60),"") | I60: =IFERROR(IF(I$8<($C60+6),_xlfn.XLOOKUP($C60,$5:$5,$15:$15)*I31,H60),"") | J60: =IFERROR(IF(J$8<($C60+6),_xlfn.XLOOKUP($C60,$5:$5,$15:$15)*J31,I60),"") | K60: =IFERROR(IF(K$8<($C60+6),_xlfn.XLOOKUP($C60,$5:$5,$15:$15)*K31,J60),"") | ... P60: =IFERROR(IF(P$8<($C60+6),_xlfn.XLOOKUP($C60,$5:$5,$15:$15)*P31,O60),"") -> 0
C61: =C60+1 -> 11 | D61: =IFERROR(IF(D$8<($C61+6),_xlfn.XLOOKUP($C61,$5:$5,$15:$15)*D32,C61),"") | E61: =IFERROR(IF(E$8<($C61+6),_xlfn.XLOOKUP($C61,$5:$5,$15:$15)*E32,D61),"") | F61: =IFERROR(IF(F$8<($C61+6),_xlfn.XLOOKUP($C61,$5:$5,$15:$15)*F32,E61),"") | G61: =IFERROR(IF(G$8<($C61+6),_xlfn.XLOOKUP($C61,$5:$5,$15:$15)*G32,F61),"") | H61: =IFERROR(IF(H$8<($C61+6),_xlfn.XLOOKUP($C61,$5:$5,$15:$15)*H32,G61),"") | I61: =IFERROR(IF(I$8<($C61+6),_xlfn.XLOOKUP($C61,$5:$5,$15:$15)*I32,H61),"") | J61: =IFERROR(IF(J$8<($C61+6),_xlfn.XLOOKUP($C61,$5:$5,$15:$15)*J32,I61),"") | K61: =IFERROR(IF(K$8<($C61+6),_xlfn.XLOOKUP($C61,$5:$5,$15:$15)*K32,J61),"") | ... P61: =IFERROR(IF(P$8<($C61+6),_xlfn.XLOOKUP($C61,$5:$5,$15:$15)*P32,O61),"") -> 0
C62: =C61+1 -> 12 | D62: =IFERROR(IF(D$8<($C62+6),_xlfn.XLOOKUP($C62,$5:$5,$15:$15)*D33,C62),"") | E62: =IFERROR(IF(E$8<($C62+6),_xlfn.XLOOKUP($C62,$5:$5,$15:$15)*E33,D62),"") | F62: =IFERROR(IF(F$8<($C62+6),_xlfn.XLOOKUP($C62,$5:$5,$15:$15)*F33,E62),"") | G62: =IFERROR(IF(G$8<($C62+6),_xlfn.XLOOKUP($C62,$5:$5,$15:$15)*G33,F62),"") | H62: =IFERROR(IF(H$8<($C62+6),_xlfn.XLOOKUP($C62,$5:$5,$15:$15)*H33,G62),"") | I62: =IFERROR(IF(I$8<($C62+6),_xlfn.XLOOKUP($C62,$5:$5,$15:$15)*I33,H62),"") | J62: =IFERROR(IF(J$8<($C62+6),_xlfn.XLOOKUP($C62,$5:$5,$15:$15)*J33,I62),"") | K62: =IFERROR(IF(K$8<($C62+6),_xlfn.XLOOKUP($C62,$5:$5,$15:$15)*K33,J62),"") | ... P62: =IFERROR(IF(P$8<($C62+6),_xlfn.XLOOKUP($C62,$5:$5,$15:$15)*P33,O62),"") -> 0
C63: =C62+1 -> 13 | D63: =IFERROR(IF(D$8<($C63+6),_xlfn.XLOOKUP($C63,$5:$5,$15:$15)*D34,C63),"") | E63: =IFERROR(IF(E$8<($C63+6),_xlfn.XLOOKUP($C63,$5:$5,$15:$15)*E34,D63),"") | F63: =IFERROR(IF(F$8<($C63+6),_xlfn.XLOOKUP($C63,$5:$5,$15:$15)*F34,E63),"") | G63: =IFERROR(IF(G$8<($C63+6),_xlfn.XLOOKUP($C63,$5:$5,$15:$15)*G34,F63),"") | H63: =IFERROR(IF(H$8<($C63+6),_xlfn.XLOOKUP($C63,$5:$5,$15:$15)*H34,G63),"") | I63: =IFERROR(IF(I$8<($C63+6),_xlfn.XLOOKUP($C63,$5:$5,$15:$15)*I34,H63),"") | J63: =IFERROR(IF(J$8<($C63+6),_xlfn.XLOOKUP($C63,$5:$5,$15:$15)*J34,I63),"") | K63: =IFERROR(IF(K$8<($C63+6),_xlfn.XLOOKUP($C63,$5:$5,$15:$15)*K34,J63),"") | ... P63: =IFERROR(IF(P$8<($C63+6),_xlfn.XLOOKUP($C63,$5:$5,$15:$15)*P34,O63),"")
... C74: =C73+1 -> 24 | D74: =IFERROR(IF(D$8<($C74+6),_xlfn.XLOOKUP($C74,$5:$5,$15:$15)*D45,C74),"") | E74: =IFERROR(IF(E$8<($C74+6),_xlfn.XLOOKUP($C74,$5:$5,$15:$15)*E45,D74),"") | F74: =IFERROR(IF(F$8<($C74+6),_xlfn.XLOOKUP($C74,$5:$5,$15:$15)*F45,E74),"") | G74: =IFERROR(IF(G$8<($C74+6),_xlfn.XLOOKUP($C74,$5:$5,$15:$15)*G45,F74),"") | H74: =IFERROR(IF(H$8<($C74+6),_xlfn.XLOOKUP($C74,$5:$5,$15:$15)*H45,G74),"") | I74: =IFERROR(IF(I$8<($C74+6),_xlfn.XLOOKUP($C74,$5:$5,$15:$15)*I45,H74),"") | J74: =IFERROR(IF(J$8<($C74+6),_xlfn.XLOOKUP($C74,$5:$5,$15:$15)*J45,I74),"") | K74: =IFERROR(IF(K$8<($C74+6),_xlfn.XLOOKUP($C74,$5:$5,$15:$15)*K45,J74),"") | ... P74: =IFERROR(IF(P$8<($C74+6),_xlfn.XLOOKUP($C74,$5:$5,$15:$15)*P45,O74),"")
H77: =IF(AND(H$8>($C79),H$8<($C79+6)), H49-G51,"") | I77: =IF(AND(I$8>($C79),I$8<($C79+6)), I49-H49,"") | J77: =IF(AND(J$8>($C79),J$8<($C79+6)), J49-I49,"") | K77: =IF(AND(K$8>($C79),K$8<($C79+6)), K49-J49,"") | L77: =IF(AND(L$8>($C79),L$8<($C79+6)), L49-K49,"") | M77: =IF(AND(M$8>($C79),M$8<($C79+6)), M49-L49,"")
C78: Cohort Attrition | H78: =IF(AND(H$8>($C80),H$8<($C80+6)), H50-G52,"") | I78: =IF(AND(I$8>($C80),I$8<($C80+6)), I50-H50,"") | J78: =IF(AND(J$8>($C80),J$8<($C80+6)), J50-I50,"") | K78: =IF(AND(K$8>($C80),K$8<($C80+6)), K50-J50,"") | L78: =IF(AND(L$8>($C80),L$8<($C80+6)), L50-K50,"") | M78: =IF(AND(M$8>($C80),M$8<($C80+6)), M50-L50,"")
C79: 1 | D79: =IF(AND(D$5>($C79),D$5<($C79+6)), D51-C51,"") | E79: =IF(AND(E$5>($C79),E$5<($C79+6)), E51-D51,"") -> -403 | F79: =IF(AND(F$5>($C79),F$5<($C79+6)), F51-E51,"") -> 0 | G79: =IF(AND(G$5>($C79),G$5<($C79+6)), G51-F51,"") -> -26 | H79: =IF(AND(H$5>($C79),H$5<($C79+6)), H51-G51,"") -> -156 | I79: =IF(AND(I$5>($C79),I$5<($C79+6)), I51-H51,"") -> 0 | J79: =IF(AND(J$5>($C79),J$5<($C79+6)), J51-I51,"") | K79: =IF(AND(K$5>($C79),K$5<($C79+6)), K51-J51,"") | ... P79: =IF(AND(P$5>($C79),P$5<($C79+6)), P51-O51,"")
C80: =C79+1 -> 2 | D80: =IF(AND(D$5>($C80),D$5<($C80+6)), D52-C52,"") | E80: =IF(AND(E$5>($C80),E$5<($C80+6)), E52-D52,"") | F80: =IF(AND(F$5>($C80),F$5<($C80+6)), F52-E52,"") -> -620 | G80: =IF(AND(G$5>($C80),G$5<($C80+6)), G52-F52,"") -> 0 | H80: =IF(AND(H$5>($C80),H$5<($C80+6)), H52-G52,"") -> -40 | I80: =IF(AND(I$5>($C80),I$5<($C80+6)), I52-H52,"") -> -240 | J80: =IF(AND(J$5>($C80),J$5<($C80+6)), J52-I52,"") -> 0 | K80: =IF(AND(K$5>($C80),K$5<($C80+6)), K52-J52,"") | ... P80: =IF(AND(P$5>($C80),P$5<($C80+6)), P52-O52,"")
C81: =C80+1 -> 3 | D81: =IF(AND(D$5>($C81),D$5<($C81+6)), D53-C53,"") | E81: =IF(AND(E$5>($C81),E$5<($C81+6)), E53-D53,"") | F81: =IF(AND(F$5>($C81),F$5<($C81+6)), F53-E53,"") | G81: =IF(AND(G$5>($C81),G$5<($C81+6)), G53-F53,"") -> -1023 | H81: =IF(AND(H$5>($C81),H$5<($C81+6)), H53-G53,"") -> 0 | I81: =IF(AND(I$5>($C81),I$5<($C81+6)), I53-H53,"") -> -66 | J81: =IF(AND(J$5>($C81),J$5<($C81+6)), J53-I53,"") -> -396 | K81: =IF(AND(K$5>($C81),K$5<($C81+6)), K53-J53,"") -> 0 | ... P81: =IF(AND(P$5>($C81),P$5<($C81+6)), P53-O53,"")
C82: =C81+1 -> 4 | D82: =IF(AND(D$5>($C82),D$5<($C82+6)), D54-C54,"") | E82: =IF(AND(E$5>($C82),E$5<($C82+6)), E54-D54,"") | F82: =IF(AND(F$5>($C82),F$5<($C82+6)), F54-E54,"") | G82: =IF(AND(G$5>($C82),G$5<($C82+6)), G54-F54,"") | H82: =IF(AND(H$5>($C82),H$5<($C82+6)), H54-G54,"") -> -1074.15 | I82: =IF(AND(I$5>($C82),I$5<($C82+6)), I54-H54,"") -> 0 | J82: =IF(AND(J$5>($C82),J$5<($C82+6)), J54-I54,"") -> -69.3 | K82: =IF(AND(K$5>($C82),K$5<($C82+6)), K54-J54,"") -> -415.8 | ... P82: =IF(AND(P$5>($C82),P$5<($C82+6)), P54-O54,"")
C83: =C82+1 -> 5 | D83: =IF(AND(D$5>($C83),D$5<($C83+6)), D55-C55,"") | E83: =IF(AND(E$5>($C83),E$5<($C83+6)), E55-D55,"") | F83: =IF(AND(F$5>($C83),F$5<($C83+6)), F55-E55,"") | G83: =IF(AND(G$5>($C83),G$5<($C83+6)), G55-F55,"") | H83: =IF(AND(H$5>($C83),H$5<($C83+6)), H55-G55,"") | I83: =IF(AND(I$5>($C83),I$5<($C83+6)), I55-H55,"") -> -1127.8575 | J83: =IF(AND(J$5>($C83),J$5<($C83+6)), J55-I55,"") -> 0 | K83: =IF(AND(K$5>($C83),K$5<($C83+6)), K55-J55,"") -> -72.765 | ... P83: =IF(AND(P$5>($C83),P$5<($C83+6)), P55-O55,"")
C84: =C83+1 -> 6 | D84: =IF(AND(D$5>($C84),D$5<($C84+6)), D56-C56,"") | E84: =IF(AND(E$5>($C84),E$5<($C84+6)), E56-D56,"") | F84: =IF(AND(F$5>($C84),F$5<($C84+6)), F56-E56,"") | G84: =IF(AND(G$5>($C84),G$5<($C84+6)), G56-F56,"") | H84: =IF(AND(H$5>($C84),H$5<($C84+6)), H56-G56,"") | I84: =IF(AND(I$5>($C84),I$5<($C84+6)), I56-H56,"") | J84: =IF(AND(J$5>($C84),J$5<($C84+6)), J56-I56,"") -> -1184.2504 | K84: =IF(AND(K$5>($C84),K$5<($C84+6)), K56-J56,"") -> 0 | ... P84: =IF(AND(P$5>($C84),P$5<($C84+6)), P56-O56,"")
C85: =C84+1 -> 7 | D85: =IF(AND(D$5>($C85),D$5<($C85+6)), D57-C57,"") | E85: =IF(AND(E$5>($C85),E$5<($C85+6)), E57-D57,"") | F85: =IF(AND(F$5>($C85),F$5<($C85+6)), F57-E57,"") | G85: =IF(AND(G$5>($C85),G$5<($C85+6)), G57-F57,"") | H85: =IF(AND(H$5>($C85),H$5<($C85+6)), H57-G57,"") | I85: =IF(AND(I$5>($C85),I$5<($C85+6)), I57-H57,"") | J85: =IF(AND(J$5>($C85),J$5<($C85+6)), J57-I57,"") | K85: =IF(AND(K$5>($C85),K$5<($C85+6)), K57-J57,"") -> -1243.4629 | ... P85: =IF(AND(P$5>($C85),P$5<($C85+6)), P57-O57,"")
C86: =C85+1 -> 8 | D86: =IF(AND(D$5>($C86),D$5<($C86+6)), D58-C58,"") | E86: =IF(AND(E$5>($C86),E$5<($C86+6)), E58-D58,"") | F86: =IF(AND(F$5>($C86),F$5<($C86+6)), F58-E58,"") | G86: =IF(AND(G$5>($C86),G$5<($C86+6)), G58-F58,"") | H86: =IF(AND(H$5>($C86),H$5<($C86+6)), H58-G58,"") | I86: =IF(AND(I$5>($C86),I$5<($C86+6)), I58-H58,"") | J86: =IF(AND(J$5>($C86),J$5<($C86+6)), J58-I58,"") | K86: =IF(AND(K$5>($C86),K$5<($C86+6)), K58-J58,"") | ... P86: =IF(AND(P$5>($C86),P$5<($C86+6)), P58-O58,"")
C87: =C86+1 -> 9 | D87: =IF(AND(D$5>($C87),D$5<($C87+6)), D59-C59,"") | E87: =IF(AND(E$5>($C87),E$5<($C87+6)), E59-D59,"") | F87: =IF(AND(F$5>($C87),F$5<($C87+6)), F59-E59,"") | G87: =IF(AND(G$5>($C87),G$5<($C87+6)), G59-F59,"") | H87: =IF(AND(H$5>($C87),H$5<($C87+6)), H59-G59,"") | I87: =IF(AND(I$5>($C87),I$5<($C87+6)), I59-H59,"") | J87: =IF(AND(J$5>($C87),J$5<($C87+6)), J59-I59,"") | K87: =IF(AND(K$5>($C87),K$5<($C87+6)), K59-J59,"") | ... P87: =IF(AND(P$5>($C87),P$5<($C87+6)), P59-O59,"")
C88: =C87+1 -> 10 | D88: =IF(AND(D$5>($C88),D$5<($C88+6)), D60-C60,"") | E88: =IF(AND(E$5>($C88),E$5<($C88+6)), E60-D60,"") | F88: =IF(AND(F$5>($C88),F$5<($C88+6)), F60-E60,"") | G88: =IF(AND(G$5>($C88),G$5<($C88+6)), G60-F60,"") | H88: =IF(AND(H$5>($C88),H$5<($C88+6)), H60-G60,"") | I88: =IF(AND(I$5>($C88),I$5<($C88+6)), I60-H60,"") | J88: =IF(AND(J$5>($C88),J$5<($C88+6)), J60-I60,"") | K88: =IF(AND(K$5>($C88),K$5<($C88+6)), K60-J60,"") | ... P88: =IF(AND(P$5>($C88),P$5<($C88+6)), P60-O60,"")
C89: =C88+1 -> 11 | D89: =IF(AND(D$5>($C89),D$5<($C89+6)), D61-C61,"") | E89: =IF(AND(E$5>($C89),E$5<($C89+6)), E61-D61,"") | F89: =IF(AND(F$5>($C89),F$5<($C89+6)), F61-E61,"") | G89: =IF(AND(G$5>($C89),G$5<($C89+6)), G61-F61,"") | H89: =IF(AND(H$5>($C89),H$5<($C89+6)), H61-G61,"") | I89: =IF(AND(I$5>($C89),I$5<($C89+6)), I61-H61,"") | J89: =IF(AND(J$5>($C89),J$5<($C89+6)), J61-I61,"") | K89: =IF(AND(K$5>($C89),K$5<($C89+6)), K61-J61,"") | ... P89: =IF(AND(P$5>($C89),P$5<($C89+6)), P61-O61,"")
C90: =C89+1 -> 12 | D90: =IF(AND(D$5>($C90),D$5<($C90+6)), D62-C62,"") | E90: =IF(AND(E$5>($C90),E$5<($C90+6)), E62-D62,"") | F90: =IF(AND(F$5>($C90),F$5<($C90+6)), F62-E62,"") | G90: =IF(AND(G$5>($C90),G$5<($C90+6)), G62-F62,"") | H90: =IF(AND(H$5>($C90),H$5<($C90+6)), H62-G62,"") | I90: =IF(AND(I$5>($C90),I$5<($C90+6)), I62-H62,"") | J90: =IF(AND(J$5>($C90),J$5<($C90+6)), J62-I62,"") | K90: =IF(AND(K$5>($C90),K$5<($C90+6)), K62-J62,"") | ... P90: =IF(AND(P$5>($C90),P$5<($C90+6)), P62-O62,"")
C91: =C90+1 -> 13 | D91: =IF(AND(D$5>($C91),D$5<($C91+6)), D63-C63,"") | E91: =IF(AND(E$5>($C91),E$5<($C91+6)), E63-D63,"") | F91: =IF(AND(F$5>($C91),F$5<($C91+6)), F63-E63,"") | G91: =IF(AND(G$5>($C91),G$5<($C91+6)), G63-F63,"") | H91: =IF(AND(H$5>($C91),H$5<($C91+6)), H63-G63,"") | I91: =IF(AND(I$5>($C91),I$5<($C91+6)), I63-H63,"") | J91: =IF(AND(J$5>($C91),J$5<($C91+6)), J63-I63,"") | K91: =IF(AND(K$5>($C91),K$5<($C91+6)), K63-J63,"") | ... P91: =IF(AND(P$5>($C91),P$5<($C91+6)), P63-O63,"")
... C102: =C101+1 -> 24 | D102: =IF(AND(D$5>($C102),D$5<($C102+6)), D74-C74,"") | E102: =IF(AND(E$5>($C102),E$5<($C102+6)), E74-D74,"") | F102: =IF(AND(F$5>($C102),F$5<($C102+6)), F74-E74,"") | G102: =IF(AND(G$5>($C102),G$5<($C102+6)), G74-F74,"") | H102: =IF(AND(H$5>($C102),H$5<($C102+6)), H74-G74,"") | I102: =IF(AND(I$5>($C102),I$5<($C102+6)), I74-H74,"") | J102: =IF(AND(J$5>($C102),J$5<($C102+6)), J74-I74,"") | K102: =IF(AND(K$5>($C102),K$5<($C102+6)), K74-J74,"") | ... P102: =IF(AND(P$5>($C102),P$5<($C102+6)), P74-O74,"")
B104: x | C104: Total Attrition | D104: =SUM(D79:D102) -> 0 | E104: =SUM(E79:E102) -> -403 | F104: =SUM(F79:F102) -> -620 | G104: =SUM(G79:G102) -> -1049 | H104: =SUM(H77:H100) -> -1270.15 | I104: =SUM(I77:I100) -> -1433.8575 | J104: =SUM(J77:J100) -> -1649.5504 | K104: =SUM(K77:K100) -> -1732.0279 | L104: =SUM(L77:L100) -> -1818.6293 | M104: =SUM(M77:M100) -> -1909.5608 | N104: =SUM(N77:N100) -> -2005.0388 | O104: =SUM(O77:O100) -> -2105.2907
C107: Lost Users | D107: =D104 -> 0 | E107: =E104 -> -403 | F107: =F104 -> -620 | G107: =G104 -> -1049 | H107: =H104 -> -1270.15 | I107: =I104 -> -1433.8575 | J107: =J104 -> -1649.5504 | K107: =K104 -> -1732.0279 | ... O107: =O104 -> -2105.2907
C109: Cumulative Premium Subscribers | D109: ='P&Lv2'!D15 -> 1300 | E109: =D109+E15+E107 -> 2897 | F109: =E109+F15+F107 -> 5577 | G109: =F109+G15+G107 -> 7993 | H109: =G109+H15+H107 -> 10361.1 | I109: =H109+I15+I107 -> 12747.405 | J109: =I109+J15+J107 -> 15109.025 | K109: =J109+K15+K107 -> 17588.727 | L109: =K109+L15+L107 -> 20192.413 | ... O109: =N109+O15+O107 -> 28810.94
C111: Attrition % | D111: =D107/D109 -> 0 | E111: =E107/E109 -> -0.13910942 | F111: =F107/F109 -> -0.11117088 | G111: =G107/G109 -> -0.13123983 | H111: =H107/H109 -> -0.12258834 | I111: =I107/I109 -> -0.11248231 | J111: =J107/J109 -> -0.10917649 | K111: =K107/K109 -> -0.098473752 | ... O111: =O107/O109 -> -0.073072615
C112: Adoption % | D112: =D15/D109 -> 1 | E112: =E15/E109 -> 0.69036935 | F112: =F15/F109 -> 0.59171598 | G112: =G15/G109 -> 0.43350432 | H112: =H15/H109 -> 0.35114515 | I112: =I15/I109 -> 0.29968158 | J112: =J15/J109 -> 0.26548176 | K112: =K15/K109 -> 0.23945617 | ... O112: =O15/O109 -> 0.17768886
B113: Plan A | C113: Revenue Generated
B114: Plan B | C114: ="Revenue by Subscribers in " &B113 -> Revenue by Subscribers in Plan A | D114: =_xlfn.LET(_xlpm.cumilative, D$109, _xlpm.price, INDEX(ModelDrivers!$D$8:$D$11, MATCH($B113,ModelDrivers!$C$8:$C$11,0)), _xlpm.subplan, INDEX(ModelDrivers!$E$8:$E$11, MATCH($B113,ModelDrivers!$C$8:$C$11,0)), _xlpm.return, (_xlpm.cumilative * _xlpm.subplan) * _xlpm.price, _xlpm.return ) -> 78000 | E114: =_xlfn.LET(_xlpm.cumilative, E$109, _xlpm.price, INDEX(ModelDrivers!$D$8:$D$11, MATCH($B113,ModelDrivers!$C$8:$C$11,0)), _xlpm.subplan, INDEX(ModelDrivers!$E$8:$E$11, MATCH($B113,ModelDrivers!$C$8:$C$11,0)), _xlpm.return, (_xlpm.cumilative * _xlpm.subplan) * _xlpm.price, _xlpm.return ) -> 173820 | F114: =_xlfn.LET(_xlpm.cumilative, F$109, _xlpm.price, INDEX(ModelDrivers!$D$8:$D$11, MATCH($B113,ModelDrivers!$C$8:$C$11,0)), _xlpm.subplan, INDEX(ModelDrivers!$E$8:$E$11, MATCH($B113,ModelDrivers!$C$8:$C$11,0)), _xlpm.return, (_xlpm.cumilative * _xlpm.subplan) * _xlpm.price, _xlpm.return ) -> 334620 | G114: =_xlfn.LET(_xlpm.cumilative, G$109, _xlpm.price, INDEX(ModelDrivers!$D$8:$D$11, MATCH($B113,ModelDrivers!$C$8:$C$11,0)), _xlpm.subplan, INDEX(ModelDrivers!$E$8:$E$11, MATCH($B113,ModelDrivers!$C$8:$C$11,0)), _xlpm.return, (_xlpm.cumilative * _xlpm.subplan) * _xlpm.price, _xlpm.return ) -> 479580 | H114: =_xlfn.LET(_xlpm.cumilative, H$109, _xlpm.price, INDEX(ModelDrivers!$D$8:$D$11, MATCH($B113,ModelDrivers!$C$8:$C$11,0)), _xlpm.subplan, INDEX(ModelDrivers!$E$8:$E$11, MATCH($B113,ModelDrivers!$C$8:$C$11,0)), _xlpm.return, (_xlpm.cumilative * _xlpm.subplan) * _xlpm.price, _xlpm.return ) -> 621666 | I114: =_xlfn.LET(_xlpm.cumilative, I$109, _xlpm.price, INDEX(ModelDrivers!$D$8:$D$11, MATCH($B113,ModelDrivers!$C$8:$C$11,0)), _xlpm.subplan, INDEX(ModelDrivers!$E$8:$E$11, MATCH($B113,ModelDrivers!$C$8:$C$11,0)), _xlpm.return, (_xlpm.cumilative * _xlpm.subplan) * _xlpm.price, _xlpm.return ) -> 764844.3 | J114: =_xlfn.LET(_xlpm.cumilative, J$109, _xlpm.price, INDEX(ModelDrivers!$D$8:$D$11, MATCH($B113,ModelDrivers!$C$8:$C$11,0)), _xlpm.subplan, INDEX(ModelDrivers!$E$8:$E$11, MATCH($B113,ModelDrivers!$C$8:$C$11,0)), _xlpm.return, (_xlpm.cumilative * _xlpm.subplan) * _xlpm.price, _xlpm.return ) -> 906541.52 | K114: =_xlfn.LET(_xlpm.cumilative, K$109, _xlpm.price, INDEX(ModelDrivers!$D$8:$D$11, MATCH($B113,ModelDrivers!$C$8:$C$11,0)), _xlpm.subplan, INDEX(ModelDrivers!$E$8:$E$11, MATCH($B113,ModelDrivers!$C$8:$C$11,0)), _xlpm.return, (_xlpm.cumilative * _xlpm.subplan) * _xlpm.price, _xlpm.return ) -> 1055323.6 | ... O114: =_xlfn.LET(_xlpm.cumilative, O$109, _xlpm.price, INDEX(ModelDrivers!$D$8:$D$11, MATCH($B113,ModelDrivers!$C$8:$C$11,0)), _xlpm.subplan, INDEX(ModelDrivers!$E$8:$E$11, MATCH($B113,ModelDrivers!$C$8:$C$11,0)), _xlpm.return, (_xlpm.cumilative * _xlpm.subplan) * _xlpm.price, _xlpm.return ) -> 1728656.4
B115: Plan C | C115: ="Revenue by Subscribers in " &B114 -> Revenue by Subscribers in Plan B | D115: =_xlfn.LET(_xlpm.cumilative, D$109, _xlpm.price, INDEX(ModelDrivers!$D$8:$D$11, MATCH($B114,ModelDrivers!$C$8:$C$11,0)), _xlpm.subplan, INDEX(ModelDrivers!$E$8:$E$11, MATCH($B114,ModelDrivers!$C$8:$C$11,0)), _xlpm.return, (_xlpm.cumilative * _xlpm.subplan) * _xlpm.price, _xlpm.return ) -> 46800 | E115: =_xlfn.LET(_xlpm.cumilative, E$109, _xlpm.price, INDEX(ModelDrivers!$D$8:$D$11, MATCH($B114,ModelDrivers!$C$8:$C$11,0)), _xlpm.subplan, INDEX(ModelDrivers!$E$8:$E$11, MATCH($B114,ModelDrivers!$C$8:$C$11,0)), _xlpm.return, (_xlpm.cumilative * _xlpm.subplan) * _xlpm.price, _xlpm.return ) -> 104292 | F115: =_xlfn.LET(_xlpm.cumilative, F$109, _xlpm.price, INDEX(ModelDrivers!$D$8:$D$11, MATCH($B114,ModelDrivers!$C$8:$C$11,0)), _xlpm.subplan, INDEX(ModelDrivers!$E$8:$E$11, MATCH($B114,ModelDrivers!$C$8:$C$11,0)), _xlpm.return, (_xlpm.cumilative * _xlpm.subplan) * _xlpm.price, _xlpm.return ) -> 200772 | G115: =_xlfn.LET(_xlpm.cumilative, G$109, _xlpm.price, INDEX(ModelDrivers!$D$8:$D$11, MATCH($B114,ModelDrivers!$C$8:$C$11,0)), _xlpm.subplan, INDEX(ModelDrivers!$E$8:$E$11, MATCH($B114,ModelDrivers!$C$8:$C$11,0)), _xlpm.return, (_xlpm.cumilative * _xlpm.subplan) * _xlpm.price, _xlpm.return ) -> 287748 | H115: =_xlfn.LET(_xlpm.cumilative, H$109, _xlpm.price, INDEX(ModelDrivers!$D$8:$D$11, MATCH($B114,ModelDrivers!$C$8:$C$11,0)), _xlpm.subplan, INDEX(ModelDrivers!$E$8:$E$11, MATCH($B114,ModelDrivers!$C$8:$C$11,0)), _xlpm.return, (_xlpm.cumilative * _xlpm.subplan) * _xlpm.price, _xlpm.return ) -> 372999.6 | I115: =_xlfn.LET(_xlpm.cumilative, I$109, _xlpm.price, INDEX(ModelDrivers!$D$8:$D$11, MATCH($B114,ModelDrivers!$C$8:$C$11,0)), _xlpm.subplan, INDEX(ModelDrivers!$E$8:$E$11, MATCH($B114,ModelDrivers!$C$8:$C$11,0)), _xlpm.return, (_xlpm.cumilative * _xlpm.subplan) * _xlpm.price, _xlpm.return ) -> 458906.58 | J115: =_xlfn.LET(_xlpm.cumilative, J$109, _xlpm.price, INDEX(ModelDrivers!$D$8:$D$11, MATCH($B114,ModelDrivers!$C$8:$C$11,0)), _xlpm.subplan, INDEX(ModelDrivers!$E$8:$E$11, MATCH($B114,ModelDrivers!$C$8:$C$11,0)), _xlpm.return, (_xlpm.cumilative * _xlpm.subplan) * _xlpm.price, _xlpm.return ) -> 543924.91 | K115: =_xlfn.LET(_xlpm.cumilative, K$109, _xlpm.price, INDEX(ModelDrivers!$D$8:$D$11, MATCH($B114,ModelDrivers!$C$8:$C$11,0)), _xlpm.subplan, INDEX(ModelDrivers!$E$8:$E$11, MATCH($B114,ModelDrivers!$C$8:$C$11,0)), _xlpm.return, (_xlpm.cumilative * _xlpm.subplan) * _xlpm.price, _xlpm.return ) -> 633194.15 | ... O115: =_xlfn.LET(_xlpm.cumilative, O$109, _xlpm.price, INDEX(ModelDrivers!$D$8:$D$11, MATCH($B114,ModelDrivers!$C$8:$C$11,0)), _xlpm.subplan, INDEX(ModelDrivers!$E$8:$E$11, MATCH($B114,ModelDrivers!$C$8:$C$11,0)), _xlpm.return, (_xlpm.cumilative * _xlpm.subplan) * _xlpm.price, _xlpm.return ) -> 1037193.8
C116: ="Revenue by Subscribers in " &B115 -> Revenue by Subscribers in Plan C | D116: =_xlfn.LET(_xlpm.cumilative, D$109, _xlpm.price, INDEX(ModelDrivers!$D$8:$D$11, MATCH($B115,ModelDrivers!$C$8:$C$11,0)), _xlpm.subplan, INDEX(ModelDrivers!$E$8:$E$11, MATCH($B115,ModelDrivers!$C$8:$C$11,0)), _xlpm.return, (_xlpm.cumilative * _xlpm.subplan) * _xlpm.price, _xlpm.return ) -> 18200 | E116: =_xlfn.LET(_xlpm.cumilative, E$109, _xlpm.price, INDEX(ModelDrivers!$D$8:$D$11, MATCH($B115,ModelDrivers!$C$8:$C$11,0)), _xlpm.subplan, INDEX(ModelDrivers!$E$8:$E$11, MATCH($B115,ModelDrivers!$C$8:$C$11,0)), _xlpm.return, (_xlpm.cumilative * _xlpm.subplan) * _xlpm.price, _xlpm.return ) -> 40558 | F116: =_xlfn.LET(_xlpm.cumilative, F$109, _xlpm.price, INDEX(ModelDrivers!$D$8:$D$11, MATCH($B115,ModelDrivers!$C$8:$C$11,0)), _xlpm.subplan, INDEX(ModelDrivers!$E$8:$E$11, MATCH($B115,ModelDrivers!$C$8:$C$11,0)), _xlpm.return, (_xlpm.cumilative * _xlpm.subplan) * _xlpm.price, _xlpm.return ) -> 78078 | G116: =_xlfn.LET(_xlpm.cumilative, G$109, _xlpm.price, INDEX(ModelDrivers!$D$8:$D$11, MATCH($B115,ModelDrivers!$C$8:$C$11,0)), _xlpm.subplan, INDEX(ModelDrivers!$E$8:$E$11, MATCH($B115,ModelDrivers!$C$8:$C$11,0)), _xlpm.return, (_xlpm.cumilative * _xlpm.subplan) * _xlpm.price, _xlpm.return ) -> 111902 | H116: =_xlfn.LET(_xlpm.cumilative, H$109, _xlpm.price, INDEX(ModelDrivers!$D$8:$D$11, MATCH($B115,ModelDrivers!$C$8:$C$11,0)), _xlpm.subplan, INDEX(ModelDrivers!$E$8:$E$11, MATCH($B115,ModelDrivers!$C$8:$C$11,0)), _xlpm.return, (_xlpm.cumilative * _xlpm.subplan) * _xlpm.price, _xlpm.return ) -> 145055.4 | I116: =_xlfn.LET(_xlpm.cumilative, I$109, _xlpm.price, INDEX(ModelDrivers!$D$8:$D$11, MATCH($B115,ModelDrivers!$C$8:$C$11,0)), _xlpm.subplan, INDEX(ModelDrivers!$E$8:$E$11, MATCH($B115,ModelDrivers!$C$8:$C$11,0)), _xlpm.return, (_xlpm.cumilative * _xlpm.subplan) * _xlpm.price, _xlpm.return ) -> 178463.67 | J116: =_xlfn.LET(_xlpm.cumilative, J$109, _xlpm.price, INDEX(ModelDrivers!$D$8:$D$11, MATCH($B115,ModelDrivers!$C$8:$C$11,0)), _xlpm.subplan, INDEX(ModelDrivers!$E$8:$E$11, MATCH($B115,ModelDrivers!$C$8:$C$11,0)), _xlpm.return, (_xlpm.cumilative * _xlpm.subplan) * _xlpm.price, _xlpm.return ) -> 211526.35 | K116: =_xlfn.LET(_xlpm.cumilative, K$109, _xlpm.price, INDEX(ModelDrivers!$D$8:$D$11, MATCH($B115,ModelDrivers!$C$8:$C$11,0)), _xlpm.subplan, INDEX(ModelDrivers!$E$8:$E$11, MATCH($B115,ModelDrivers!$C$8:$C$11,0)), _xlpm.return, (_xlpm.cumilative * _xlpm.subplan) * _xlpm.price, _xlpm.return ) -> 246242.17 | ... O116: =_xlfn.LET(_xlpm.cumilative, O$109, _xlpm.price, INDEX(ModelDrivers!$D$8:$D$11, MATCH($B115,ModelDrivers!$C$8:$C$11,0)), _xlpm.subplan, INDEX(ModelDrivers!$E$8:$E$11, MATCH($B115,ModelDrivers!$C$8:$C$11,0)), _xlpm.return, (_xlpm.cumilative * _xlpm.subplan) * _xlpm.price, _xlpm.return ) -> 403353.16
C118: Total Subscription Revenue | D118: =SUM(D114:D116) -> 143000 | E118: =SUM(E114:E116) -> 318670 | F118: =SUM(F114:F116) -> 613470 | G118: =SUM(G114:G116) -> 879230 | H118: =SUM(H114:H116) -> 1139721 | I118: =SUM(I114:I116) -> 1402214.6 | J118: =SUM(J114:J116) -> 1661992.8 | K118: =SUM(K114:K116) -> 1934759.9 | ... O118: =SUM(O114:O116) -> 3169203.4
C119: % growth | E119: =E118/D118-1 -> 1.2284615 | F119: =F118/E118-1 -> 0.92509493 | G119: =G118/F118-1 -> 0.43320782 | H119: =H118/G118-1 -> 0.29627174 | I119: =I118/H118-1 -> 0.23031387 | J119: =J118/I118-1 -> 0.18526282 | K119: =K118/J118-1 -> 0.16412053 | L119: =L118/K118-1 -> 0.14803154 | ... O119: =O118/N118-1 -> 0.11683956
C122: 12 Month P&L Statement - 12 month Cash Budget
C123: Yr | D123: 1 | E123: =D123+1 -> 2 | F123: =E123+1 -> 3 | G123: =F123+1 -> 4 | H123: =G123+1 -> 5 | I123: =H123+1 -> 6 | J123: =I123+1 -> 7 | K123: =J123+1 -> 8 | L123: =K123+1 -> 9 | ... O123: =N123+1 -> 12
C125: Days in Month | D125: 30 | E125: 30 | F125: 30 | G125: 30 | H125: 30 | I125: 30 | J125: 30 | K125: 30 | L125: 30 | M125: 30 | N125: 30 | O125: 30
C127: Revenues | D127: ='P&Lv2'!D118 -> 143000 | E127: =D127*(1+E129) -> 318670 | F127: =E127*(1+F129) -> 613470 | G127: =F127*(1+G129) -> 879230 | H127: =G127*(1+H129) -> 1139721 | I127: =H127*(1+I129) -> 1402214.6 | J127: =I127*(1+J129) -> 1661992.8 | K127: =J127*(1+K129) -> 1934759.9 | L127: =K127*(1+L129) -> 2221165.4 | ... O127: =N127*(1+O129) -> 3169203.4
C129: Revenue Growth | E129: ='P&Lv2'!E119 -> 1.2284615 | F129: ='P&Lv2'!F119 -> 0.92509493 | G129: ='P&Lv2'!G119 -> 0.43320782 | H129: ='P&Lv2'!H119 -> 0.29627174 | I129: ='P&Lv2'!I119 -> 0.23031387 | J129: ='P&Lv2'!J119 -> 0.18526282 | K129: ='P&Lv2'!K119 -> 0.16412053 | L129: ='P&Lv2'!L119 -> 0.14803154 | ... O129: ='P&Lv2'!O119 -> 0.11683956
C131: Production Cost | D131: =ModelDrivers!D31 -> 3250 | E131: =E127*E141 -> 7242.5 | F131: =F127*F141 -> 13942.5 | G131: =G127*G141 -> 19982.5 | H131: =H127*H141 -> 25902.75 | I131: =I127*I141 -> 31868.513 | J131: =J127*J141 -> 37772.563 | K131: =K127*K141 -> 43971.816 | L131: =L127*L141 -> 50481.032 | ... O131: =O127*O141 -> 72027.35 | P131: x
C132: Salary | D132: ='Head Count'!H12 -> 60000 | E132: ='Head Count'!I12 -> 70000 | F132: ='Head Count'!J12 -> 70000 | G132: ='Head Count'!K12 -> 160000 | H132: ='Head Count'!L12 -> 160000 | I132: ='Head Count'!M12 -> 180000 | J132: ='Head Count'!N12 -> 270000 | K132: ='Head Count'!O12 -> 276000 | ... O132: ='Head Count'!S12 -> 368000
C133: Labor | D133: =D125*ModelDrivers!$J$31 -> 65967.6 | E133: =D133*E142 -> 30431.638 | F133: =E133*F142 -> 14038.476 | G133: =F133*G142 -> 6476.1161 | H133: =G133*H142 -> 2987.5093 | I133: =H133*I142 -> 1378.1736 | J133: =I133*J142 -> 635.76785 | K133: =J133*K142 -> 293.28727 | L133: =K133*L142 -> 135.2969 | ... O133: =N133*O142 -> 13.282254
C134: Fixed Costs | D134: =ModelDrivers!D31 -> 3250 | E134: =D134 -> 3250 | F134: =E134 -> 3250 | G134: =F134 -> 3250 | H134: =G134 -> 3250 | I134: =H134 -> 3250 | J134: =I134 -> 3250 | K134: =J134 -> 3250 | L134: =K134 -> 3250 | ... O134: =N134 -> 3250
C135: COGS | D135: =SUM(D131:D134) -> 132467.6 | E135: =SUM(E131:E134) -> 110924.14 | F135: =SUM(F131:F134) -> 101230.98 | G135: =SUM(G131:G134) -> 189708.62 | H135: =SUM(H131:H134) -> 192140.26 | I135: =SUM(I131:I134) -> 216496.69 | J135: =SUM(J131:J134) -> 311658.33 | K135: =SUM(K131:K134) -> 323515.1 | ... O135: =SUM(O131:O134) -> 443290.63
C136: Gross Profit | D136: =D127-D135 -> 10532.4 | E136: =E127-E135 -> 207745.86 | F136: =F127-F135 -> 512239.02 | G136: =G127-G135 -> 689521.38 | H136: =H127-H135 -> 947580.74 | I136: =I127-I135 -> 1185717.9 | J136: =J127-J135 -> 1350334.4 | K136: =K127-K135 -> 1611244.8 | ... O136: =O127-O135 -> 2725912.8
D138: =((D127-D135) / D127) -> 0.073653147 | E138: =((E127-E135) / E127) -> 0.65191534 | F138: =((F127-F135) / F127) -> 0.83498626 | G138: =((G127-G135) / G127) -> 0.78423323 | H138: =((H127-H135) / H127) -> 0.83141465 | I138: =((I127-I135) / I127) -> 0.84560374 | J138: =((J127-J135) / J127) -> 0.81247913 | K138: =((K127-K135) / K127) -> 0.83278799 | ... O138: =((O127-O135) / O127) -> 0.86012553
D140: Common Size
C141: Production Cost | D141: =D131/D127 -> 0.022727273 | E141: =D141 -> 0.022727273 | F141: =E141 -> 0.022727273 | G141: =F141 -> 0.022727273 | H141: =G141 -> 0.022727273 | I141: =H141 -> 0.022727273 | J141: =I141 -> 0.022727273 | K141: =J141 -> 0.022727273 | L141: =K141 -> 0.022727273 | ... O141: =N141 -> 0.022727273
C142: Labor | D142: =D133/D127 -> 0.46131189 | E142: =D142 -> 0.46131189 | F142: =E142 -> 0.46131189 | G142: =F142 -> 0.46131189 | H142: =G142 -> 0.46131189 | I142: =H142 -> 0.46131189 | J142: =I142 -> 0.46131189 | K142: =J142 -> 0.46131189 | L142: =K142 -> 0.46131189 | ... O142: =N142 -> 0.46131189

Sheet P&L
B2: x | C2: ="Financial Statement Model for "&D5 -> Financial Statement Model for Apple
C3: $ mm except per share
C5: Company name | D5: Apple
C6: Ticker | D6: AAPL
C7: Circ break 1=off, 0=on | D7: 1
C8: Latest closing share price date | D8: 43500
C9: Latest fiscal year end date | D9: 45198
C10: Select an operating scenario: | D10: Base case
B14: x | C14: INCOME STATEMENT | O14: x
C15: Fiscal year | D15: =E15-1 -> 2021 | E15: =F15-1 -> 2022 | F15: =YEAR(D9) -> 2023 | G15: =F15+1 -> 2024 | H15: =G15+1 -> 2025 | I15: =H15+1 -> 2026 | J15: =I15+1 -> 2027 | K15: =J15+1 -> 2028 | L15: =K15+1 -> 2029 | M15: =L15+1 -> 2030
C16: Fiscal year end date | D16: =EOMONTH(E16,-12) -> 44469 | E16: =EOMONTH(F16,-12) -> 44834 | F16: =D9 -> 45198 | G16: =EOMONTH(F16,12) -> 45565 | H16: =EOMONTH(G16,12) -> 45930 | I16: =EOMONTH(H16,12) -> 46295 | J16: =EOMONTH(I16,12) -> 46660 | K16: =EOMONTH(J16,12) -> 47026 | L16: =EOMONTH(K16,12) -> 47391 | M16: =EOMONTH(L16,12) -> 47756 | P16: WSP Comments
C18: Revenue | D18: 215639 | E18: 229234 | F18: 265595 | G18: =F18*(1+G37) -> 265595 | H18: =G18*(1+H37) -> 265595 | I18: =H18*(1+I37) -> 265595 | J18: =I18*(1+J37) -> 265595 | K18: =J18*(1+K37) -> 265595 | L18: =K18*(1+L37) -> 265595 | M18: =L18*(1+M37) -> 265595 | P18: Previous year's revenues x (1+revenue growth rate)
C19: Cost of sales (enter as -) | D19: -131376 | E19: -141048 | F19: -163756 | G19: =G20-G18 -> -265595 | H19: =H20-H18 -> -265595 | I19: =I20-I18 -> -265595 | J19: =J20-J18 -> -265595 | K19: =K20-K18 -> -265595 | L19: =L20-L18 -> -265595 | M19: =M20-M18 -> -265595 | P19: Plug = Revenue - Gross Profit
C20: Gross Profit | D20: =SUM(D18:D19) -> 84263 | E20: =SUM(E18:E19) -> 88186 | F20: =SUM(F18:F19) -> 101839 | G20: =G18*G38 -> 0 | H20: =H18*H38 -> 0 | I20: =I18*I38 -> 0 | J20: =J18*J38 -> 0 | K20: =K18*K38 -> 0 | L20: =L18*L38 -> 0 | M20: =M18*M38 -> 0 | P20: Revenue x Gross Profit Margin forecast
C21: Research & development (enter as -) | D21: -10045 | E21: -11581 | F21: -14236 | G21: =-G39*G18 -> 0 | H21: =-H39*H18 -> 0 | I21: =-I39*I18 -> 0 | J21: =-J39*J18 -> 0 | K21: =-K39*K18 -> 0 | L21: =-L39*L18 -> 0 | M21: =-M39*M18 -> 0 | P21: Revenue x R&D % of sales forecast
C22: Selling, general & administrative (enter as -) | D22: -14194 | E22: -15261 | F22: -16705 | G22: =-G18*G40 -> 0 | H22: =-H18*H40 -> 0 | I22: =-I18*I40 -> 0 | J22: =-J18*J40 -> 0 | K22: =-K18*K40 -> 0 | L22: =-L18*L40 -> 0 | M22: =-M18*M40 -> 0 | P22: Revenue x SG&A % of sales forecast
C23: Operating profit (EBIT) | D23: =D20+D21+D22 -> 60024 | E23: =E20+E21+E22 -> 61344 | F23: =F20+F21+F22 -> 70898 | G23: =G20+G21+G22 -> 0 | H23: =H20+H21+H22 -> 0 | I23: =I20+I21+I22 -> 0 | J23: =J20+J21+J22 -> 0 | K23: =K20+K21+K22 -> 0 | ... M23: =M20+M21+M22 -> 0 | P23: Gross Profit - R&D - SG&A
C24: Interest income | D24: 3999 | E24: 5201 | F24: 5686 | G24: =G157 -> 0 | H24: =H157 -> 0 | I24: =I157 -> 0 | J24: =J157 -> 0 | K24: =K157 -> 0 | L24: =L157 -> 0 | M24: =M157 -> 0 | P24: Reference from interest on cash schedule
C25: Interest expense (enter as -) | D25: -1456 | E25: -2323 | F25: -3240 | G25: =-G143 -> 0 | H25: =-H143 -> 0 | I25: =-I143 -> 0 | J25: =-J143 -> 0 | K25: =-K143 -> 0 | L25: =-L143 -> 0 | M25: =-M143 -> 0 | P25: Reference from interest expense schedule
C26: Other expense, net (enter as -) | D26: -1195 | E26: -133 | F26: -441 | G26: =F26 -> -441 | H26: =G26 -> -441 | I26: =H26 -> -441 | J26: =I26 -> -441 | K26: =J26 -> -441 | L26: =K26 -> -441 | M26: =L26 -> -441 | P26: Straight-line
C27: Pretax profit | D27: =SUM(D23:D26) -> 61372 | E27: =SUM(E23:E26) -> 64089 | F27: =SUM(F23:F26) -> 72903 | G27: =SUM(G23:G26) -> -441 | H27: =SUM(H23:H26) -> -441 | I27: =SUM(I23:I26) -> -441 | J27: =SUM(J23:J26) -> -441 | K27: =SUM(K23:K26) -> -441 | ... M27: =SUM(M23:M26) -> -441 | P27: EBIT + interest income less interest expense less other expense
C28: Taxes (enter expense as -) | D28: -15685 | E28: -15738 | F28: -13372 | G28: =-G41*G27 -> 73.647 | H28: =-H41*H27 -> 74.97 | I28: =-I41*I27 -> 74.529 | J28: =-J41*J27 -> 74.529 | K28: =-K41*K27 -> 74.529 | L28: =-L41*L27 -> 74.529 | M28: =-M41*M27 -> 74.529 | P28: Pre-tax Profit x Tax Rate forecast
C29: Net income | D29: =SUM(D27:D28) -> 45687 | E29: =SUM(E27:E28) -> 48351 | F29: =SUM(F27:F28) -> 59531 | G29: =SUM(G27:G28) -> -367.353 | H29: =SUM(H27:H28) -> -366.03 | I29: =SUM(I27:I28) -> -366.471 | J29: =SUM(J27:J28) -> -366.471 | K29: =SUM(K27:K28) -> -366.471 | ... M29: =SUM(M27:M28) -> -366.471 | P29: Pre-tax Profit less taxes
C31: Depreciation & amortization | D31: 10505 | E31: 10157 | F31: 10903 | G31: =G107 -> 0 | H31: =H107 -> 0 | I31: =I107 -> 0 | J31: =J107 -> 0 | K31: =K107 -> 0 | L31: =L107 -> 0 | M31: =M107 -> 0 | P31: Reference from D&A schedule
C32: EBITDA | D32: =D23+D31 -> 70529 | E32: =E23+E31 -> 71501 | F32: =F23+F31 -> 81801 | G32: =G23+G31 -> 0 | H32: =H23+H31 -> 0 | I32: =I23+I31 -> 0 | J32: =J23+J31 -> 0 | K32: =K23+K31 -> 0 | ... M32: =M23+M31 -> 0 | P32: EBIT + D&A
C33: Stock based compensation | D33: 4210 | E33: 4840 | F33: 5340 | G33: =F33*(1+G37) -> 5340 | H33: =G33*(1+H37) -> 5340 | I33: =H33*(1+I37) -> 5340 | J33: =I33*(1+J37) -> 5340 | K33: =J33*(1+K37) -> 5340 | L33: =K33*(1+L37) -> 5340 | M33: =L33*(1+M37) -> 5340 | P33: WSP assumption: grow SBC in-line with revenue growth
C34: Adjusted EBITDA | D34: =SUM(D32:D33) -> 74739 | E34: =SUM(E32:E33) -> 76341 | F34: =SUM(F32:F33) -> 87141 | G34: =SUM(G32:G33) -> 5340 | H34: =SUM(H32:H33) -> 5340 | I34: =SUM(I32:I33) -> 5340 | J34: =SUM(J32:J33) -> 5340 | K34: =SUM(K32:K33) -> 5340 | ... M34: =SUM(M32:M33) -> 5340 | P34: EBITDA + Stock-based compensation
C36: Growth rates & margins
C37: Revenue growth | E37: =E18/D18-1 -> 0.063045182 | F37: =F18/E18-1 -> 0.15861958 | G37: =G175 -> 0 | H37: =H175 -> 0 | I37: =I175 -> 0 | J37: =J175 -> 0 | K37: =K175 -> 0 | L37: =L175 -> 0 | M37: =M175 -> 0 | P37: From scenario analysis below
C38: Gross profit margin | D38: =D20/D18 -> 0.39075956 | E38: =E20/E18 -> 0.3846986 | F38: =F20/F18 -> 0.38343719 | G38: =G176 -> 0 | H38: =H176 -> 0 | I38: =I176 -> 0 | J38: =J176 -> 0 | K38: =K176 -> 0 | L38: =L176 -> 0 | M38: =M176 -> 0 | P38: From scenario analysis below
C39: R&D % of sales | D39: =-D21/D18 -> 0.046582483 | E39: =-E21/E18 -> 0.050520429 | F39: =-F21/F18 -> 0.053600407 | G39: =G177 -> 0 | H39: =H177 -> 0 | I39: =I177 -> 0 | J39: =J177 -> 0 | K39: =K177 -> 0 | L39: =L177 -> 0 | M39: =M177 -> 0 | P39: From scenario analysis below
C40: SG&A % of sales | D40: =-D22/D18 -> 0.065822973 | E40: =-E22/E18 -> 0.066573894 | F40: =-F22/F18 -> 0.062896515 | G40: =G178 -> 0 | H40: =H178 -> 0 | I40: =I178 -> 0 | J40: =J178 -> 0 | K40: =K178 -> 0 | L40: =L178 -> 0 | M40: =M178 -> 0 | P40: From scenario analysis below
C41: Tax rate | D41: =-(D28/D27) -> 0.25557257 | E41: =-(E28/E27) -> 0.24556476 | F41: =-(F28/F27) -> 0.18342181 | G41: 0.167 | H41: 0.17 | I41: 0.169 | J41: =I41 -> 0.169 | K41: =J41 -> 0.169 | L41: =K41 -> 0.169 | M41: =L41 -> 0.169 | P41: JP Morgan estimates through 2021: straight-line margin thereafter

Sheet Sheet1
B7: FQ
C9: Ticker | D9: Share Price | E9: Shares Outstanding | F9: Equity Value | G9: Net Debt | H9: Enterprise Value | J9: Total Revenue | K9: EBITDA | L9: Net Income | N9: EV/Revenue | O9: EV/EBITDA | P9: P/E
B10: TVS Motor Company | C10: BOM: 532343 | D10: {=_xll.PBF($C10,"Close Price",$B$7,"16-Jul-2025","","USD","","")} -> 33.698399 | E10: {=_xll.PBF($C10,"Common Shares Outstanding",$B$7,"16-Jul-2025","","USD","","")/10^6} -> 474.73611 | F10: =D10*E10 -> 15997.847 | G10: {=_xll.PBF($C10,"Net Debt",$B$7,"16-Jul-2025","","USD","","")/10^6} -> 2733.3869 | H10: =G10+F10 -> 18731.234 | J10: {=_xll.PBF($C10,"Total Revenue","FQ","16-Jul-2025","","USD","","")/10^6} -> 1298.257 | K10: {=_xll.PBF($C10,"EBITDA",$B$7,"16-Jul-2025","","USD","","")/10^6} -> 206.85132 | L10: {=_xll.PBF($C10,"Net Income (Normalized)",$B$7,"16-Jul-2025","","USD","","")/10^6} -> 77.069954 | N10: =$H10/J10 -> 14.427986 | O10: =$H10/K10 -> 90.554093
B11: Chijet Motor Company | C11: NAS: CJET | D11: {=_xll.PBF($C11,"Close Price",$B$7,"16-Jul-2025","","USD","","")} -> 2.785 | E11: {=_xll.PBF($C11,"Common Shares Outstanding",$B$7,"16-Jul-2025","","USD","","")/10^6} -> #N/A | F11: =D11*E11 -> #N/A | G11: {=_xll.PBF($C11,"Net Debt",$B$7,"16-Jul-2025","","USD","","")/10^6} -> #N/A | H11: =G11+F11 -> #N/A | J11: {=_xll.PBF($C11,"Total Revenue","FQ","16-Jul-2025","","USD","","")/10^6} -> #N/A | K11: {=_xll.PBF($C11,"EBITDA",$B$7,"16-Jul-2025","","USD","","")/10^6} -> #N/A | L11: {=_xll.PBF($C11,"Net Income (Normalized)",$B$7,"16-Jul-2025","","USD","","")/10^6} -> #N/A | N11: =$H11/J11 -> #N/A | O11: =$H11/K11 -> #N/A
B12: Volkswagen Group | C12: ETR: VOW3 | D12: {=_xll.PBF($C12,"Close Price",$B$7,"16-Jul-2025","","USD","","")} -> 109.11891 | E12: {=_xll.PBF($C12,"Common Shares Outstanding",$B$7,"16-Jul-2025","","USD","","")/10^6} -> 501.29526 | F12: =D12*E12 -> 54700.791 | G12: {=_xll.PBF($C12,"Net Debt",$B$7,"16-Jul-2025","","USD","","")/10^6} -> 136068.75 | H12: =G12+F12 -> 190769.54 | J12: {=_xll.PBF($C12,"Total Revenue","FQ","16-Jul-2025","","USD","","")/10^6} -> 81572.36 | K12: {=_xll.PBF($C12,"EBITDA",$B$7,"16-Jul-2025","","USD","","")/10^6} -> 11349.39 | L12: {=_xll.PBF($C12,"Net Income (Normalized)",$B$7,"16-Jul-2025","","USD","","")/10^6} -> 2594.918 | N12: =$H12/J12 -> 2.3386542 | O12: =$H12/K12 -> 16.808792
B13: Cenntro | C13: NAS: CENN | D13: {=_xll.PBF($C13,"Close Price",$B$7,"16-Jul-2025","","USD","","")} -> 0.646 | E13: {=_xll.PBF($C13,"Common Shares Outstanding",$B$7,"16-Jul-2025","","USD","","")/10^6} -> 30.866614 | F13: =D13*E13 -> 19.939833 | G13: {=_xll.PBF($C13,"Net Debt",$B$7,"16-Jul-2025","","USD","","")/10^6} -> 13.606323 | H13: =G13+F13 -> 33.546156 | J13: {=_xll.PBF($C13,"Total Revenue","FQ","16-Jul-2025","","USD","","")/10^6} -> 2.143058 | K13: {=_xll.PBF($C13,"EBITDA",$B$7,"16-Jul-2025","","USD","","")/10^6} -> -4.70491 | L13: {=_xll.PBF($C13,"Net Income (Normalized)",$B$7,"16-Jul-2025","","USD","","")/10^6} -> -5.6164366 | N13: =$H13/J13 -> 15.653405 | O13: =$H13/K13 -> -7.1300313
B14: Mullen Automotive | C14: NAS: MULN | D14: {=_xll.PBF($C14,"Close Price",$B$7,"16-Jul-2025","","USD","","")} -> 0.1114 | E14: {=_xll.PBF($C14,"Common Shares Outstanding",$B$7,"16-Jul-2025","","USD","","")/10^6} -> 0.010205 | F14: =D14*E14 -> 0.001136837 | G14: {=_xll.PBF($C14,"Net Debt",$B$7,"16-Jul-2025","","USD","","")/10^6} -> 23.775418 | H14: =G14+F14 -> 23.776555 | J14: {=_xll.PBF($C14,"Total Revenue","FQ","16-Jul-2025","","USD","","")/10^6} -> 4.95014 | K14: {=_xll.PBF($C14,"EBITDA",$B$7,"16-Jul-2025","","USD","","")/10^6} -> -41.553772 | L14: {=_xll.PBF($C14,"Net Income (Normalized)",$B$7,"16-Jul-2025","","USD","","")/10^6} -> -40.991525 | N14: =$H14/J14 -> 4.8032086 | O14: =$H14/K14 -> -0.57218764
B15: BYD Company | C15: SHE: 002594 | D15: {=_xll.PBF($C15,"Close Price",$B$7,"16-Jul-2025","","USD","","")} -> 45.129721 | E15: {=_xll.PBF($C15,"Common Shares Outstanding",$B$7,"16-Jul-2025","","USD","","")/10^6} -> 5494.6659 | F15: =D15*E15 -> 247972.74 | G15: {=_xll.PBF($C15,"Net Debt",$B$7,"16-Jul-2025","","USD","","")/10^6} -> -15455.131 | H15: =G15+F15 -> 232517.6 | J15: {=_xll.PBF($C15,"Total Revenue","FQ","16-Jul-2025","","USD","","")/10^6} -> 23415.731 | K15: {=_xll.PBF($C15,"EBITDA",$B$7,"16-Jul-2025","","USD","","")/10^6} -> 1541.9462 | L15: {=_xll.PBF($C15,"Net Income (Normalized)",$B$7,"16-Jul-2025","","USD","","")/10^6} -> 1123.1751 | N15: =$H15/J15 -> 9.9299742 | O15: =$H15/K15 -> 150.79489
B16: Nu Ride | C16: PINX: NRDE | D16: {=_xll.PBF($C16,"Close Price",$B$7,"16-Jul-2025","","USD","","")} -> 1.45 | E16: {=_xll.PBF($C16,"Common Shares Outstanding",$B$7,"16-Jul-2025","","USD","","")/10^6} -> 16.096296 | F16: =D16*E16 -> 23.339629 | G16: {=_xll.PBF($C16,"Net Debt",$B$7,"16-Jul-2025","","USD","","")/10^6} -> -28.04 | H16: =G16+F16 -> -4.7003708 | J16: {=_xll.PBF($C16,"Total Revenue","FQ","16-Jul-2025","","USD","","")/10^6} -> 0 | K16: {=_xll.PBF($C16,"EBITDA",$B$7,"16-Jul-2025","","USD","","")/10^6} -> -1.211 | L16: {=_xll.PBF($C16,"Net Income (Normalized)",$B$7,"16-Jul-2025","","USD","","")/10^6} -> -1.504 | N16: =$H16/J16 -> #DIV/0! | O16: =$H16/K16 -> 3.8813962
B17: Carbon Revolution | C17: NAS: CREV | D17: {=_xll.PBF($C17,"Close Price",$B$7,"16-Jul-2025","","USD","","")} -> 4.93 | E17: {=_xll.PBF($C17,"Common Shares Outstanding",$B$7,"16-Jul-2025","","USD","","")/10^6} -> #N/A | F17: =D17*E17 -> #N/A | G17: {=_xll.PBF($C17,"Net Debt",$B$7,"16-Jul-2025","","USD","","")/10^6} -> #N/A | H17: =G17+F17 -> #N/A | J17: {=_xll.PBF($C17,"Total Revenue","FQ","16-Jul-2025","","USD","","")/10^6} -> #N/A | K17: {=_xll.PBF($C17,"EBITDA",$B$7,"16-Jul-2025","","USD","","")/10^6} -> #N/A | L17: {=_xll.PBF($C17,"Net Income (Normalized)",$B$7,"16-Jul-2025","","USD","","")/10^6} -> #N/A | N17: =$H17/J17 -> #N/A | O17: =$H17/K17 -> #N/A
B18: Nikola | C18: PINX: NKLAQ | D18: {=_xll.PBF($C18,"Close Price",$B$7,"16-Jul-2025","","USD","","")} -> 0.0684 | E18: {=_xll.PBF($C18,"Common Shares Outstanding",$B$7,"16-Jul-2025","","USD","","")/10^6} -> #N/A | F18: =D18*E18 -> #N/A | G18: {=_xll.PBF($C18,"Net Debt",$B$7,"16-Jul-2025","","USD","","")/10^6} -> #N/A | H18: =G18+F18 -> #N/A | J18: {=_xll.PBF($C18,"Total Revenue","FQ","16-Jul-2025","","USD","","")/10^6} -> #N/A | K18: {=_xll.PBF($C18,"EBITDA",$B$7,"16-Jul-2025","","USD","","")/10^6} -> #N/A | L18: {=_xll.PBF($C18,"Net Income (Normalized)",$B$7,"16-Jul-2025","","USD","","")/10^6} -> #N/A | N18: =$H18/J18 -> #N/A | O18: =$H18/K18 -> #N/A
B19: Gogoro | C19: NAS: GGR | D19: {=_xll.PBF($C19,"Close Price",$B$7,"16-Jul-2025","","USD","","")} -> 0.3292 | E19: {=_xll.PBF($C19,"Common Shares Outstanding",$B$7,"16-Jul-2025","","USD","","")/10^6} -> 295.35349 | F19: =D19*E19 -> 97.230369 | G19: {=_xll.PBF($C19,"Net Debt",$B$7,"16-Jul-2025","","USD","","")/10^6} -> 317.137 | H19: =G19+F19 -> 414.36737 | J19: {=_xll.PBF($C19,"Total Revenue","FQ","16-Jul-2025","","USD","","")/10^6} -> 63.621 | K19: {=_xll.PBF($C19,"EBITDA",$B$7,"16-Jul-2025","","USD","","")/10^6} -> 6.673 | L19: {=_xll.PBF($C19,"Net Income (Normalized)",$B$7,"16-Jul-2025","","USD","","")/10^6} -> -10.915 | N19: =$H19/J19 -> 6.5130597 | O19: =$H19/K19 -> 62.096114
